Workbook

Sheet Leia-me
A1: Controle tributário familiar — Simples Nacional / Fator R
A3: Como usar
A4: 1. Aba Parâmetros: confira alíquotas, CLT, dependentes e os 3 cenários de pró-labore.
A5: 2. Aba Notas: preencha o NOME de cada empresa (linha amarela) e o VALOR da nota mês a mês.
A6: 3. Aba Simulação: calcula automaticamente receita, Fator R (12 meses), anexo, DAS, INSS, IRRF, lucro isento e líquido familiar.
A7: 4. Aba Comparativo: resume o ano e mostra qual cenário fica mais barato.
A9: Cores
A10: Amarelo = campo editável (você preenche).
A11: Cinza = campo calculado (não editar).
A12: Verde = Anexo III (Fator R ≥ 28%).
A13: Vermelho claro = Anexo V (Fator R < 28%).
A15: Cenários de pró-labore
... A26: • Brasília (DF): ISS está embutido no DAS do Simples neste modelo (como no seu documento).

Sheet Parâmetros
A1: Parâmetros editáveis
A3: EMPRESA / REGIME
A4: Alíquota Anexo III (Fator R ≥ 28%) | B4: 0.06 | C4: ← amarelo = editável
A5: Alíquota Anexo V (Fator R < 28%) | B5: 0.155
A6: Meta Fator R | B6: 0.28
A7: INSS pró-labore (%) | B7: 0.11
A8: Teto INSS 2026 | B8: 8157.41
A9: Desconto simplificado IRRF mensal | B9: 607.2
A10: Dedução por dependente (mensal) | B10: 189.59
A12: PESSOA FÍSICA / FAMÍLIA
A13: CLT bruto mensal (você) | B13: 10000
A14: Nº dependentes (filhos) | B14: 2
A15: Dependentes alocados no CLT? (1=sim, 0=não) | B15: 1
A16: Meses de CLT em 2026 (ex.: 5 se começou em ago) | B16: 5
A18: CENÁRIOS DE PRÓ-LABORE
A19: C1 — Pró-labore fixo atual | B19: 4400
A20: C2 — Modo (deixar AUTOMATICO) | B20: AUTOMATICO
A21: C3 — Pró-labore fixo alternativo | B21: 7300
A22: Pró-labore mínimo (piso, ex. salário mínimo) | B22: 1518
A23: C2 — Início do ajuste automático (mês) | B23: 46266 | C23: Antes disso, C2 usa o pró-labore atual (histórico real)
A24: TABELA IRRF 2026 (referência — usada nas fórmulas)
A25: Faixa 1 teto (isento) | B25: 2428.8
A26: Faixa 2 teto | B26: 2826.65
A27: Faixa 3 teto | B27: 3751.05
A28: Faixa 4 teto | B28: 4664.68
A29: Deduzir faixa 2 (7,5%) | B29: 182.16
A30: Deduzir faixa 3 (15%) | B30: 394.16
A31: Deduzir faixa 4 (22,5%) | B31: 675.49
A32: Deduzir faixa 5 (27,5%) | B32: 908.73
A33: Redução: isenção até | B33: 5000
A34: Redução: teto parcial | B34: 7350
A35: Redução: constante | B35: 978.62
A36: Redução: coeficiente | B36: 0.133145
A38: Named ranges usados pela Simulação:
A39: Os valores desta aba alimentam as fórmulas das outras abas. Não renomeie as células B4:B22.

Sheet Notas
A1: Notas fiscais por empresa (preencha os nomes e valores)
A2: Campos amarelos são editáveis. O total mensal alimenta a aba Simulação e o Fator R.
A3: Preencha os nomes na linha 5 (amarelo). Cada coluna é uma empresa contratante; some até 5. Se a nota for menor, só altere o valor do mês.
A4: Mês | B4: Empresa 1 | C4: Empresa 2 | D4: Empresa 3 | E4: Empresa 4 | F4: Empresa 5 | G4: Total do mês
A5: Nome da empresa → | B5: Contrato atual (editar) | C5: Contrato novo (editar) | G5: ← digite os nomes aqui
A6: 45658 | B6: 15500 | C6: 0 | D6: 0 | E6: 0 | F6: 0 | G6: =SUM(B6:F6)
A7: 45689 | B7: 15500 | C7: 0 | D7: 0 | E7: 0 | F7: 0 | G7: =SUM(B7:F7)
A8: 45717 | B8: 15500 | C8: 0 | D8: 0 | E8: 0 | F8: 0 | G8: =SUM(B8:F8)
A9: 45748 | B9: 15500 | C9: 0 | D9: 0 | E9: 0 | F9: 0 | G9: =SUM(B9:F9)
A10: 45778 | B10: 15500 | C10: 0 | D10: 0 | E10: 0 | F10: 0 | G10: =SUM(B10:F10)
A11: 45809 | B11: 15500 | C11: 0 | D11: 0 | E11: 0 | F11: 0 | G11: =SUM(B11:F11)
A12: 45839 | B12: 15500 | C12: 0 | D12: 0 | E12: 0 | F12: 0 | G12: =SUM(B12:F12)
A13: 45870 | B13: 15500 | C13: 0 | D13: 0 | E13: 0 | F13: 0 | G13: =SUM(B13:F13)
A14: 45901 | B14: 15500 | C14: 0 | D14: 0 | E14: 0 | F14: 0 | G14: =SUM(B14:F14)
A15: 45931 | B15: 15500 | C15: 0 | D15: 0 | E15: 0 | F15: 0 | G15: =SUM(B15:F15)
A16: 45962 | B16: 15500 | C16: 0 | D16: 0 | E16: 0 | F16: 0 | G16: =SUM(B16:F16)
A17: 45992 | B17: 15500 | C17: 0 | D17: 0 | E17: 0 | F17: 0 | G17: =SUM(B17:F17)
... A41: 46722 | B41: 15500 | C41: 10500 | D41: 0 | E41: 0 | F41: 0 | G41: =SUM(B41:F41)
A43: Dica: os valores já vêm pré-preenchidos com R$ 15.500 (empresa 1) e, a partir de set/2026, + R$ 10.500 (empresa 2). Ajuste se a nota for um pouco menor.

Sheet Simulação
A1: Simulação mês a mês — DAS, Fator R, pró-labore, INSS, IRRF, lucro e líquido familiar
A2: Receita vem da aba Notas. Altere o valor da nota lá e o Fator R / pró-labore sugerido atualizam aqui.
C3: CENÁRIO 1 — Pró-labore atual (fixo) | K3: CENÁRIO 2 — Automático (mínimo p/ Fator R ≥ meta) | S3: CENÁRIO 3 — Pró-labore manual alternativo
A4: Mês | B4: Receita | C4: Pró-labore | D4: Fator R | E4: Anexo | F4: DAS | G4: INSS | H4: IRRF | I4: Lucro isento* | J4: Líquido familiar** | K4: Pró-labore | L4: Fator R | M4: Anexo | N4: DAS | O4: INSS | P4: IRRF | Q4: Lucro isento* | R4: Líquido familiar** | S4: Pró-labore | T4: Fator R | U4: Anexo | V4: DAS | W4: INSS | X4: IRRF | Y4: Lucro isento* | Z4: Líquido familiar**
A5: 45658 | B5: =Notas!G6 | C5: =Parâmetros!$B$19 | D5: =IF(B5=0,0,C5/B5) | E5: =IF(D5>=Parâmetros!$B$6,"III","V") | F5: =IF(E5="III",B5*Parâmetros!$B$4,B5*Parâmetros!$B$5) | G5: =MIN(C5,Parâmetros!$B$8)*Parâmetros!$B$7 | H5: =IF(C5<=Parâmetros!$B$33,0,MAX(0,(IF(MAX(0,C5-(MIN(C5,Parâmetros!$B$8)*Parâmetros!$B$7)-(IF(Parâmetros!$B$15=1,0,Parâmetros!$B$14)*Parâmetros!$B$10))<=Parâmetros!$B$25,0,IF(MAX(0,C5-(MIN(C5,Parâmetros!$B$8)*Parâmetros!$B$7)-(IF(Parâmetros!$B$15=1,0,Parâmetros!$B$14)*Parâmetros!$B$10))<=Parâmetros!$B$26,MAX(0,C5-(MIN(C5,Parâmetros!$B$8)*Parâmetros!$B$7)-(IF(Parâmetros!$B$15=1,0,Parâmetros!$B$14)*Parâmetros!$B$10))*0.075-Parâmetros!$B$29,IF(MAX(0,C5-(MIN(C5,Parâmetros!$B$8)*Parâmetros!$B$7)-(IF(Parâmetros!$B$15=1,0,Parâmetros!$B$14)*Parâmetros!$B$10))<=Parâmetros!$B$27,MAX(0,C5-(MIN(C5,Parâmetros!$B$8)*Parâmetros!$B$7)-(IF(Parâmetros!$B$15=1,0,Parâmetros!$B$14)*Parâmetros!$B$10))*0.15-Parâmetros!$B$30,IF(MAX(0,C5-(MIN(C5,Parâmetros!$B$8)*Parâmetros!$B$7)-(IF(Parâmetros!$B$15=1,0,Parâmetros!$B$14)*Parâmetros!$B$10))<=Parâmetros!$B$28,MAX(0,C5-(MIN(C5,Parâmetros!$B$8)*Parâmetros!$B$7)-(IF(Parâmetros!$B$15=1,0,Parâmetros!$B$14)*Parâmetros!$B$10))*0.225-Parâmetros!$B$31,MAX(0,C5-(MIN(C5,Parâmetros!$B$8)*Parâmetros!$B$7)-(IF(Parâmetros!$B$15=1,0,Parâmetros!$B$14)*Parâmetros!$B$10))*0.275-Parâmetros!$B$32)))))-IF(C5<=Parâmetros!$B$34,Parâmetros!$B$35-Parâmetros!$B$36*C5,0))) | I5: =MAX(0,B5-F5-C5) | J5: =B5-F5-G5-H5 | K5: =IF(A5<Parâmetros!$B$23,Parâmetros!$B$19,MAX(Parâmetros!$B$22,Parâmetros!$B$6*B5)) | L5: =IF(B5=0,0,K5/B5) | M5: =IF(L5>=Parâmetros!$B$6,"III","V") | N5: =IF(M5="III",B5*Parâmetros!$B$4,B5*Parâmetros!$B$5) | O5: =MIN(K5,Parâmetros!$B$8)*Parâmetros!$B$7 | P5: =IF(K5<=Parâmetros!$B$33,0,MAX(0,(IF(MAX(0,K5-(MIN(K5,Parâmetros!$B$8)*Parâmetros!$B$7)-(IF(Parâmetros!$B$15=1,0,Parâmetros!$B$14)*Parâmetros!$B$10))<=Parâmetros!$B$25,0,IF(MAX(0,K5-(MIN(K5,Parâmetros!$B$8)*Parâmetros!$B$7)-(IF(Parâmetros!$B$15=1,0,Parâmetros!$B$14)*Parâmetros!$B$10))<=Parâmetros!$B$26,MAX(0,K5-(MIN(K5,Parâmetros!$B$8)*Parâmetros!$B$7)-(IF(Parâmetros!$B$15=1,0,Parâmetros!$B$14)*Parâmetros!$B$10))*0.075-Parâmetros!$B$29,IF(MAX(0,K5-(MIN(K5,Parâmetros!$B$8)*Parâmetros!$B$7)-(IF(Parâmetros!$B$15=1,0,Parâmetros!$B$14)*Parâmetros!$B$10))<=Parâmetros!$B$27,MAX(0,K5-(MIN(K5,Parâmetros!$B$8)*Parâmetros!$B$7)-(IF(Parâmetros!$B$15=1,0,Parâmetros!$B$14)*Parâmetros!$B$10))*0.15-Parâmetros!$B$30,IF(MAX(0,K5-(MIN(K5,Parâmetros!$B$8)*Parâmetros!$B$7)-(IF(Parâmetros!$B$15=1,0,Parâmetros!$B$14)*Parâmetros!$B$10))<=Parâmetros!$B$28,MAX(0,K5-(MIN(K5,Parâmetros!$B$8)*Parâmetros!$B$7)-(IF(Parâmetros!$B$15=1,0,Parâmetros!$B$14)*Parâmetros!$B$10))*0.225-Parâmetros!$B$31,MAX(0,K5-(MIN(K5,Parâmetros!$B$8)*Parâmetros!$B$7)-(IF(Parâmetros!$B$15=1,0,Parâmetros!$B$14)*Parâmetros!$B$10))*0.275-Parâmetros!$B$32)))))-IF(K5<=Parâmetros!$B$34,Parâmetros!$B$35-Parâmetros!$B$36*K5,0))) | Q5: =MAX(0,B5-N5-K5) | R5: =B5-N5-O5-P5 | S5: =Parâmetros!$B$21 | T5: =IF(B5=0,0,S5/B5) | U5: =IF(T5>=Parâmetros!$B$6,"III","V") | V5: =IF(U5="III",B5*Parâmetros!$B$4,B5*Parâmetros!$B$5) | W5: =MIN(S5,Parâmetros!$B$8)*Parâmetros!$B$7 | X5: =IF(S5<=Parâmetros!$B$33,0,MAX(0,(IF(MAX(0,S5-(MIN(S5,Parâmetros!$B$8)*Parâmetros!$B$7)-(IF(Parâmetros!$B$15=1,0,Parâmetros!$B$14)*Parâmetros!$B$10))<=Parâmetros!$B$25,0,IF(MAX(0,S5-(MIN(S5,Parâmetros!$B$8)*Parâmetros!$B$7)-(IF(Parâmetros!$B$15=1,0,Parâmetros!$B$14)*Parâmetros!$B$10))<=Parâmetros!$B$26,MAX(0,S5-(MIN(S5,Parâmetros!$B$8)*Parâmetros!$B$7)-(IF(Parâmetros!$B$15=1,0,Parâmetros!$B$14)*Parâmetros!$B$10))*0.075-Parâmetros!$B$29,IF(MAX(0,S5-(MIN(S5,Parâmetros!$B$8)*Parâmetros!$B$7)-(IF(Parâmetros!$B$15=1,0,Parâmetros!$B$14)*Parâmetros!$B$10))<=Parâmetros!$B$27,MAX(0,S5-(MIN(S5,Parâmetros!$B$8)*Parâmetros!$B$7)-(IF(Parâmetros!$B$15=1,0,Parâmetros!$B$14)*Parâmetros!$B$10))*0.15-Parâmetros!$B$30,IF(MAX(0,S5-(MIN(S5,Parâmetros!$B$8)*Parâmetros!$B$7)-(IF(Parâmetros!$B$15=1,0,Parâmetros!$B$14)*Parâmetros!$B$10))<=Parâmetros!$B$28,MAX(0,S5-(MIN(S5,Parâmetros!$B$8)*Parâmetros!$B$7)-(IF(Parâmetros!$B$15=1,0,Parâmetros!$B$14)*Parâmetros!$B$10))*0.225-Parâmetros!$B$31,MAX(0,S5-(MIN(S5,Parâmetros!$B$8)*Parâmetros!$B$7)-(IF(Parâmetros!$B$15=1,0,Parâmetros!$B$14)*Parâmetros!$B$10))*0.275-Parâmetros!$B$32)))))-IF(S5<=Parâmetros!$B$34,Parâmetros!$B$35-Parâmetros!$B$36*S5,0))) | Y5: =MAX(0,B5-V5-S5) | Z5: =B5-V5-W5-X5
A6: 45689 | B6: =Notas!G7 | C6: =Parâmetros!$B$19 | D6: =IF(SUM(B5:B6)=0,0,SUM(C5:C6)/SUM(B5:B6)) | E6: =IF(D6>=Parâmetros!$B$6,"III","V") | F6: =IF(E6="III",B6*Parâmetros!$B$4,B6*Parâmetros!$B$5) | G6: =MIN(C6,Parâmetros!$B$8)*Parâmetros!$B$7 | H6: =IF(C6<=Parâmetros!$B$33,0,MAX(0,(IF(MAX(0,C6-(MIN(C6,Parâmetros!$B$8)*Parâmetros!$B$7)-(IF(Parâmetros!$B$15=1,0,Parâmetros!$B$14)*Parâmetros!$B$10))<=Parâmetros!$B$25,0,IF(MAX(0,C6-(MIN(C6,Parâmetros!$B$8)*Parâmetros!$B$7)-(IF(Parâmetros!$B$15=1,0,Parâmetros!$B$14)*Parâmetros!$B$10))<=Parâmetros!$B$26,MAX(0,C6-(MIN(C6,Parâmetros!$B$8)*Parâmetros!$B$7)-(IF(Parâmetros!$B$15=1,0,Parâmetros!$B$14)*Parâmetros!$B$10))*0.075-Parâmetros!$B$29,IF(MAX(0,C6-(MIN(C6,Parâmetros!$B$8)*Parâmetros!$B$7)-(IF(Parâmetros!$B$15=1,0,Parâmetros!$B$14)*Parâmetros!$B$10))<=Parâmetros!$B$27,MAX(0,C6-(MIN(C6,Parâmetros!$B$8)*Parâmetros!$B$7)-(IF(Parâmetros!$B$15=1,0,Parâmetros!$B$14)*Parâmetros!$B$10))*0.15-Parâmetros!$B$30,IF(MAX(0,C6-(MIN(C6,Parâmetros!$B$8)*Parâmetros!$B$7)-(IF(Parâmetros!$B$15=1,0,Parâmetros!$B$14)*Parâmetros!$B$10))<=Parâmetros!$B$28,MAX(0,C6-(MIN(C6,Parâmetros!$B$8)*Parâmetros!$B$7)-(IF(Parâmetros!$B$15=1,0,Parâmetros!$B$14)*Parâmetros!$B$10))*0.225-Parâmetros!$B$31,MAX(0,C6-(MIN(C6,Parâmetros!$B$8)*Parâmetros!$B$7)-(IF(Parâmetros!$B$15=1,0,Parâmetros!$B$14)*Parâmetros!$B$10))*0.275-Parâmetros!$B$32)))))-IF(C6<=Parâmetros!$B$34,Parâmetros!$B$35-Parâmetros!$B$36*C6,0))) | I6: =MAX(0,B6-F6-C6) | J6: =B6-F6-G6-H6 | K6: =IF(A6<Parâmetros!$B$23,Parâmetros!$B$19,MAX(Parâmetros!$B$22,Parâmetros!$B$6*SUM(B5:B6)-SUM(K5:K5))) | L6: =IF(SUM(B5:B6)=0,0,SUM(K5:K6)/SUM(B5:B6)) | M6: =IF(L6>=Parâmetros!$B$6,"III","V") | N6: =IF(M6="III",B6*Parâmetros!$B$4,B6*Parâmetros!$B$5) | O6: =MIN(K6,Parâmetros!$B$8)*Parâmetros!$B$7 | P6: =IF(K6<=Parâmetros!$B$33,0,MAX(0,(IF(MAX(0,K6-(MIN(K6,Parâmetros!$B$8)*Parâmetros!$B$7)-(IF(Parâmetros!$B$15=1,0,Parâmetros!$B$14)*Parâmetros!$B$10))<=Parâmetros!$B$25,0,IF(MAX(0,K6-(MIN(K6,Parâmetros!$B$8)*Parâmetros!$B$7)-(IF(Parâmetros!$B$15=1,0,Parâmetros!$B$14)*Parâmetros!$B$10))<=Parâmetros!$B$26,MAX(0,K6-(MIN(K6,Parâmetros!$B$8)*Parâmetros!$B$7)-(IF(Parâmetros!$B$15=1,0,Parâmetros!$B$14)*Parâmetros!$B$10))*0.075-Parâmetros!$B$29,IF(MAX(0,K6-(MIN(K6,Parâmetros!$B$8)*Parâmetros!$B$7)-(IF(Parâmetros!$B$15=1,0,Parâmetros!$B$14)*Parâmetros!$B$10))<=Parâmetros!$B$27,MAX(0,K6-(MIN(K6,Parâmetros!$B$8)*Parâmetros!$B$7)-(IF(Parâmetros!$B$15=1,0,Parâmetros!$B$14)*Parâmetros!$B$10))*0.15-Parâmetros!$B$30,IF(MAX(0,K6-(MIN(K6,Parâmetros!$B$8)*Parâmetros!$B$7)-(IF(Parâmetros!$B$15=1,0,Parâmetros!$B$14)*Parâmetros!$B$10))<=Parâmetros!$B$28,MAX(0,K6-(MIN(K6,Parâmetros!$B$8)*Parâmetros!$B$7)-(IF(Parâmetros!$B$15=1,0,Parâmetros!$B$14)*Parâmetros!$B$10))*0.225-Parâmetros!$B$31,MAX(0,K6-(MIN(K6,Parâmetros!$B$8)*Parâmetros!$B$7)-(IF(Parâmetros!$B$15=1,0,Parâmetros!$B$14)*Parâmetros!$B$10))*0.275-Parâmetros!$B$32)))))-IF(K6<=Parâmetros!$B$34,Parâmetros!$B$35-Parâmetros!$B$36*K6,0))) | Q6: =MAX(0,B6-N6-K6) | R6: =B6-N6-O6-P6 | S6: =Parâmetros!$B$21 | T6: =IF(SUM(B5:B6)=0,0,SUM(S5:S6)/SUM(B5:B6)) | U6: =IF(T6>=Parâmetros!$B$6,"III","V") | V6: =IF(U6="III",B6*Parâmetros!$B$4,B6*Parâmetros!$B$5) | W6: =MIN(S6,Parâmetros!$B$8)*Parâmetros!$B$7 | X6: =IF(S6<=Parâmetros!$B$33,0,MAX(0,(IF(MAX(0,S6-(MIN(S6,Parâmetros!$B$8)*Parâmetros!$B$7)-(IF(Parâmetros!$B$15=1,0,Parâmetros!$B$14)*Parâmetros!$B$10))<=Parâmetros!$B$25,0,IF(MAX(0,S6-(MIN(S6,Parâmetros!$B$8)*Parâmetros!$B$7)-(IF(Parâmetros!$B$15=1,0,Parâmetros!$B$14)*Parâmetros!$B$10))<=Parâmetros!$B$26,MAX(0,S6-(MIN(S6,Parâmetros!$B$8)*Parâmetros!$B$7)-(IF(Parâmetros!$B$15=1,0,Parâmetros!$B$14)*Parâmetros!$B$10))*0.075-Parâmetros!$B$29,IF(MAX(0,S6-(MIN(S6,Parâmetros!$B$8)*Parâmetros!$B$7)-(IF(Parâmetros!$B$15=1,0,Parâmetros!$B$14)*Parâmetros!$B$10))<=Parâmetros!$B$27,MAX(0,S6-(MIN(S6,Parâmetros!$B$8)*Parâmetros!$B$7)-(IF(Parâmetros!$B$15=1,0,Parâmetros!$B$14)*Parâmetros!$B$10))*0.15-Parâmetros!$B$30,IF(MAX(0,S6-(MIN(S6,Parâmetros!$B$8)*Parâmetros!$B$7)-(IF(Parâmetros!$B$15=1,0,Parâmetros!$B$14)*Parâmetros!$B$10))<=Parâmetros!$B$28,MAX(0,S6-(MIN(S6,Parâmetros!$B$8)*Parâmetros!$B$7)-(IF(Parâmetros!$B$15=1,0,Parâmetros!$B$14)*Parâmetros!$B$10))*0.225-Parâmetros!$B$31,MAX(0,S6-(MIN(S6,Parâmetros!$B$8)*Parâmetros!$B$7)-(IF(Parâmetros!$B$15=1,0,Parâmetros!$B$14)*Parâmetros!$B$10))*0.275-Parâmetros!$B$32)))))-IF(S6<=Parâmetros!$B$34,Parâmetros!$B$35-Parâmetros!$B$36*S6,0))) | Y6: =MAX(0,B6-V6-S6) | Z6: =B6-V6-W6-X6
A7: 45717 | B7: =Notas!G8 | C7: =Parâmetros!$B$19 | D7: =IF(SUM(B5:B7)=0,0,SUM(C5:C7)/SUM(B5:B7)) | E7: =IF(D7>=Parâmetros!$B$6,"III","V") | F7: =IF(E7="III",B7*Parâmetros!$B$4,B7*Parâmetros!$B$5) | G7: =MIN(C7,Parâmetros!$B$8)*Parâmetros!$B$7 | H7: =IF(C7<=Parâmetros!$B$33,0,MAX(0,(IF(MAX(0,C7-(MIN(C7,Parâmetros!$B$8)*Parâmetros!$B$7)-(IF(Parâmetros!$B$15=1,0,Parâmetros!$B$14)*Parâmetros!$B$10))<=Parâmetros!$B$25,0,IF(MAX(0,C7-(MIN(C7,Parâmetros!$B$8)*Parâmetros!$B$7)-(IF(Parâmetros!$B$15=1,0,Parâmetros!$B$14)*Parâmetros!$B$10))<=Parâmetros!$B$26,MAX(0,C7-(MIN(C7,Parâmetros!$B$8)*Parâmetros!$B$7)-(IF(Parâmetros!$B$15=1,0,Parâmetros!$B$14)*Parâmetros!$B$10))*0.075-Parâmetros!$B$29,IF(MAX(0,C7-(MIN(C7,Parâmetros!$B$8)*Parâmetros!$B$7)-(IF(Parâmetros!$B$15=1,0,Parâmetros!$B$14)*Parâmetros!$B$10))<=Parâmetros!$B$27,MAX(0,C7-(MIN(C7,Parâmetros!$B$8)*Parâmetros!$B$7)-(IF(Parâmetros!$B$15=1,0,Parâmetros!$B$14)*Parâmetros!$B$10))*0.15-Parâmetros!$B$30,IF(MAX(0,C7-(MIN(C7,Parâmetros!$B$8)*Parâmetros!$B$7)-(IF(Parâmetros!$B$15=1,0,Parâmetros!$B$14)*Parâmetros!$B$10))<=Parâmetros!$B$28,MAX(0,C7-(MIN(C7,Parâmetros!$B$8)*Parâmetros!$B$7)-(IF(Parâmetros!$B$15=1,0,Parâmetros!$B$14)*Parâmetros!$B$10))*0.225-Parâmetros!$B$31,MAX(0,C7-(MIN(C7,Parâmetros!$B$8)*Parâmetros!$B$7)-(IF(Parâmetros!$B$15=1,0,Parâmetros!$B$14)*Parâmetros!$B$10))*0.275-Parâmetros!$B$32)))))-IF(C7<=Parâmetros!$B$34,Parâmetros!$B$35-Parâmetros!$B$36*C7,0))) | I7: =MAX(0,B7-F7-C7) | J7: =B7-F7-G7-H7 | K7: =IF(A7<Parâmetros!$B$23,Parâmetros!$B$19,MAX(Parâmetros!$B$22,Parâmetros!$B$6*SUM(B5:B7)-SUM(K5:K6))) | L7: =IF(SUM(B5:B7)=0,0,SUM(K5:K7)/SUM(B5:B7)) | M7: =IF(L7>=Parâmetros!$B$6,"III","V") | N7: =IF(M7="III",B7*Parâmetros!$B$4,B7*Parâmetros!$B$5) | O7: =MIN(K7,Parâmetros!$B$8)*Parâmetros!$B$7 | P7: =IF(K7<=Parâmetros!$B$33,0,MAX(0,(IF(MAX(0,K7-(MIN(K7,Parâmetros!$B$8)*Parâmetros!$B$7)-(IF(Parâmetros!$B$15=1,0,Parâmetros!$B$14)*Parâmetros!$B$10))<=Parâmetros!$B$25,0,IF(MAX(0,K7-(MIN(K7,Parâmetros!$B$8)*Parâmetros!$B$7)-(IF(Parâmetros!$B$15=1,0,Parâmetros!$B$14)*Parâmetros!$B$10))<=Parâmetros!$B$26,MAX(0,K7-(MIN(K7,Parâmetros!$B$8)*Parâmetros!$B$7)-(IF(Parâmetros!$B$15=1,0,Parâmetros!$B$14)*Parâmetros!$B$10))*0.075-Parâmetros!$B$29,IF(MAX(0,K7-(MIN(K7,Parâmetros!$B$8)*Parâmetros!$B$7)-(IF(Parâmetros!$B$15=1,0,Parâmetros!$B$14)*Parâmetros!$B$10))<=Parâmetros!$B$27,MAX(0,K7-(MIN(K7,Parâmetros!$B$8)*Parâmetros!$B$7)-(IF(Parâmetros!$B$15=1,0,Parâmetros!$B$14)*Parâmetros!$B$10))*0.15-Parâmetros!$B$30,IF(MAX(0,K7-(MIN(K7,Parâmetros!$B$8)*Parâmetros!$B$7)-(IF(Parâmetros!$B$15=1,0,Parâmetros!$B$14)*Parâmetros!$B$10))<=Parâmetros!$B$28,MAX(0,K7-(MIN(K7,Parâmetros!$B$8)*Parâmetros!$B$7)-(IF(Parâmetros!$B$15=1,0,Parâmetros!$B$14)*Parâmetros!$B$10))*0.225-Parâmetros!$B$31,MAX(0,K7-(MIN(K7,Parâmetros!$B$8)*Parâmetros!$B$7)-(IF(Parâmetros!$B$15=1,0,Parâmetros!$B$14)*Parâmetros!$B$10))*0.275-Parâmetros!$B$32)))))-IF(K7<=Parâmetros!$B$34,Parâmetros!$B$35-Parâmetros!$B$36*K7,0))) | Q7: =MAX(0,B7-N7-K7) | R7: =B7-N7-O7-P7 | S7: =Parâmetros!$B$21 | T7: =IF(SUM(B5:B7)=0,0,SUM(S5:S7)/SUM(B5:B7)) | U7: =IF(T7>=Parâmetros!$B$6,"III","V") | V7: =IF(U7="III",B7*Parâmetros!$B$4,B7*Parâmetros!$B$5) | W7: =MIN(S7,Parâmetros!$B$8)*Parâmetros!$B$7 | X7: =IF(S7<=Parâmetros!$B$33,0,MAX(0,(IF(MAX(0,S7-(MIN(S7,Parâmetros!$B$8)*Parâmetros!$B$7)-(IF(Parâmetros!$B$15=1,0,Parâmetros!$B$14)*Parâmetros!$B$10))<=Parâmetros!$B$25,0,IF(MAX(0,S7-(MIN(S7,Parâmetros!$B$8)*Parâmetros!$B$7)-(IF(Parâmetros!$B$15=1,0,Parâmetros!$B$14)*Parâmetros!$B$10))<=Parâmetros!$B$26,MAX(0,S7-(MIN(S7,Parâmetros!$B$8)*Parâmetros!$B$7)-(IF(Parâmetros!$B$15=1,0,Parâmetros!$B$14)*Parâmetros!$B$10))*0.075-Parâmetros!$B$29,IF(MAX(0,S7-(MIN(S7,Parâmetros!$B$8)*Parâmetros!$B$7)-(IF(Parâmetros!$B$15=1,0,Parâmetros!$B$14)*Parâmetros!$B$10))<=Parâmetros!$B$27,MAX(0,S7-(MIN(S7,Parâmetros!$B$8)*Parâmetros!$B$7)-(IF(Parâmetros!$B$15=1,0,Parâmetros!$B$14)*Parâmetros!$B$10))*0.15-Parâmetros!$B$30,IF(MAX(0,S7-(MIN(S7,Parâmetros!$B$8)*Parâmetros!$B$7)-(IF(Parâmetros!$B$15=1,0,Parâmetros!$B$14)*Parâmetros!$B$10))<=Parâmetros!$B$28,MAX(0,S7-(MIN(S7,Parâmetros!$B$8)*Parâmetros!$B$7)-(IF(Parâmetros!$B$15=1,0,Parâmetros!$B$14)*Parâmetros!$B$10))*0.225-Parâmetros!$B$31,MAX(0,S7-(MIN(S7,Parâmetros!$B$8)*Parâmetros!$B$7)-(IF(Parâmetros!$B$15=1,0,Parâmetros!$B$14)*Parâmetros!$B$10))*0.275-Parâmetros!$B$32)))))-IF(S7<=Parâmetros!$B$34,Parâmetros!$B$35-Parâmetros!$B$36*S7,0))) | Y7: =MAX(0,B7-V7-S7) | Z7: =B7-V7-W7-X7
A8: 45748 | B8: =Notas!G9 | C8: =Parâmetros!$B$19 | D8: =IF(SUM(B5:B8)=0,0,SUM(C5:C8)/SUM(B5:B8)) | E8: =IF(D8>=Parâmetros!$B$6,"III","V") | F8: =IF(E8="III",B8*Parâmetros!$B$4,B8*Parâmetros!$B$5) | G8: =MIN(C8,Parâmetros!$B$8)*Parâmetros!$B$7 | H8: =IF(C8<=Parâmetros!$B$33,0,MAX(0,(IF(MAX(0,C8-(MIN(C8,Parâmetros!$B$8)*Parâmetros!$B$7)-(IF(Parâmetros!$B$15=1,0,Parâmetros!$B$14)*Parâmetros!$B$10))<=Parâmetros!$B$25,0,IF(MAX(0,C8-(MIN(C8,Parâmetros!$B$8)*Parâmetros!$B$7)-(IF(Parâmetros!$B$15=1,0,Parâmetros!$B$14)*Parâmetros!$B$10))<=Parâmetros!$B$26,MAX(0,C8-(MIN(C8,Parâmetros!$B$8)*Parâmetros!$B$7)-(IF(Parâmetros!$B$15=1,0,Parâmetros!$B$14)*Parâmetros!$B$10))*0.075-Parâmetros!$B$29,IF(MAX(0,C8-(MIN(C8,Parâmetros!$B$8)*Parâmetros!$B$7)-(IF(Parâmetros!$B$15=1,0,Parâmetros!$B$14)*Parâmetros!$B$10))<=Parâmetros!$B$27,MAX(0,C8-(MIN(C8,Parâmetros!$B$8)*Parâmetros!$B$7)-(IF(Parâmetros!$B$15=1,0,Parâmetros!$B$14)*Parâmetros!$B$10))*0.15-Parâmetros!$B$30,IF(MAX(0,C8-(MIN(C8,Parâmetros!$B$8)*Parâmetros!$B$7)-(IF(Parâmetros!$B$15=1,0,Parâmetros!$B$14)*Parâmetros!$B$10))<=Parâmetros!$B$28,MAX(0,C8-(MIN(C8,Parâmetros!$B$8)*Parâmetros!$B$7)-(IF(Parâmetros!$B$15=1,0,Parâmetros!$B$14)*Parâmetros!$B$10))*0.225-Parâmetros!$B$31,MAX(0,C8-(MIN(C8,Parâmetros!$B$8)*Parâmetros!$B$7)-(IF(Parâmetros!$B$15=1,0,Parâmetros!$B$14)*Parâmetros!$B$10))*0.275-Parâmetros!$B$32)))))-IF(C8<=Parâmetros!$B$34,Parâmetros!$B$35-Parâmetros!$B$36*C8,0))) | I8: =MAX(0,B8-F8-C8) | J8: =B8-F8-G8-H8 | K8: =IF(A8<Parâmetros!$B$23,Parâmetros!$B$19,MAX(Parâmetros!$B$22,Parâmetros!$B$6*SUM(B5:B8)-SUM(K5:K7))) | L8: =IF(SUM(B5:B8)=0,0,SUM(K5:K8)/SUM(B5:B8)) | M8: =IF(L8>=Parâmetros!$B$6,"III","V") | N8: =IF(M8="III",B8*Parâmetros!$B$4,B8*Parâmetros!$B$5) | O8: =MIN(K8,Parâmetros!$B$8)*Parâmetros!$B$7 | P8: =IF(K8<=Parâmetros!$B$33,0,MAX(0,(IF(MAX(0,K8-(MIN(K8,Parâmetros!$B$8)*Parâmetros!$B$7)-(IF(Parâmetros!$B$15=1,0,Parâmetros!$B$14)*Parâmetros!$B$10))<=Parâmetros!$B$25,0,IF(MAX(0,K8-(MIN(K8,Parâmetros!$B$8)*Parâmetros!$B$7)-(IF(Parâmetros!$B$15=1,0,Parâmetros!$B$14)*Parâmetros!$B$10))<=Parâmetros!$B$26,MAX(0,K8-(MIN(K8,Parâmetros!$B$8)*Parâmetros!$B$7)-(IF(Parâmetros!$B$15=1,0,Parâmetros!$B$14)*Parâmetros!$B$10))*0.075-Parâmetros!$B$29,IF(MAX(0,K8-(MIN(K8,Parâmetros!$B$8)*Parâmetros!$B$7)-(IF(Parâmetros!$B$15=1,0,Parâmetros!$B$14)*Parâmetros!$B$10))<=Parâmetros!$B$27,MAX(0,K8-(MIN(K8,Parâmetros!$B$8)*Parâmetros!$B$7)-(IF(Parâmetros!$B$15=1,0,Parâmetros!$B$14)*Parâmetros!$B$10))*0.15-Parâmetros!$B$30,IF(MAX(0,K8-(MIN(K8,Parâmetros!$B$8)*Parâmetros!$B$7)-(IF(Parâmetros!$B$15=1,0,Parâmetros!$B$14)*Parâmetros!$B$10))<=Parâmetros!$B$28,MAX(0,K8-(MIN(K8,Parâmetros!$B$8)*Parâmetros!$B$7)-(IF(Parâmetros!$B$15=1,0,Parâmetros!$B$14)*Parâmetros!$B$10))*0.225-Parâmetros!$B$31,MAX(0,K8-(MIN(K8,Parâmetros!$B$8)*Parâmetros!$B$7)-(IF(Parâmetros!$B$15=1,0,Parâmetros!$B$14)*Parâmetros!$B$10))*0.275-Parâmetros!$B$32)))))-IF(K8<=Parâmetros!$B$34,Parâmetros!$B$35-Parâmetros!$B$36*K8,0))) | Q8: =MAX(0,B8-N8-K8) | R8: =B8-N8-O8-P8 | S8: =Parâmetros!$B$21 | T8: =IF(SUM(B5:B8)=0,0,SUM(S5:S8)/SUM(B5:B8)) | U8: =IF(T8>=Parâmetros!$B$6,"III","V") | V8: =IF(U8="III",B8*Parâmetros!$B$4,B8*Parâmetros!$B$5) | W8: =MIN(S8,Parâmetros!$B$8)*Parâmetros!$B$7 | X8: =IF(S8<=Parâmetros!$B$33,0,MAX(0,(IF(MAX(0,S8-(MIN(S8,Parâmetros!$B$8)*Parâmetros!$B$7)-(IF(Parâmetros!$B$15=1,0,Parâmetros!$B$14)*Parâmetros!$B$10))<=Parâmetros!$B$25,0,IF(MAX(0,S8-(MIN(S8,Parâmetros!$B$8)*Parâmetros!$B$7)-(IF(Parâmetros!$B$15=1,0,Parâmetros!$B$14)*Parâmetros!$B$10))<=Parâmetros!$B$26,MAX(0,S8-(MIN(S8,Parâmetros!$B$8)*Parâmetros!$B$7)-(IF(Parâmetros!$B$15=1,0,Parâmetros!$B$14)*Parâmetros!$B$10))*0.075-Parâmetros!$B$29,IF(MAX(0,S8-(MIN(S8,Parâmetros!$B$8)*Parâmetros!$B$7)-(IF(Parâmetros!$B$15=1,0,Parâmetros!$B$14)*Parâmetros!$B$10))<=Parâmetros!$B$27,MAX(0,S8-(MIN(S8,Parâmetros!$B$8)*Parâmetros!$B$7)-(IF(Parâmetros!$B$15=1,0,Parâmetros!$B$14)*Parâmetros!$B$10))*0.15-Parâmetros!$B$30,IF(MAX(0,S8-(MIN(S8,Parâmetros!$B$8)*Parâmetros!$B$7)-(IF(Parâmetros!$B$15=1,0,Parâmetros!$B$14)*Parâmetros!$B$10))<=Parâmetros!$B$28,MAX(0,S8-(MIN(S8,Parâmetros!$B$8)*Parâmetros!$B$7)-(IF(Parâmetros!$B$15=1,0,Parâmetros!$B$14)*Parâmetros!$B$10))*0.225-Parâmetros!$B$31,MAX(0,S8-(MIN(S8,Parâmetros!$B$8)*Parâmetros!$B$7)-(IF(Parâmetros!$B$15=1,0,Parâmetros!$B$14)*Parâmetros!$B$10))*0.275-Parâmetros!$B$32)))))-IF(S8<=Parâmetros!$B$34,Parâmetros!$B$35-Parâmetros!$B$36*S8,0))) | Y8: =MAX(0,B8-V8-S8) | Z8: =B8-V8-W8-X8
A9: 45778 | B9: =Notas!G10 | C9: =Parâmetros!$B$19 | D9: =IF(SUM(B5:B9)=0,0,SUM(C5:C9)/SUM(B5:B9)) | E9: =IF(D9>=Parâmetros!$B$6,"III","V") | F9: =IF(E9="III",B9*Parâmetros!$B$4,B9*Parâmetros!$B$5) | G9: =MIN(C9,Parâmetros!$B$8)*Parâmetros!$B$7 | H9: =IF(C9<=Parâmetros!$B$33,0,MAX(0,(IF(MAX(0,C9-(MIN(C9,Parâmetros!$B$8)*Parâmetros!$B$7)-(IF(Parâmetros!$B$15=1,0,Parâmetros!$B$14)*Parâmetros!$B$10))<=Parâmetros!$B$25,0,IF(MAX(0,C9-(MIN(C9,Parâmetros!$B$8)*Parâmetros!$B$7)-(IF(Parâmetros!$B$15=1,0,Parâmetros!$B$14)*Parâmetros!$B$10))<=Parâmetros!$B$26,MAX(0,C9-(MIN(C9,Parâmetros!$B$8)*Parâmetros!$B$7)-(IF(Parâmetros!$B$15=1,0,Parâmetros!$B$14)*Parâmetros!$B$10))*0.075-Parâmetros!$B$29,IF(MAX(0,C9-(MIN(C9,Parâmetros!$B$8)*Parâmetros!$B$7)-(IF(Parâmetros!$B$15=1,0,Parâmetros!$B$14)*Parâmetros!$B$10))<=Parâmetros!$B$27,MAX(0,C9-(MIN(C9,Parâmetros!$B$8)*Parâmetros!$B$7)-(IF(Parâmetros!$B$15=1,0,Parâmetros!$B$14)*Parâmetros!$B$10))*0.15-Parâmetros!$B$30,IF(MAX(0,C9-(MIN(C9,Parâmetros!$B$8)*Parâmetros!$B$7)-(IF(Parâmetros!$B$15=1,0,Parâmetros!$B$14)*Parâmetros!$B$10))<=Parâmetros!$B$28,MAX(0,C9-(MIN(C9,Parâmetros!$B$8)*Parâmetros!$B$7)-(IF(Parâmetros!$B$15=1,0,Parâmetros!$B$14)*Parâmetros!$B$10))*0.225-Parâmetros!$B$31,MAX(0,C9-(MIN(C9,Parâmetros!$B$8)*Parâmetros!$B$7)-(IF(Parâmetros!$B$15=1,0,Parâmetros!$B$14)*Parâmetros!$B$10))*0.275-Parâmetros!$B$32)))))-IF(C9<=Parâmetros!$B$34,Parâmetros!$B$35-Parâmetros!$B$36*C9,0))) | I9: =MAX(0,B9-F9-C9) | J9: =B9-F9-G9-H9 | K9: =IF(A9<Parâmetros!$B$23,Parâmetros!$B$19,MAX(Parâmetros!$B$22,Parâmetros!$B$6*SUM(B5:B9)-SUM(K5:K8))) | L9: =IF(SUM(B5:B9)=0,0,SUM(K5:K9)/SUM(B5:B9)) | M9: =IF(L9>=Parâmetros!$B$6,"III","V") | N9: =IF(M9="III",B9*Parâmetros!$B$4,B9*Parâmetros!$B$5) | O9: =MIN(K9,Parâmetros!$B$8)*Parâmetros!$B$7 | P9: =IF(K9<=Parâmetros!$B$33,0,MAX(0,(IF(MAX(0,K9-(MIN(K9,Parâmetros!$B$8)*Parâmetros!$B$7)-(IF(Parâmetros!$B$15=1,0,Parâmetros!$B$14)*Parâmetros!$B$10))<=Parâmetros!$B$25,0,IF(MAX(0,K9-(MIN(K9,Parâmetros!$B$8)*Parâmetros!$B$7)-(IF(Parâmetros!$B$15=1,0,Parâmetros!$B$14)*Parâmetros!$B$10))<=Parâmetros!$B$26,MAX(0,K9-(MIN(K9,Parâmetros!$B$8)*Parâmetros!$B$7)-(IF(Parâmetros!$B$15=1,0,Parâmetros!$B$14)*Parâmetros!$B$10))*0.075-Parâmetros!$B$29,IF(MAX(0,K9-(MIN(K9,Parâmetros!$B$8)*Parâmetros!$B$7)-(IF(Parâmetros!$B$15=1,0,Parâmetros!$B$14)*Parâmetros!$B$10))<=Parâmetros!$B$27,MAX(0,K9-(MIN(K9,Parâmetros!$B$8)*Parâmetros!$B$7)-(IF(Parâmetros!$B$15=1,0,Parâmetros!$B$14)*Parâmetros!$B$10))*0.15-Parâmetros!$B$30,IF(MAX(0,K9-(MIN(K9,Parâmetros!$B$8)*Parâmetros!$B$7)-(IF(Parâmetros!$B$15=1,0,Parâmetros!$B$14)*Parâmetros!$B$10))<=Parâmetros!$B$28,MAX(0,K9-(MIN(K9,Parâmetros!$B$8)*Parâmetros!$B$7)-(IF(Parâmetros!$B$15=1,0,Parâmetros!$B$14)*Parâmetros!$B$10))*0.225-Parâmetros!$B$31,MAX(0,K9-(MIN(K9,Parâmetros!$B$8)*Parâmetros!$B$7)-(IF(Parâmetros!$B$15=1,0,Parâmetros!$B$14)*Parâmetros!$B$10))*0.275-Parâmetros!$B$32)))))-IF(K9<=Parâmetros!$B$34,Parâmetros!$B$35-Parâmetros!$B$36*K9,0))) | Q9: =MAX(0,B9-N9-K9) | R9: =B9-N9-O9-P9 | S9: =Parâmetros!$B$21 | T9: =IF(SUM(B5:B9)=0,0,SUM(S5:S9)/SUM(B5:B9)) | U9: =IF(T9>=Parâmetros!$B$6,"III","V") | V9: =IF(U9="III",B9*Parâmetros!$B$4,B9*Parâmetros!$B$5) | W9: =MIN(S9,Parâmetros!$B$8)*Parâmetros!$B$7 | X9: =IF(S9<=Parâmetros!$B$33,0,MAX(0,(IF(MAX(0,S9-(MIN(S9,Parâmetros!$B$8)*Parâmetros!$B$7)-(IF(Parâmetros!$B$15=1,0,Parâmetros!$B$14)*Parâmetros!$B$10))<=Parâmetros!$B$25,0,IF(MAX(0,S9-(MIN(S9,Parâmetros!$B$8)*Parâmetros!$B$7)-(IF(Parâmetros!$B$15=1,0,Parâmetros!$B$14)*Parâmetros!$B$10))<=Parâmetros!$B$26,MAX(0,S9-(MIN(S9,Parâmetros!$B$8)*Parâmetros!$B$7)-(IF(Parâmetros!$B$15=1,0,Parâmetros!$B$14)*Parâmetros!$B$10))*0.075-Parâmetros!$B$29,IF(MAX(0,S9-(MIN(S9,Parâmetros!$B$8)*Parâmetros!$B$7)-(IF(Parâmetros!$B$15=1,0,Parâmetros!$B$14)*Parâmetros!$B$10))<=Parâmetros!$B$27,MAX(0,S9-(MIN(S9,Parâmetros!$B$8)*Parâmetros!$B$7)-(IF(Parâmetros!$B$15=1,0,Parâmetros!$B$14)*Parâmetros!$B$10))*0.15-Parâmetros!$B$30,IF(MAX(0,S9-(MIN(S9,Parâmetros!$B$8)*Parâmetros!$B$7)-(IF(Parâmetros!$B$15=1,0,Parâmetros!$B$14)*Parâmetros!$B$10))<=Parâmetros!$B$28,MAX(0,S9-(MIN(S9,Parâmetros!$B$8)*Parâmetros!$B$7)-(IF(Parâmetros!$B$15=1,0,Parâmetros!$B$14)*Parâmetros!$B$10))*0.225-Parâmetros!$B$31,MAX(0,S9-(MIN(S9,Parâmetros!$B$8)*Parâmetros!$B$7)-(IF(Parâmetros!$B$15=1,0,Parâmetros!$B$14)*Parâmetros!$B$10))*0.275-Parâmetros!$B$32)))))-IF(S9<=Parâmetros!$B$34,Parâmetros!$B$35-Parâmetros!$B$36*S9,0))) | Y9: =MAX(0,B9-V9-S9) | Z9: =B9-V9-W9-X9
A10: 45809 | B10: =Notas!G11 | C10: =Parâmetros!$B$19 | D10: =IF(SUM(B5:B10)=0,0,SUM(C5:C10)/SUM(B5:B10)) | E10: =IF(D10>=Parâmetros!$B$6,"III","V") | F10: =IF(E10="III",B10*Parâmetros!$B$4,B10*Parâmetros!$B$5) | G10: =MIN(C10,Parâmetros!$B$8)*Parâmetros!$B$7 | H10: =IF(C10<=Parâmetros!$B$33,0,MAX(0,(IF(MAX(0,C10-(MIN(C10,Parâmetros!$B$8)*Parâmetros!$B$7)-(IF(Parâmetros!$B$15=1,0,Parâmetros!$B$14)*Parâmetros!$B$10))<=Parâmetros!$B$25,0,IF(MAX(0,C10-(MIN(C10,Parâmetros!$B$8)*Parâmetros!$B$7)-(IF(Parâmetros!$B$15=1,0,Parâmetros!$B$14)*Parâmetros!$B$10))<=Parâmetros!$B$26,MAX(0,C10-(MIN(C10,Parâmetros!$B$8)*Parâmetros!$B$7)-(IF(Parâmetros!$B$15=1,0,Parâmetros!$B$14)*Parâmetros!$B$10))*0.075-Parâmetros!$B$29,IF(MAX(0,C10-(MIN(C10,Parâmetros!$B$8)*Parâmetros!$B$7)-(IF(Parâmetros!$B$15=1,0,Parâmetros!$B$14)*Parâmetros!$B$10))<=Parâmetros!$B$27,MAX(0,C10-(MIN(C10,Parâmetros!$B$8)*Parâmetros!$B$7)-(IF(Parâmetros!$B$15=1,0,Parâmetros!$B$14)*Parâmetros!$B$10))*0.15-Parâmetros!$B$30,IF(MAX(0,C10-(MIN(C10,Parâmetros!$B$8)*Parâmetros!$B$7)-(IF(Parâmetros!$B$15=1,0,Parâmetros!$B$14)*Parâmetros!$B$10))<=Parâmetros!$B$28,MAX(0,C10-(MIN(C10,Parâmetros!$B$8)*Parâmetros!$B$7)-(IF(Parâmetros!$B$15=1,0,Parâmetros!$B$14)*Parâmetros!$B$10))*0.225-Parâmetros!$B$31,MAX(0,C10-(MIN(C10,Parâmetros!$B$8)*Parâmetros!$B$7)-(IF(Parâmetros!$B$15=1,0,Parâmetros!$B$14)*Parâmetros!$B$10))*0.275-Parâmetros!$B$32)))))-IF(C10<=Parâmetros!$B$34,Parâmetros!$B$35-Parâmetros!$B$36*C10,0))) | I10: =MAX(0,B10-F10-C10) | J10: =B10-F10-G10-H10 | K10: =IF(A10<Parâmetros!$B$23,Parâmetros!$B$19,MAX(Parâmetros!$B$22,Parâmetros!$B$6*SUM(B5:B10)-SUM(K5:K9))) | L10: =IF(SUM(B5:B10)=0,0,SUM(K5:K10)/SUM(B5:B10)) | M10: =IF(L10>=Parâmetros!$B$6,"III","V") | N10: =IF(M10="III",B10*Parâmetros!$B$4,B10*Parâmetros!$B$5) | O10: =MIN(K10,Parâmetros!$B$8)*Parâmetros!$B$7 | P10: =IF(K10<=Parâmetros!$B$33,0,MAX(0,(IF(MAX(0,K10-(MIN(K10,Parâmetros!$B$8)*Parâmetros!$B$7)-(IF(Parâmetros!$B$15=1,0,Parâmetros!$B$14)*Parâmetros!$B$10))<=Parâmetros!$B$25,0,IF(MAX(0,K10-(MIN(K10,Parâmetros!$B$8)*Parâmetros!$B$7)-(IF(Parâmetros!$B$15=1,0,Parâmetros!$B$14)*Parâmetros!$B$10))<=Parâmetros!$B$26,MAX(0,K10-(MIN(K10,Parâmetros!$B$8)*Parâmetros!$B$7)-(IF(Parâmetros!$B$15=1,0,Parâmetros!$B$14)*Parâmetros!$B$10))*0.075-Parâmetros!$B$29,IF(MAX(0,K10-(MIN(K10,Parâmetros!$B$8)*Parâmetros!$B$7)-(IF(Parâmetros!$B$15=1,0,Parâmetros!$B$14)*Parâmetros!$B$10))<=Parâmetros!$B$27,MAX(0,K10-(MIN(K10,Parâmetros!$B$8)*Parâmetros!$B$7)-(IF(Parâmetros!$B$15=1,0,Parâmetros!$B$14)*Parâmetros!$B$10))*0.15-Parâmetros!$B$30,IF(MAX(0,K10-(MIN(K10,Parâmetros!$B$8)*Parâmetros!$B$7)-(IF(Parâmetros!$B$15=1,0,Parâmetros!$B$14)*Parâmetros!$B$10))<=Parâmetros!$B$28,MAX(0,K10-(MIN(K10,Parâmetros!$B$8)*Parâmetros!$B$7)-(IF(Parâmetros!$B$15=1,0,Parâmetros!$B$14)*Parâmetros!$B$10))*0.225-Parâmetros!$B$31,MAX(0,K10-(MIN(K10,Parâmetros!$B$8)*Parâmetros!$B$7)-(IF(Parâmetros!$B$15=1,0,Parâmetros!$B$14)*Parâmetros!$B$10))*0.275-Parâmetros!$B$32)))))-IF(K10<=Parâmetros!$B$34,Parâmetros!$B$35-Parâmetros!$B$36*K10,0))) | Q10: =MAX(0,B10-N10-K10) | R10: =B10-N10-O10-P10 | S10: =Parâmetros!$B$21 | T10: =IF(SUM(B5:B10)=0,0,SUM(S5:S10)/SUM(B5:B10)) | U10: =IF(T10>=Parâmetros!$B$6,"III","V") | V10: =IF(U10="III",B10*Parâmetros!$B$4,B10*Parâmetros!$B$5) | W10: =MIN(S10,Parâmetros!$B$8)*Parâmetros!$B$7 | X10: =IF(S10<=Parâmetros!$B$33,0,MAX(0,(IF(MAX(0,S10-(MIN(S10,Parâmetros!$B$8)*Parâmetros!$B$7)-(IF(Parâmetros!$B$15=1,0,Parâmetros!$B$14)*Parâmetros!$B$10))<=Parâmetros!$B$25,0,IF(MAX(0,S10-(MIN(S10,Parâmetros!$B$8)*Parâmetros!$B$7)-(IF(Parâmetros!$B$15=1,0,Parâmetros!$B$14)*Parâmetros!$B$10))<=Parâmetros!$B$26,MAX(0,S10-(MIN(S10,Parâmetros!$B$8)*Parâmetros!$B$7)-(IF(Parâmetros!$B$15=1,0,Parâmetros!$B$14)*Parâmetros!$B$10))*0.075-Parâmetros!$B$29,IF(MAX(0,S10-(MIN(S10,Parâmetros!$B$8)*Parâmetros!$B$7)-(IF(Parâmetros!$B$15=1,0,Parâmetros!$B$14)*Parâmetros!$B$10))<=Parâmetros!$B$27,MAX(0,S10-(MIN(S10,Parâmetros!$B$8)*Parâmetros!$B$7)-(IF(Parâmetros!$B$15=1,0,Parâmetros!$B$14)*Parâmetros!$B$10))*0.15-Parâmetros!$B$30,IF(MAX(0,S10-(MIN(S10,Parâmetros!$B$8)*Parâmetros!$B$7)-(IF(Parâmetros!$B$15=1,0,Parâmetros!$B$14)*Parâmetros!$B$10))<=Parâmetros!$B$28,MAX(0,S10-(MIN(S10,Parâmetros!$B$8)*Parâmetros!$B$7)-(IF(Parâmetros!$B$15=1,0,Parâmetros!$B$14)*Parâmetros!$B$10))*0.225-Parâmetros!$B$31,MAX(0,S10-(MIN(S10,Parâmetros!$B$8)*Parâmetros!$B$7)-(IF(Parâmetros!$B$15=1,0,Parâmetros!$B$14)*Parâmetros!$B$10))*0.275-Parâmetros!$B$32)))))-IF(S10<=Parâmetros!$B$34,Parâmetros!$B$35-Parâmetros!$B$36*S10,0))) | Y10: =MAX(0,B10-V10-S10) | Z10: =B10-V10-W10-X10
A11: 45839 | B11: =Notas!G12 | C11: =Parâmetros!$B$19 | D11: =IF(SUM(B5:B11)=0,0,SUM(C5:C11)/SUM(B5:B11)) | E11: =IF(D11>=Parâmetros!$B$6,"III","V") | F11: =IF(E11="III",B11*Parâmetros!$B$4,B11*Parâmetros!$B$5) | G11: =MIN(C11,Parâmetros!$B$8)*Parâmetros!$B$7 | H11: =IF(C11<=Parâmetros!$B$33,0,MAX(0,(IF(MAX(0,C11-(MIN(C11,Parâmetros!$B$8)*Parâmetros!$B$7)-(IF(Parâmetros!$B$15=1,0,Parâmetros!$B$14)*Parâmetros!$B$10))<=Parâmetros!$B$25,0,IF(MAX(0,C11-(MIN(C11,Parâmetros!$B$8)*Parâmetros!$B$7)-(IF(Parâmetros!$B$15=1,0,Parâmetros!$B$14)*Parâmetros!$B$10))<=Parâmetros!$B$26,MAX(0,C11-(MIN(C11,Parâmetros!$B$8)*Parâmetros!$B$7)-(IF(Parâmetros!$B$15=1,0,Parâmetros!$B$14)*Parâmetros!$B$10))*0.075-Parâmetros!$B$29,IF(MAX(0,C11-(MIN(C11,Parâmetros!$B$8)*Parâmetros!$B$7)-(IF(Parâmetros!$B$15=1,0,Parâmetros!$B$14)*Parâmetros!$B$10))<=Parâmetros!$B$27,MAX(0,C11-(MIN(C11,Parâmetros!$B$8)*Parâmetros!$B$7)-(IF(Parâmetros!$B$15=1,0,Parâmetros!$B$14)*Parâmetros!$B$10))*0.15-Parâmetros!$B$30,IF(MAX(0,C11-(MIN(C11,Parâmetros!$B$8)*Parâmetros!$B$7)-(IF(Parâmetros!$B$15=1,0,Parâmetros!$B$14)*Parâmetros!$B$10))<=Parâmetros!$B$28,MAX(0,C11-(MIN(C11,Parâmetros!$B$8)*Parâmetros!$B$7)-(IF(Parâmetros!$B$15=1,0,Parâmetros!$B$14)*Parâmetros!$B$10))*0.225-Parâmetros!$B$31,MAX(0,C11-(MIN(C11,Parâmetros!$B$8)*Parâmetros!$B$7)-(IF(Parâmetros!$B$15=1,0,Parâmetros!$B$14)*Parâmetros!$B$10))*0.275-Parâmetros!$B$32)))))-IF(C11<=Parâmetros!$B$34,Parâmetros!$B$35-Parâmetros!$B$36*C11,0))) | I11: =MAX(0,B11-F11-C11) | J11: =B11-F11-G11-H11 | K11: =IF(A11<Parâmetros!$B$23,Parâmetros!$B$19,MAX(Parâmetros!$B$22,Parâmetros!$B$6*SUM(B5:B11)-SUM(K5:K10))) | L11: =IF(SUM(B5:B11)=0,0,SUM(K5:K11)/SUM(B5:B11)) | M11: =IF(L11>=Parâmetros!$B$6,"III","V") | N11: =IF(M11="III",B11*Parâmetros!$B$4,B11*Parâmetros!$B$5) | O11: =MIN(K11,Parâmetros!$B$8)*Parâmetros!$B$7 | P11: =IF(K11<=Parâmetros!$B$33,0,MAX(0,(IF(MAX(0,K11-(MIN(K11,Parâmetros!$B$8)*Parâmetros!$B$7)-(IF(Parâmetros!$B$15=1,0,Parâmetros!$B$14)*Parâmetros!$B$10))<=Parâmetros!$B$25,0,IF(MAX(0,K11-(MIN(K11,Parâmetros!$B$8)*Parâmetros!$B$7)-(IF(Parâmetros!$B$15=1,0,Parâmetros!$B$14)*Parâmetros!$B$10))<=Parâmetros!$B$26,MAX(0,K11-(MIN(K11,Parâmetros!$B$8)*Parâmetros!$B$7)-(IF(Parâmetros!$B$15=1,0,Parâmetros!$B$14)*Parâmetros!$B$10))*0.075-Parâmetros!$B$29,IF(MAX(0,K11-(MIN(K11,Parâmetros!$B$8)*Parâmetros!$B$7)-(IF(Parâmetros!$B$15=1,0,Parâmetros!$B$14)*Parâmetros!$B$10))<=Parâmetros!$B$27,MAX(0,K11-(MIN(K11,Parâmetros!$B$8)*Parâmetros!$B$7)-(IF(Parâmetros!$B$15=1,0,Parâmetros!$B$14)*Parâmetros!$B$10))*0.15-Parâmetros!$B$30,IF(MAX(0,K11-(MIN(K11,Parâmetros!$B$8)*Parâmetros!$B$7)-(IF(Parâmetros!$B$15=1,0,Parâmetros!$B$14)*Parâmetros!$B$10))<=Parâmetros!$B$28,MAX(0,K11-(MIN(K11,Parâmetros!$B$8)*Parâmetros!$B$7)-(IF(Parâmetros!$B$15=1,0,Parâmetros!$B$14)*Parâmetros!$B$10))*0.225-Parâmetros!$B$31,MAX(0,K11-(MIN(K11,Parâmetros!$B$8)*Parâmetros!$B$7)-(IF(Parâmetros!$B$15=1,0,Parâmetros!$B$14)*Parâmetros!$B$10))*0.275-Parâmetros!$B$32)))))-IF(K11<=Parâmetros!$B$34,Parâmetros!$B$35-Parâmetros!$B$36*K11,0))) | Q11: =MAX(0,B11-N11-K11) | R11: =B11-N11-O11-P11 | S11: =Parâmetros!$B$21 | T11: =IF(SUM(B5:B11)=0,0,SUM(S5:S11)/SUM(B5:B11)) | U11: =IF(T11>=Parâmetros!$B$6,"III","V") | V11: =IF(U11="III",B11*Parâmetros!$B$4,B11*Parâmetros!$B$5) | W11: =MIN(S11,Parâmetros!$B$8)*Parâmetros!$B$7 | X11: =IF(S11<=Parâmetros!$B$33,0,MAX(0,(IF(MAX(0,S11-(MIN(S11,Parâmetros!$B$8)*Parâmetros!$B$7)-(IF(Parâmetros!$B$15=1,0,Parâmetros!$B$14)*Parâmetros!$B$10))<=Parâmetros!$B$25,0,IF(MAX(0,S11-(MIN(S11,Parâmetros!$B$8)*Parâmetros!$B$7)-(IF(Parâmetros!$B$15=1,0,Parâmetros!$B$14)*Parâmetros!$B$10))<=Parâmetros!$B$26,MAX(0,S11-(MIN(S11,Parâmetros!$B$8)*Parâmetros!$B$7)-(IF(Parâmetros!$B$15=1,0,Parâmetros!$B$14)*Parâmetros!$B$10))*0.075-Parâmetros!$B$29,IF(MAX(0,S11-(MIN(S11,Parâmetros!$B$8)*Parâmetros!$B$7)-(IF(Parâmetros!$B$15=1,0,Parâmetros!$B$14)*Parâmetros!$B$10))<=Parâmetros!$B$27,MAX(0,S11-(MIN(S11,Parâmetros!$B$8)*Parâmetros!$B$7)-(IF(Parâmetros!$B$15=1,0,Parâmetros!$B$14)*Parâmetros!$B$10))*0.15-Parâmetros!$B$30,IF(MAX(0,S11-(MIN(S11,Parâmetros!$B$8)*Parâmetros!$B$7)-(IF(Parâmetros!$B$15=1,0,Parâmetros!$B$14)*Parâmetros!$B$10))<=Parâmetros!$B$28,MAX(0,S11-(MIN(S11,Parâmetros!$B$8)*Parâmetros!$B$7)-(IF(Parâmetros!$B$15=1,0,Parâmetros!$B$14)*Parâmetros!$B$10))*0.225-Parâmetros!$B$31,MAX(0,S11-(MIN(S11,Parâmetros!$B$8)*Parâmetros!$B$7)-(IF(Parâmetros!$B$15=1,0,Parâmetros!$B$14)*Parâmetros!$B$10))*0.275-Parâmetros!$B$32)))))-IF(S11<=Parâmetros!$B$34,Parâmetros!$B$35-Parâmetros!$B$36*S11,0))) | Y11: =MAX(0,B11-V11-S11) | Z11: =B11-V11-W11-X11
A12: 45870 | B12: =Notas!G13 | C12: =Parâmetros!$B$19 | D12: =IF(SUM(B5:B12)=0,0,SUM(C5:C12)/SUM(B5:B12)) | E12: =IF(D12>=Parâmetros!$B$6,"III","V") | F12: =IF(E12="III",B12*Parâmetros!$B$4,B12*Parâmetros!$B$5) | G12: =MIN(C12,Parâmetros!$B$8)*Parâmetros!$B$7 | H12: =IF(C12<=Parâmetros!$B$33,0,MAX(0,(IF(MAX(0,C12-(MIN(C12,Parâmetros!$B$8)*Parâmetros!$B$7)-(IF(Parâmetros!$B$15=1,0,Parâmetros!$B$14)*Parâmetros!$B$10))<=Parâmetros!$B$25,0,IF(MAX(0,C12-(MIN(C12,Parâmetros!$B$8)*Parâmetros!$B$7)-(IF(Parâmetros!$B$15=1,0,Parâmetros!$B$14)*Parâmetros!$B$10))<=Parâmetros!$B$26,MAX(0,C12-(MIN(C12,Parâmetros!$B$8)*Parâmetros!$B$7)-(IF(Parâmetros!$B$15=1,0,Parâmetros!$B$14)*Parâmetros!$B$10))*0.075-Parâmetros!$B$29,IF(MAX(0,C12-(MIN(C12,Parâmetros!$B$8)*Parâmetros!$B$7)-(IF(Parâmetros!$B$15=1,0,Parâmetros!$B$14)*Parâmetros!$B$10))<=Parâmetros!$B$27,MAX(0,C12-(MIN(C12,Parâmetros!$B$8)*Parâmetros!$B$7)-(IF(Parâmetros!$B$15=1,0,Parâmetros!$B$14)*Parâmetros!$B$10))*0.15-Parâmetros!$B$30,IF(MAX(0,C12-(MIN(C12,Parâmetros!$B$8)*Parâmetros!$B$7)-(IF(Parâmetros!$B$15=1,0,Parâmetros!$B$14)*Parâmetros!$B$10))<=Parâmetros!$B$28,MAX(0,C12-(MIN(C12,Parâmetros!$B$8)*Parâmetros!$B$7)-(IF(Parâmetros!$B$15=1,0,Parâmetros!$B$14)*Parâmetros!$B$10))*0.225-Parâmetros!$B$31,MAX(0,C12-(MIN(C12,Parâmetros!$B$8)*Parâmetros!$B$7)-(IF(Parâmetros!$B$15=1,0,Parâmetros!$B$14)*Parâmetros!$B$10))*0.275-Parâmetros!$B$32)))))-IF(C12<=Parâmetros!$B$34,Parâmetros!$B$35-Parâmetros!$B$36*C12,0))) | I12: =MAX(0,B12-F12-C12) | J12: =B12-F12-G12-H12 | K12: =IF(A12<Parâmetros!$B$23,Parâmetros!$B$19,MAX(Parâmetros!$B$22,Parâmetros!$B$6*SUM(B5:B12)-SUM(K5:K11))) | L12: =IF(SUM(B5:B12)=0,0,SUM(K5:K12)/SUM(B5:B12)) | M12: =IF(L12>=Parâmetros!$B$6,"III","V") | N12: =IF(M12="III",B12*Parâmetros!$B$4,B12*Parâmetros!$B$5) | O12: =MIN(K12,Parâmetros!$B$8)*Parâmetros!$B$7 | P12: =IF(K12<=Parâmetros!$B$33,0,MAX(0,(IF(MAX(0,K12-(MIN(K12,Parâmetros!$B$8)*Parâmetros!$B$7)-(IF(Parâmetros!$B$15=1,0,Parâmetros!$B$14)*Parâmetros!$B$10))<=Parâmetros!$B$25,0,IF(MAX(0,K12-(MIN(K12,Parâmetros!$B$8)*Parâmetros!$B$7)-(IF(Parâmetros!$B$15=1,0,Parâmetros!$B$14)*Parâmetros!$B$10))<=Parâmetros!$B$26,MAX(0,K12-(MIN(K12,Parâmetros!$B$8)*Parâmetros!$B$7)-(IF(Parâmetros!$B$15=1,0,Parâmetros!$B$14)*Parâmetros!$B$10))*0.075-Parâmetros!$B$29,IF(MAX(0,K12-(MIN(K12,Parâmetros!$B$8)*Parâmetros!$B$7)-(IF(Parâmetros!$B$15=1,0,Parâmetros!$B$14)*Parâmetros!$B$10))<=Parâmetros!$B$27,MAX(0,K12-(MIN(K12,Parâmetros!$B$8)*Parâmetros!$B$7)-(IF(Parâmetros!$B$15=1,0,Parâmetros!$B$14)*Parâmetros!$B$10))*0.15-Parâmetros!$B$30,IF(MAX(0,K12-(MIN(K12,Parâmetros!$B$8)*Parâmetros!$B$7)-(IF(Parâmetros!$B$15=1,0,Parâmetros!$B$14)*Parâmetros!$B$10))<=Parâmetros!$B$28,MAX(0,K12-(MIN(K12,Parâmetros!$B$8)*Parâmetros!$B$7)-(IF(Parâmetros!$B$15=1,0,Parâmetros!$B$14)*Parâmetros!$B$10))*0.225-Parâmetros!$B$31,MAX(0,K12-(MIN(K12,Parâmetros!$B$8)*Parâmetros!$B$7)-(IF(Parâmetros!$B$15=1,0,Parâmetros!$B$14)*Parâmetros!$B$10))*0.275-Parâmetros!$B$32)))))-IF(K12<=Parâmetros!$B$34,Parâmetros!$B$35-Parâmetros!$B$36*K12,0))) | Q12: =MAX(0,B12-N12-K12) | R12: =B12-N12-O12-P12 | S12: =Parâmetros!$B$21 | T12: =IF(SUM(B5:B12)=0,0,SUM(S5:S12)/SUM(B5:B12)) | U12: =IF(T12>=Parâmetros!$B$6,"III","V") | V12: =IF(U12="III",B12*Parâmetros!$B$4,B12*Parâmetros!$B$5) | W12: =MIN(S12,Parâmetros!$B$8)*Parâmetros!$B$7 | X12: =IF(S12<=Parâmetros!$B$33,0,MAX(0,(IF(MAX(0,S12-(MIN(S12,Parâmetros!$B$8)*Parâmetros!$B$7)-(IF(Parâmetros!$B$15=1,0,Parâmetros!$B$14)*Parâmetros!$B$10))<=Parâmetros!$B$25,0,IF(MAX(0,S12-(MIN(S12,Parâmetros!$B$8)*Parâmetros!$B$7)-(IF(Parâmetros!$B$15=1,0,Parâmetros!$B$14)*Parâmetros!$B$10))<=Parâmetros!$B$26,MAX(0,S12-(MIN(S12,Parâmetros!$B$8)*Parâmetros!$B$7)-(IF(Parâmetros!$B$15=1,0,Parâmetros!$B$14)*Parâmetros!$B$10))*0.075-Parâmetros!$B$29,IF(MAX(0,S12-(MIN(S12,Parâmetros!$B$8)*Parâmetros!$B$7)-(IF(Parâmetros!$B$15=1,0,Parâmetros!$B$14)*Parâmetros!$B$10))<=Parâmetros!$B$27,MAX(0,S12-(MIN(S12,Parâmetros!$B$8)*Parâmetros!$B$7)-(IF(Parâmetros!$B$15=1,0,Parâmetros!$B$14)*Parâmetros!$B$10))*0.15-Parâmetros!$B$30,IF(MAX(0,S12-(MIN(S12,Parâmetros!$B$8)*Parâmetros!$B$7)-(IF(Parâmetros!$B$15=1,0,Parâmetros!$B$14)*Parâmetros!$B$10))<=Parâmetros!$B$28,MAX(0,S12-(MIN(S12,Parâmetros!$B$8)*Parâmetros!$B$7)-(IF(Parâmetros!$B$15=1,0,Parâmetros!$B$14)*Parâmetros!$B$10))*0.225-Parâmetros!$B$31,MAX(0,S12-(MIN(S12,Parâmetros!$B$8)*Parâmetros!$B$7)-(IF(Parâmetros!$B$15=1,0,Parâmetros!$B$14)*Parâmetros!$B$10))*0.275-Parâmetros!$B$32)))))-IF(S12<=Parâmetros!$B$34,Parâmetros!$B$35-Parâmetros!$B$36*S12,0))) | Y12: =MAX(0,B12-V12-S12) | Z12: =B12-V12-W12-X12
A13: 45901 | B13: =Notas!G14 | C13: =Parâmetros!$B$19 | D13: =IF(SUM(B5:B13)=0,0,SUM(C5:C13)/SUM(B5:B13)) | E13: =IF(D13>=Parâmetros!$B$6,"III","V") | F13: =IF(E13="III",B13*Parâmetros!$B$4,B13*Parâmetros!$B$5) | G13: =MIN(C13,Parâmetros!$B$8)*Parâmetros!$B$7 | H13: =IF(C13<=Parâmetros!$B$33,0,MAX(0,(IF(MAX(0,C13-(MIN(C13,Parâmetros!$B$8)*Parâmetros!$B$7)-(IF(Parâmetros!$B$15=1,0,Parâmetros!$B$14)*Parâmetros!$B$10))<=Parâmetros!$B$25,0,IF(MAX(0,C13-(MIN(C13,Parâmetros!$B$8)*Parâmetros!$B$7)-(IF(Parâmetros!$B$15=1,0,Parâmetros!$B$14)*Parâmetros!$B$10))<=Parâmetros!$B$26,MAX(0,C13-(MIN(C13,Parâmetros!$B$8)*Parâmetros!$B$7)-(IF(Parâmetros!$B$15=1,0,Parâmetros!$B$14)*Parâmetros!$B$10))*0.075-Parâmetros!$B$29,IF(MAX(0,C13-(MIN(C13,Parâmetros!$B$8)*Parâmetros!$B$7)-(IF(Parâmetros!$B$15=1,0,Parâmetros!$B$14)*Parâmetros!$B$10))<=Parâmetros!$B$27,MAX(0,C13-(MIN(C13,Parâmetros!$B$8)*Parâmetros!$B$7)-(IF(Parâmetros!$B$15=1,0,Parâmetros!$B$14)*Parâmetros!$B$10))*0.15-Parâmetros!$B$30,IF(MAX(0,C13-(MIN(C13,Parâmetros!$B$8)*Parâmetros!$B$7)-(IF(Parâmetros!$B$15=1,0,Parâmetros!$B$14)*Parâmetros!$B$10))<=Parâmetros!$B$28,MAX(0,C13-(MIN(C13,Parâmetros!$B$8)*Parâmetros!$B$7)-(IF(Parâmetros!$B$15=1,0,Parâmetros!$B$14)*Parâmetros!$B$10))*0.225-Parâmetros!$B$31,MAX(0,C13-(MIN(C13,Parâmetros!$B$8)*Parâmetros!$B$7)-(IF(Parâmetros!$B$15=1,0,Parâmetros!$B$14)*Parâmetros!$B$10))*0.275-Parâmetros!$B$32)))))-IF(C13<=Parâmetros!$B$34,Parâmetros!$B$35-Parâmetros!$B$36*C13,0))) | I13: =MAX(0,B13-F13-C13) | J13: =B13-F13-G13-H13 | K13: =IF(A13<Parâmetros!$B$23,Parâmetros!$B$19,MAX(Parâmetros!$B$22,Parâmetros!$B$6*SUM(B5:B13)-SUM(K5:K12))) | L13: =IF(SUM(B5:B13)=0,0,SUM(K5:K13)/SUM(B5:B13)) | M13: =IF(L13>=Parâmetros!$B$6,"III","V") | N13: =IF(M13="III",B13*Parâmetros!$B$4,B13*Parâmetros!$B$5) | O13: =MIN(K13,Parâmetros!$B$8)*Parâmetros!$B$7 | P13: =IF(K13<=Parâmetros!$B$33,0,MAX(0,(IF(MAX(0,K13-(MIN(K13,Parâmetros!$B$8)*Parâmetros!$B$7)-(IF(Parâmetros!$B$15=1,0,Parâmetros!$B$14)*Parâmetros!$B$10))<=Parâmetros!$B$25,0,IF(MAX(0,K13-(MIN(K13,Parâmetros!$B$8)*Parâmetros!$B$7)-(IF(Parâmetros!$B$15=1,0,Parâmetros!$B$14)*Parâmetros!$B$10))<=Parâmetros!$B$26,MAX(0,K13-(MIN(K13,Parâmetros!$B$8)*Parâmetros!$B$7)-(IF(Parâmetros!$B$15=1,0,Parâmetros!$B$14)*Parâmetros!$B$10))*0.075-Parâmetros!$B$29,IF(MAX(0,K13-(MIN(K13,Parâmetros!$B$8)*Parâmetros!$B$7)-(IF(Parâmetros!$B$15=1,0,Parâmetros!$B$14)*Parâmetros!$B$10))<=Parâmetros!$B$27,MAX(0,K13-(MIN(K13,Parâmetros!$B$8)*Parâmetros!$B$7)-(IF(Parâmetros!$B$15=1,0,Parâmetros!$B$14)*Parâmetros!$B$10))*0.15-Parâmetros!$B$30,IF(MAX(0,K13-(MIN(K13,Parâmetros!$B$8)*Parâmetros!$B$7)-(IF(Parâmetros!$B$15=1,0,Parâmetros!$B$14)*Parâmetros!$B$10))<=Parâmetros!$B$28,MAX(0,K13-(MIN(K13,Parâmetros!$B$8)*Parâmetros!$B$7)-(IF(Parâmetros!$B$15=1,0,Parâmetros!$B$14)*Parâmetros!$B$10))*0.225-Parâmetros!$B$31,MAX(0,K13-(MIN(K13,Parâmetros!$B$8)*Parâmetros!$B$7)-(IF(Parâmetros!$B$15=1,0,Parâmetros!$B$14)*Parâmetros!$B$10))*0.275-Parâmetros!$B$32)))))-IF(K13<=Parâmetros!$B$34,Parâmetros!$B$35-Parâmetros!$B$36*K13,0))) | Q13: =MAX(0,B13-N13-K13) | R13: =B13-N13-O13-P13 | S13: =Parâmetros!$B$21 | T13: =IF(SUM(B5:B13)=0,0,SUM(S5:S13)/SUM(B5:B13)) | U13: =IF(T13>=Parâmetros!$B$6,"III","V") | V13: =IF(U13="III",B13*Parâmetros!$B$4,B13*Parâmetros!$B$5) | W13: =MIN(S13,Parâmetros!$B$8)*Parâmetros!$B$7 | X13: =IF(S13<=Parâmetros!$B$33,0,MAX(0,(IF(MAX(0,S13-(MIN(S13,Parâmetros!$B$8)*Parâmetros!$B$7)-(IF(Parâmetros!$B$15=1,0,Parâmetros!$B$14)*Parâmetros!$B$10))<=Parâmetros!$B$25,0,IF(MAX(0,S13-(MIN(S13,Parâmetros!$B$8)*Parâmetros!$B$7)-(IF(Parâmetros!$B$15=1,0,Parâmetros!$B$14)*Parâmetros!$B$10))<=Parâmetros!$B$26,MAX(0,S13-(MIN(S13,Parâmetros!$B$8)*Parâmetros!$B$7)-(IF(Parâmetros!$B$15=1,0,Parâmetros!$B$14)*Parâmetros!$B$10))*0.075-Parâmetros!$B$29,IF(MAX(0,S13-(MIN(S13,Parâmetros!$B$8)*Parâmetros!$B$7)-(IF(Parâmetros!$B$15=1,0,Parâmetros!$B$14)*Parâmetros!$B$10))<=Parâmetros!$B$27,MAX(0,S13-(MIN(S13,Parâmetros!$B$8)*Parâmetros!$B$7)-(IF(Parâmetros!$B$15=1,0,Parâmetros!$B$14)*Parâmetros!$B$10))*0.15-Parâmetros!$B$30,IF(MAX(0,S13-(MIN(S13,Parâmetros!$B$8)*Parâmetros!$B$7)-(IF(Parâmetros!$B$15=1,0,Parâmetros!$B$14)*Parâmetros!$B$10))<=Parâmetros!$B$28,MAX(0,S13-(MIN(S13,Parâmetros!$B$8)*Parâmetros!$B$7)-(IF(Parâmetros!$B$15=1,0,Parâmetros!$B$14)*Parâmetros!$B$10))*0.225-Parâmetros!$B$31,MAX(0,S13-(MIN(S13,Parâmetros!$B$8)*Parâmetros!$B$7)-(IF(Parâmetros!$B$15=1,0,Parâmetros!$B$14)*Parâmetros!$B$10))*0.275-Parâmetros!$B$32)))))-IF(S13<=Parâmetros!$B$34,Parâmetros!$B$35-Parâmetros!$B$36*S13,0))) | Y13: =MAX(0,B13-V13-S13) | Z13: =B13-V13-W13-X13
A14: 45931 | B14: =Notas!G15 | C14: =Parâmetros!$B$19 | D14: =IF(SUM(B5:B14)=0,0,SUM(C5:C14)/SUM(B5:B14)) | E14: =IF(D14>=Parâmetros!$B$6,"III","V") | F14: =IF(E14="III",B14*Parâmetros!$B$4,B14*Parâmetros!$B$5) | G14: =MIN(C14,Parâmetros!$B$8)*Parâmetros!$B$7 | H14: =IF(C14<=Parâmetros!$B$33,0,MAX(0,(IF(MAX(0,C14-(MIN(C14,Parâmetros!$B$8)*Parâmetros!$B$7)-(IF(Parâmetros!$B$15=1,0,Parâmetros!$B$14)*Parâmetros!$B$10))<=Parâmetros!$B$25,0,IF(MAX(0,C14-(MIN(C14,Parâmetros!$B$8)*Parâmetros!$B$7)-(IF(Parâmetros!$B$15=1,0,Parâmetros!$B$14)*Parâmetros!$B$10))<=Parâmetros!$B$26,MAX(0,C14-(MIN(C14,Parâmetros!$B$8)*Parâmetros!$B$7)-(IF(Parâmetros!$B$15=1,0,Parâmetros!$B$14)*Parâmetros!$B$10))*0.075-Parâmetros!$B$29,IF(MAX(0,C14-(MIN(C14,Parâmetros!$B$8)*Parâmetros!$B$7)-(IF(Parâmetros!$B$15=1,0,Parâmetros!$B$14)*Parâmetros!$B$10))<=Parâmetros!$B$27,MAX(0,C14-(MIN(C14,Parâmetros!$B$8)*Parâmetros!$B$7)-(IF(Parâmetros!$B$15=1,0,Parâmetros!$B$14)*Parâmetros!$B$10))*0.15-Parâmetros!$B$30,IF(MAX(0,C14-(MIN(C14,Parâmetros!$B$8)*Parâmetros!$B$7)-(IF(Parâmetros!$B$15=1,0,Parâmetros!$B$14)*Parâmetros!$B$10))<=Parâmetros!$B$28,MAX(0,C14-(MIN(C14,Parâmetros!$B$8)*Parâmetros!$B$7)-(IF(Parâmetros!$B$15=1,0,Parâmetros!$B$14)*Parâmetros!$B$10))*0.225-Parâmetros!$B$31,MAX(0,C14-(MIN(C14,Parâmetros!$B$8)*Parâmetros!$B$7)-(IF(Parâmetros!$B$15=1,0,Parâmetros!$B$14)*Parâmetros!$B$10))*0.275-Parâmetros!$B$32)))))-IF(C14<=Parâmetros!$B$34,Parâmetros!$B$35-Parâmetros!$B$36*C14,0))) | I14: =MAX(0,B14-F14-C14) | J14: =B14-F14-G14-H14 | K14: =IF(A14<Parâmetros!$B$23,Parâmetros!$B$19,MAX(Parâmetros!$B$22,Parâmetros!$B$6*SUM(B5:B14)-SUM(K5:K13))) | L14: =IF(SUM(B5:B14)=0,0,SUM(K5:K14)/SUM(B5:B14)) | M14: =IF(L14>=Parâmetros!$B$6,"III","V") | N14: =IF(M14="III",B14*Parâmetros!$B$4,B14*Parâmetros!$B$5) | O14: =MIN(K14,Parâmetros!$B$8)*Parâmetros!$B$7 | P14: =IF(K14<=Parâmetros!$B$33,0,MAX(0,(IF(MAX(0,K14-(MIN(K14,Parâmetros!$B$8)*Parâmetros!$B$7)-(IF(Parâmetros!$B$15=1,0,Parâmetros!$B$14)*Parâmetros!$B$10))<=Parâmetros!$B$25,0,IF(MAX(0,K14-(MIN(K14,Parâmetros!$B$8)*Parâmetros!$B$7)-(IF(Parâmetros!$B$15=1,0,Parâmetros!$B$14)*Parâmetros!$B$10))<=Parâmetros!$B$26,MAX(0,K14-(MIN(K14,Parâmetros!$B$8)*Parâmetros!$B$7)-(IF(Parâmetros!$B$15=1,0,Parâmetros!$B$14)*Parâmetros!$B$10))*0.075-Parâmetros!$B$29,IF(MAX(0,K14-(MIN(K14,Parâmetros!$B$8)*Parâmetros!$B$7)-(IF(Parâmetros!$B$15=1,0,Parâmetros!$B$14)*Parâmetros!$B$10))<=Parâmetros!$B$27,MAX(0,K14-(MIN(K14,Parâmetros!$B$8)*Parâmetros!$B$7)-(IF(Parâmetros!$B$15=1,0,Parâmetros!$B$14)*Parâmetros!$B$10))*0.15-Parâmetros!$B$30,IF(MAX(0,K14-(MIN(K14,Parâmetros!$B$8)*Parâmetros!$B$7)-(IF(Parâmetros!$B$15=1,0,Parâmetros!$B$14)*Parâmetros!$B$10))<=Parâmetros!$B$28,MAX(0,K14-(MIN(K14,Parâmetros!$B$8)*Parâmetros!$B$7)-(IF(Parâmetros!$B$15=1,0,Parâmetros!$B$14)*Parâmetros!$B$10))*0.225-Parâmetros!$B$31,MAX(0,K14-(MIN(K14,Parâmetros!$B$8)*Parâmetros!$B$7)-(IF(Parâmetros!$B$15=1,0,Parâmetros!$B$14)*Parâmetros!$B$10))*0.275-Parâmetros!$B$32)))))-IF(K14<=Parâmetros!$B$34,Parâmetros!$B$35-Parâmetros!$B$36*K14,0))) | Q14: =MAX(0,B14-N14-K14) | R14: =B14-N14-O14-P14 | S14: =Parâmetros!$B$21 | T14: =IF(SUM(B5:B14)=0,0,SUM(S5:S14)/SUM(B5:B14)) | U14: =IF(T14>=Parâmetros!$B$6,"III","V") | V14: =IF(U14="III",B14*Parâmetros!$B$4,B14*Parâmetros!$B$5) | W14: =MIN(S14,Parâmetros!$B$8)*Parâmetros!$B$7 | X14: =IF(S14<=Parâmetros!$B$33,0,MAX(0,(IF(MAX(0,S14-(MIN(S14,Parâmetros!$B$8)*Parâmetros!$B$7)-(IF(Parâmetros!$B$15=1,0,Parâmetros!$B$14)*Parâmetros!$B$10))<=Parâmetros!$B$25,0,IF(MAX(0,S14-(MIN(S14,Parâmetros!$B$8)*Parâmetros!$B$7)-(IF(Parâmetros!$B$15=1,0,Parâmetros!$B$14)*Parâmetros!$B$10))<=Parâmetros!$B$26,MAX(0,S14-(MIN(S14,Parâmetros!$B$8)*Parâmetros!$B$7)-(IF(Parâmetros!$B$15=1,0,Parâmetros!$B$14)*Parâmetros!$B$10))*0.075-Parâmetros!$B$29,IF(MAX(0,S14-(MIN(S14,Parâmetros!$B$8)*Parâmetros!$B$7)-(IF(Parâmetros!$B$15=1,0,Parâmetros!$B$14)*Parâmetros!$B$10))<=Parâmetros!$B$27,MAX(0,S14-(MIN(S14,Parâmetros!$B$8)*Parâmetros!$B$7)-(IF(Parâmetros!$B$15=1,0,Parâmetros!$B$14)*Parâmetros!$B$10))*0.15-Parâmetros!$B$30,IF(MAX(0,S14-(MIN(S14,Parâmetros!$B$8)*Parâmetros!$B$7)-(IF(Parâmetros!$B$15=1,0,Parâmetros!$B$14)*Parâmetros!$B$10))<=Parâmetros!$B$28,MAX(0,S14-(MIN(S14,Parâmetros!$B$8)*Parâmetros!$B$7)-(IF(Parâmetros!$B$15=1,0,Parâmetros!$B$14)*Parâmetros!$B$10))*0.225-Parâmetros!$B$31,MAX(0,S14-(MIN(S14,Parâmetros!$B$8)*Parâmetros!$B$7)-(IF(Parâmetros!$B$15=1,0,Parâmetros!$B$14)*Parâmetros!$B$10))*0.275-Parâmetros!$B$32)))))-IF(S14<=Parâmetros!$B$34,Parâmetros!$B$35-Parâmetros!$B$36*S14,0))) | Y14: =MAX(0,B14-V14-S14) | Z14: =B14-V14-W14-X14
A15: 45962 | B15: =Notas!G16 | C15: =Parâmetros!$B$19 | D15: =IF(SUM(B5:B15)=0,0,SUM(C5:C15)/SUM(B5:B15)) | E15: =IF(D15>=Parâmetros!$B$6,"III","V") | F15: =IF(E15="III",B15*Parâmetros!$B$4,B15*Parâmetros!$B$5) | G15: =MIN(C15,Parâmetros!$B$8)*Parâmetros!$B$7 | H15: =IF(C15<=Parâmetros!$B$33,0,MAX(0,(IF(MAX(0,C15-(MIN(C15,Parâmetros!$B$8)*Parâmetros!$B$7)-(IF(Parâmetros!$B$15=1,0,Parâmetros!$B$14)*Parâmetros!$B$10))<=Parâmetros!$B$25,0,IF(MAX(0,C15-(MIN(C15,Parâmetros!$B$8)*Parâmetros!$B$7)-(IF(Parâmetros!$B$15=1,0,Parâmetros!$B$14)*Parâmetros!$B$10))<=Parâmetros!$B$26,MAX(0,C15-(MIN(C15,Parâmetros!$B$8)*Parâmetros!$B$7)-(IF(Parâmetros!$B$15=1,0,Parâmetros!$B$14)*Parâmetros!$B$10))*0.075-Parâmetros!$B$29,IF(MAX(0,C15-(MIN(C15,Parâmetros!$B$8)*Parâmetros!$B$7)-(IF(Parâmetros!$B$15=1,0,Parâmetros!$B$14)*Parâmetros!$B$10))<=Parâmetros!$B$27,MAX(0,C15-(MIN(C15,Parâmetros!$B$8)*Parâmetros!$B$7)-(IF(Parâmetros!$B$15=1,0,Parâmetros!$B$14)*Parâmetros!$B$10))*0.15-Parâmetros!$B$30,IF(MAX(0,C15-(MIN(C15,Parâmetros!$B$8)*Parâmetros!$B$7)-(IF(Parâmetros!$B$15=1,0,Parâmetros!$B$14)*Parâmetros!$B$10))<=Parâmetros!$B$28,MAX(0,C15-(MIN(C15,Parâmetros!$B$8)*Parâmetros!$B$7)-(IF(Parâmetros!$B$15=1,0,Parâmetros!$B$14)*Parâmetros!$B$10))*0.225-Parâmetros!$B$31,MAX(0,C15-(MIN(C15,Parâmetros!$B$8)*Parâmetros!$B$7)-(IF(Parâmetros!$B$15=1,0,Parâmetros!$B$14)*Parâmetros!$B$10))*0.275-Parâmetros!$B$32)))))-IF(C15<=Parâmetros!$B$34,Parâmetros!$B$35-Parâmetros!$B$36*C15,0))) | I15: =MAX(0,B15-F15-C15) | J15: =B15-F15-G15-H15 | K15: =IF(A15<Parâmetros!$B$23,Parâmetros!$B$19,MAX(Parâmetros!$B$22,Parâmetros!$B$6*SUM(B5:B15)-SUM(K5:K14))) | L15: =IF(SUM(B5:B15)=0,0,SUM(K5:K15)/SUM(B5:B15)) | M15: =IF(L15>=Parâmetros!$B$6,"III","V") | N15: =IF(M15="III",B15*Parâmetros!$B$4,B15*Parâmetros!$B$5) | O15: =MIN(K15,Parâmetros!$B$8)*Parâmetros!$B$7 | P15: =IF(K15<=Parâmetros!$B$33,0,MAX(0,(IF(MAX(0,K15-(MIN(K15,Parâmetros!$B$8)*Parâmetros!$B$7)-(IF(Parâmetros!$B$15=1,0,Parâmetros!$B$14)*Parâmetros!$B$10))<=Parâmetros!$B$25,0,IF(MAX(0,K15-(MIN(K15,Parâmetros!$B$8)*Parâmetros!$B$7)-(IF(Parâmetros!$B$15=1,0,Parâmetros!$B$14)*Parâmetros!$B$10))<=Parâmetros!$B$26,MAX(0,K15-(MIN(K15,Parâmetros!$B$8)*Parâmetros!$B$7)-(IF(Parâmetros!$B$15=1,0,Parâmetros!$B$14)*Parâmetros!$B$10))*0.075-Parâmetros!$B$29,IF(MAX(0,K15-(MIN(K15,Parâmetros!$B$8)*Parâmetros!$B$7)-(IF(Parâmetros!$B$15=1,0,Parâmetros!$B$14)*Parâmetros!$B$10))<=Parâmetros!$B$27,MAX(0,K15-(MIN(K15,Parâmetros!$B$8)*Parâmetros!$B$7)-(IF(Parâmetros!$B$15=1,0,Parâmetros!$B$14)*Parâmetros!$B$10))*0.15-Parâmetros!$B$30,IF(MAX(0,K15-(MIN(K15,Parâmetros!$B$8)*Parâmetros!$B$7)-(IF(Parâmetros!$B$15=1,0,Parâmetros!$B$14)*Parâmetros!$B$10))<=Parâmetros!$B$28,MAX(0,K15-(MIN(K15,Parâmetros!$B$8)*Parâmetros!$B$7)-(IF(Parâmetros!$B$15=1,0,Parâmetros!$B$14)*Parâmetros!$B$10))*0.225-Parâmetros!$B$31,MAX(0,K15-(MIN(K15,Parâmetros!$B$8)*Parâmetros!$B$7)-(IF(Parâmetros!$B$15=1,0,Parâmetros!$B$14)*Parâmetros!$B$10))*0.275-Parâmetros!$B$32)))))-IF(K15<=Parâmetros!$B$34,Parâmetros!$B$35-Parâmetros!$B$36*K15,0))) | Q15: =MAX(0,B15-N15-K15) | R15: =B15-N15-O15-P15 | S15: =Parâmetros!$B$21 | T15: =IF(SUM(B5:B15)=0,0,SUM(S5:S15)/SUM(B5:B15)) | U15: =IF(T15>=Parâmetros!$B$6,"III","V") | V15: =IF(U15="III",B15*Parâmetros!$B$4,B15*Parâmetros!$B$5) | W15: =MIN(S15,Parâmetros!$B$8)*Parâmetros!$B$7 | X15: =IF(S15<=Parâmetros!$B$33,0,MAX(0,(IF(MAX(0,S15-(MIN(S15,Parâmetros!$B$8)*Parâmetros!$B$7)-(IF(Parâmetros!$B$15=1,0,Parâmetros!$B$14)*Parâmetros!$B$10))<=Parâmetros!$B$25,0,IF(MAX(0,S15-(MIN(S15,Parâmetros!$B$8)*Parâmetros!$B$7)-(IF(Parâmetros!$B$15=1,0,Parâmetros!$B$14)*Parâmetros!$B$10))<=Parâmetros!$B$26,MAX(0,S15-(MIN(S15,Parâmetros!$B$8)*Parâmetros!$B$7)-(IF(Parâmetros!$B$15=1,0,Parâmetros!$B$14)*Parâmetros!$B$10))*0.075-Parâmetros!$B$29,IF(MAX(0,S15-(MIN(S15,Parâmetros!$B$8)*Parâmetros!$B$7)-(IF(Parâmetros!$B$15=1,0,Parâmetros!$B$14)*Parâmetros!$B$10))<=Parâmetros!$B$27,MAX(0,S15-(MIN(S15,Parâmetros!$B$8)*Parâmetros!$B$7)-(IF(Parâmetros!$B$15=1,0,Parâmetros!$B$14)*Parâmetros!$B$10))*0.15-Parâmetros!$B$30,IF(MAX(0,S15-(MIN(S15,Parâmetros!$B$8)*Parâmetros!$B$7)-(IF(Parâmetros!$B$15=1,0,Parâmetros!$B$14)*Parâmetros!$B$10))<=Parâmetros!$B$28,MAX(0,S15-(MIN(S15,Parâmetros!$B$8)*Parâmetros!$B$7)-(IF(Parâmetros!$B$15=1,0,Parâmetros!$B$14)*Parâmetros!$B$10))*0.225-Parâmetros!$B$31,MAX(0,S15-(MIN(S15,Parâmetros!$B$8)*Parâmetros!$B$7)-(IF(Parâmetros!$B$15=1,0,Parâmetros!$B$14)*Parâmetros!$B$10))*0.275-Parâmetros!$B$32)))))-IF(S15<=Parâmetros!$B$34,Parâmetros!$B$35-Parâmetros!$B$36*S15,0))) | Y15: =MAX(0,B15-V15-S15) | Z15: =B15-V15-W15-X15
A16: 45992 | B16: =Notas!G17 | C16: =Parâmetros!$B$19 | D16: =IF(SUM(B5:B16)=0,0,SUM(C5:C16)/SUM(B5:B16)) | E16: =IF(D16>=Parâmetros!$B$6,"III","V") | F16: =IF(E16="III",B16*Parâmetros!$B$4,B16*Parâmetros!$B$5) | G16: =MIN(C16,Parâmetros!$B$8)*Parâmetros!$B$7 | H16: =IF(C16<=Parâmetros!$B$33,0,MAX(0,(IF(MAX(0,C16-(MIN(C16,Parâmetros!$B$8)*Parâmetros!$B$7)-(IF(Parâmetros!$B$15=1,0,Parâmetros!$B$14)*Parâmetros!$B$10))<=Parâmetros!$B$25,0,IF(MAX(0,C16-(MIN(C16,Parâmetros!$B$8)*Parâmetros!$B$7)-(IF(Parâmetros!$B$15=1,0,Parâmetros!$B$14)*Parâmetros!$B$10))<=Parâmetros!$B$26,MAX(0,C16-(MIN(C16,Parâmetros!$B$8)*Parâmetros!$B$7)-(IF(Parâmetros!$B$15=1,0,Parâmetros!$B$14)*Parâmetros!$B$10))*0.075-Parâmetros!$B$29,IF(MAX(0,C16-(MIN(C16,Parâmetros!$B$8)*Parâmetros!$B$7)-(IF(Parâmetros!$B$15=1,0,Parâmetros!$B$14)*Parâmetros!$B$10))<=Parâmetros!$B$27,MAX(0,C16-(MIN(C16,Parâmetros!$B$8)*Parâmetros!$B$7)-(IF(Parâmetros!$B$15=1,0,Parâmetros!$B$14)*Parâmetros!$B$10))*0.15-Parâmetros!$B$30,IF(MAX(0,C16-(MIN(C16,Parâmetros!$B$8)*Parâmetros!$B$7)-(IF(Parâmetros!$B$15=1,0,Parâmetros!$B$14)*Parâmetros!$B$10))<=Parâmetros!$B$28,MAX(0,C16-(MIN(C16,Parâmetros!$B$8)*Parâmetros!$B$7)-(IF(Parâmetros!$B$15=1,0,Parâmetros!$B$14)*Parâmetros!$B$10))*0.225-Parâmetros!$B$31,MAX(0,C16-(MIN(C16,Parâmetros!$B$8)*Parâmetros!$B$7)-(IF(Parâmetros!$B$15=1,0,Parâmetros!$B$14)*Parâmetros!$B$10))*0.275-Parâmetros!$B$32)))))-IF(C16<=Parâmetros!$B$34,Parâmetros!$B$35-Parâmetros!$B$36*C16,0))) | I16: =MAX(0,B16-F16-C16) | J16: =B16-F16-G16-H16 | K16: =IF(A16<Parâmetros!$B$23,Parâmetros!$B$19,MAX(Parâmetros!$B$22,Parâmetros!$B$6*SUM(B5:B16)-SUM(K5:K15))) | L16: =IF(SUM(B5:B16)=0,0,SUM(K5:K16)/SUM(B5:B16)) | M16: =IF(L16>=Parâmetros!$B$6,"III","V") | N16: =IF(M16="III",B16*Parâmetros!$B$4,B16*Parâmetros!$B$5) | O16: =MIN(K16,Parâmetros!$B$8)*Parâmetros!$B$7 | P16: =IF(K16<=Parâmetros!$B$33,0,MAX(0,(IF(MAX(0,K16-(MIN(K16,Parâmetros!$B$8)*Parâmetros!$B$7)-(IF(Parâmetros!$B$15=1,0,Parâmetros!$B$14)*Parâmetros!$B$10))<=Parâmetros!$B$25,0,IF(MAX(0,K16-(MIN(K16,Parâmetros!$B$8)*Parâmetros!$B$7)-(IF(Parâmetros!$B$15=1,0,Parâmetros!$B$14)*Parâmetros!$B$10))<=Parâmetros!$B$26,MAX(0,K16-(MIN(K16,Parâmetros!$B$8)*Parâmetros!$B$7)-(IF(Parâmetros!$B$15=1,0,Parâmetros!$B$14)*Parâmetros!$B$10))*0.075-Parâmetros!$B$29,IF(MAX(0,K16-(MIN(K16,Parâmetros!$B$8)*Parâmetros!$B$7)-(IF(Parâmetros!$B$15=1,0,Parâmetros!$B$14)*Parâmetros!$B$10))<=Parâmetros!$B$27,MAX(0,K16-(MIN(K16,Parâmetros!$B$8)*Parâmetros!$B$7)-(IF(Parâmetros!$B$15=1,0,Parâmetros!$B$14)*Parâmetros!$B$10))*0.15-Parâmetros!$B$30,IF(MAX(0,K16-(MIN(K16,Parâmetros!$B$8)*Parâmetros!$B$7)-(IF(Parâmetros!$B$15=1,0,Parâmetros!$B$14)*Parâmetros!$B$10))<=Parâmetros!$B$28,MAX(0,K16-(MIN(K16,Parâmetros!$B$8)*Parâmetros!$B$7)-(IF(Parâmetros!$B$15=1,0,Parâmetros!$B$14)*Parâmetros!$B$10))*0.225-Parâmetros!$B$31,MAX(0,K16-(MIN(K16,Parâmetros!$B$8)*Parâmetros!$B$7)-(IF(Parâmetros!$B$15=1,0,Parâmetros!$B$14)*Parâmetros!$B$10))*0.275-Parâmetros!$B$32)))))-IF(K16<=Parâmetros!$B$34,Parâmetros!$B$35-Parâmetros!$B$36*K16,0))) | Q16: =MAX(0,B16-N16-K16) | R16: =B16-N16-O16-P16 | S16: =Parâmetros!$B$21 | T16: =IF(SUM(B5:B16)=0,0,SUM(S5:S16)/SUM(B5:B16)) | U16: =IF(T16>=Parâmetros!$B$6,"III","V") | V16: =IF(U16="III",B16*Parâmetros!$B$4,B16*Parâmetros!$B$5) | W16: =MIN(S16,Parâmetros!$B$8)*Parâmetros!$B$7 | X16: =IF(S16<=Parâmetros!$B$33,0,MAX(0,(IF(MAX(0,S16-(MIN(S16,Parâmetros!$B$8)*Parâmetros!$B$7)-(IF(Parâmetros!$B$15=1,0,Parâmetros!$B$14)*Parâmetros!$B$10))<=Parâmetros!$B$25,0,IF(MAX(0,S16-(MIN(S16,Parâmetros!$B$8)*Parâmetros!$B$7)-(IF(Parâmetros!$B$15=1,0,Parâmetros!$B$14)*Parâmetros!$B$10))<=Parâmetros!$B$26,MAX(0,S16-(MIN(S16,Parâmetros!$B$8)*Parâmetros!$B$7)-(IF(Parâmetros!$B$15=1,0,Parâmetros!$B$14)*Parâmetros!$B$10))*0.075-Parâmetros!$B$29,IF(MAX(0,S16-(MIN(S16,Parâmetros!$B$8)*Parâmetros!$B$7)-(IF(Parâmetros!$B$15=1,0,Parâmetros!$B$14)*Parâmetros!$B$10))<=Parâmetros!$B$27,MAX(0,S16-(MIN(S16,Parâmetros!$B$8)*Parâmetros!$B$7)-(IF(Parâmetros!$B$15=1,0,Parâmetros!$B$14)*Parâmetros!$B$10))*0.15-Parâmetros!$B$30,IF(MAX(0,S16-(MIN(S16,Parâmetros!$B$8)*Parâmetros!$B$7)-(IF(Parâmetros!$B$15=1,0,Parâmetros!$B$14)*Parâmetros!$B$10))<=Parâmetros!$B$28,MAX(0,S16-(MIN(S16,Parâmetros!$B$8)*Parâmetros!$B$7)-(IF(Parâmetros!$B$15=1,0,Parâmetros!$B$14)*Parâmetros!$B$10))*0.225-Parâmetros!$B$31,MAX(0,S16-(MIN(S16,Parâmetros!$B$8)*Parâmetros!$B$7)-(IF(Parâmetros!$B$15=1,0,Parâmetros!$B$14)*Parâmetros!$B$10))*0.275-Parâmetros!$B$32)))))-IF(S16<=Parâmetros!$B$34,Parâmetros!$B$35-Parâmetros!$B$36*S16,0))) | Y16: =MAX(0,B16-V16-S16) | Z16: =B16-V16-W16-X16
A17: 46023 | B17: =Notas!G18 | C17: =Parâmetros!$B$19 | D17: =IF(SUM(B6:B17)=0,0,SUM(C6:C17)/SUM(B6:B17)) | E17: =IF(D17>=Parâmetros!$B$6,"III","V") | F17: =IF(E17="III",B17*Parâmetros!$B$4,B17*Parâmetros!$B$5) | G17: =MIN(C17,Parâmetros!$B$8)*Parâmetros!$B$7 | H17: =IF(C17<=Parâmetros!$B$33,0,MAX(0,(IF(MAX(0,C17-(MIN(C17,Parâmetros!$B$8)*Parâmetros!$B$7)-(IF(Parâmetros!$B$15=1,0,Parâmetros!$B$14)*Parâmetros!$B$10))<=Parâmetros!$B$25,0,IF(MAX(0,C17-(MIN(C17,Parâmetros!$B$8)*Parâmetros!$B$7)-(IF(Parâmetros!$B$15=1,0,Parâmetros!$B$14)*Parâmetros!$B$10))<=Parâmetros!$B$26,MAX(0,C17-(MIN(C17,Parâmetros!$B$8)*Parâmetros!$B$7)-(IF(Parâmetros!$B$15=1,0,Parâmetros!$B$14)*Parâmetros!$B$10))*0.075-Parâmetros!$B$29,IF(MAX(0,C17-(MIN(C17,Parâmetros!$B$8)*Parâmetros!$B$7)-(IF(Parâmetros!$B$15=1,0,Parâmetros!$B$14)*Parâmetros!$B$10))<=Parâmetros!$B$27,MAX(0,C17-(MIN(C17,Parâmetros!$B$8)*Parâmetros!$B$7)-(IF(Parâmetros!$B$15=1,0,Parâmetros!$B$14)*Parâmetros!$B$10))*0.15-Parâmetros!$B$30,IF(MAX(0,C17-(MIN(C17,Parâmetros!$B$8)*Parâmetros!$B$7)-(IF(Parâmetros!$B$15=1,0,Parâmetros!$B$14)*Parâmetros!$B$10))<=Parâmetros!$B$28,MAX(0,C17-(MIN(C17,Parâmetros!$B$8)*Parâmetros!$B$7)-(IF(Parâmetros!$B$15=1,0,Parâmetros!$B$14)*Parâmetros!$B$10))*0.225-Parâmetros!$B$31,MAX(0,C17-(MIN(C17,Parâmetros!$B$8)*Parâmetros!$B$7)-(IF(Parâmetros!$B$15=1,0,Parâmetros!$B$14)*Parâmetros!$B$10))*0.275-Parâmetros!$B$32)))))-IF(C17<=Parâmetros!$B$34,Parâmetros!$B$35-Parâmetros!$B$36*C17,0))) | I17: =MAX(0,B17-F17-C17) | J17: =B17-F17-G17-H17 | K17: =IF(A17<Parâmetros!$B$23,Parâmetros!$B$19,MAX(Parâmetros!$B$22,Parâmetros!$B$6*SUM(B6:B17)-SUM(K6:K16))) | L17: =IF(SUM(B6:B17)=0,0,SUM(K6:K17)/SUM(B6:B17)) | M17: =IF(L17>=Parâmetros!$B$6,"III","V") | N17: =IF(M17="III",B17*Parâmetros!$B$4,B17*Parâmetros!$B$5) | O17: =MIN(K17,Parâmetros!$B$8)*Parâmetros!$B$7 | P17: =IF(K17<=Parâmetros!$B$33,0,MAX(0,(IF(MAX(0,K17-(MIN(K17,Parâmetros!$B$8)*Parâmetros!$B$7)-(IF(Parâmetros!$B$15=1,0,Parâmetros!$B$14)*Parâmetros!$B$10))<=Parâmetros!$B$25,0,IF(MAX(0,K17-(MIN(K17,Parâmetros!$B$8)*Parâmetros!$B$7)-(IF(Parâmetros!$B$15=1,0,Parâmetros!$B$14)*Parâmetros!$B$10))<=Parâmetros!$B$26,MAX(0,K17-(MIN(K17,Parâmetros!$B$8)*Parâmetros!$B$7)-(IF(Parâmetros!$B$15=1,0,Parâmetros!$B$14)*Parâmetros!$B$10))*0.075-Parâmetros!$B$29,IF(MAX(0,K17-(MIN(K17,Parâmetros!$B$8)*Parâmetros!$B$7)-(IF(Parâmetros!$B$15=1,0,Parâmetros!$B$14)*Parâmetros!$B$10))<=Parâmetros!$B$27,MAX(0,K17-(MIN(K17,Parâmetros!$B$8)*Parâmetros!$B$7)-(IF(Parâmetros!$B$15=1,0,Parâmetros!$B$14)*Parâmetros!$B$10))*0.15-Parâmetros!$B$30,IF(MAX(0,K17-(MIN(K17,Parâmetros!$B$8)*Parâmetros!$B$7)-(IF(Parâmetros!$B$15=1,0,Parâmetros!$B$14)*Parâmetros!$B$10))<=Parâmetros!$B$28,MAX(0,K17-(MIN(K17,Parâmetros!$B$8)*Parâmetros!$B$7)-(IF(Parâmetros!$B$15=1,0,Parâmetros!$B$14)*Parâmetros!$B$10))*0.225-Parâmetros!$B$31,MAX(0,K17-(MIN(K17,Parâmetros!$B$8)*Parâmetros!$B$7)-(IF(Parâmetros!$B$15=1,0,Parâmetros!$B$14)*Parâmetros!$B$10))*0.275-Parâmetros!$B$32)))))-IF(K17<=Parâmetros!$B$34,Parâmetros!$B$35-Parâmetros!$B$36*K17,0))) | Q17: =MAX(0,B17-N17-K17) | R17: =B17-N17-O17-P17 | S17: =Parâmetros!$B$21 | T17: =IF(SUM(B6:B17)=0,0,SUM(S6:S17)/SUM(B6:B17)) | U17: =IF(T17>=Parâmetros!$B$6,"III","V") | V17: =IF(U17="III",B17*Parâmetros!$B$4,B17*Parâmetros!$B$5) | W17: =MIN(S17,Parâmetros!$B$8)*Parâmetros!$B$7 | X17: =IF(S17<=Parâmetros!$B$33,0,MAX(0,(IF(MAX(0,S17-(MIN(S17,Parâmetros!$B$8)*Parâmetros!$B$7)-(IF(Parâmetros!$B$15=1,0,Parâmetros!$B$14)*Parâmetros!$B$10))<=Parâmetros!$B$25,0,IF(MAX(0,S17-(MIN(S17,Parâmetros!$B$8)*Parâmetros!$B$7)-(IF(Parâmetros!$B$15=1,0,Parâmetros!$B$14)*Parâmetros!$B$10))<=Parâmetros!$B$26,MAX(0,S17-(MIN(S17,Parâmetros!$B$8)*Parâmetros!$B$7)-(IF(Parâmetros!$B$15=1,0,Parâmetros!$B$14)*Parâmetros!$B$10))*0.075-Parâmetros!$B$29,IF(MAX(0,S17-(MIN(S17,Parâmetros!$B$8)*Parâmetros!$B$7)-(IF(Parâmetros!$B$15=1,0,Parâmetros!$B$14)*Parâmetros!$B$10))<=Parâmetros!$B$27,MAX(0,S17-(MIN(S17,Parâmetros!$B$8)*Parâmetros!$B$7)-(IF(Parâmetros!$B$15=1,0,Parâmetros!$B$14)*Parâmetros!$B$10))*0.15-Parâmetros!$B$30,IF(MAX(0,S17-(MIN(S17,Parâmetros!$B$8)*Parâmetros!$B$7)-(IF(Parâmetros!$B$15=1,0,Parâmetros!$B$14)*Parâmetros!$B$10))<=Parâmetros!$B$28,MAX(0,S17-(MIN(S17,Parâmetros!$B$8)*Parâmetros!$B$7)-(IF(Parâmetros!$B$15=1,0,Parâmetros!$B$14)*Parâmetros!$B$10))*0.225-Parâmetros!$B$31,MAX(0,S17-(MIN(S17,Parâmetros!$B$8)*Parâmetros!$B$7)-(IF(Parâmetros!$B$15=1,0,Parâmetros!$B$14)*Parâmetros!$B$10))*0.275-Parâmetros!$B$32)))))-IF(S17<=Parâmetros!$B$34,Parâmetros!$B$35-Parâmetros!$B$36*S17,0))) | Y17: =MAX(0,B17-V17-S17) | Z17: =B17-V17-W17-X17
A18: 46054 | B18: =Notas!G19 | C18: =Parâmetros!$B$19 | D18: =IF(SUM(B7:B18)=0,0,SUM(C7:C18)/SUM(B7:B18)) | E18: =IF(D18>=Parâmetros!$B$6,"III","V") | F18: =IF(E18="III",B18*Parâmetros!$B$4,B18*Parâmetros!$B$5) | G18: =MIN(C18,Parâmetros!$B$8)*Parâmetros!$B$7 | H18: =IF(C18<=Parâmetros!$B$33,0,MAX(0,(IF(MAX(0,C18-(MIN(C18,Parâmetros!$B$8)*Parâmetros!$B$7)-(IF(Parâmetros!$B$15=1,0,Parâmetros!$B$14)*Parâmetros!$B$10))<=Parâmetros!$B$25,0,IF(MAX(0,C18-(MIN(C18,Parâmetros!$B$8)*Parâmetros!$B$7)-(IF(Parâmetros!$B$15=1,0,Parâmetros!$B$14)*Parâmetros!$B$10))<=Parâmetros!$B$26,MAX(0,C18-(MIN(C18,Parâmetros!$B$8)*Parâmetros!$B$7)-(IF(Parâmetros!$B$15=1,0,Parâmetros!$B$14)*Parâmetros!$B$10))*0.075-Parâmetros!$B$29,IF(MAX(0,C18-(MIN(C18,Parâmetros!$B$8)*Parâmetros!$B$7)-(IF(Parâmetros!$B$15=1,0,Parâmetros!$B$14)*Parâmetros!$B$10))<=Parâmetros!$B$27,MAX(0,C18-(MIN(C18,Parâmetros!$B$8)*Parâmetros!$B$7)-(IF(Parâmetros!$B$15=1,0,Parâmetros!$B$14)*Parâmetros!$B$10))*0.15-Parâmetros!$B$30,IF(MAX(0,C18-(MIN(C18,Parâmetros!$B$8)*Parâmetros!$B$7)-(IF(Parâmetros!$B$15=1,0,Parâmetros!$B$14)*Parâmetros!$B$10))<=Parâmetros!$B$28,MAX(0,C18-(MIN(C18,Parâmetros!$B$8)*Parâmetros!$B$7)-(IF(Parâmetros!$B$15=1,0,Parâmetros!$B$14)*Parâmetros!$B$10))*0.225-Parâmetros!$B$31,MAX(0,C18-(MIN(C18,Parâmetros!$B$8)*Parâmetros!$B$7)-(IF(Parâmetros!$B$15=1,0,Parâmetros!$B$14)*Parâmetros!$B$10))*0.275-Parâmetros!$B$32)))))-IF(C18<=Parâmetros!$B$34,Parâmetros!$B$35-Parâmetros!$B$36*C18,0))) | I18: =MAX(0,B18-F18-C18) | J18: =B18-F18-G18-H18 | K18: =IF(A18<Parâmetros!$B$23,Parâmetros!$B$19,MAX(Parâmetros!$B$22,Parâmetros!$B$6*SUM(B7:B18)-SUM(K7:K17))) | L18: =IF(SUM(B7:B18)=0,0,SUM(K7:K18)/SUM(B7:B18)) | M18: =IF(L18>=Parâmetros!$B$6,"III","V") | N18: =IF(M18="III",B18*Parâmetros!$B$4,B18*Parâmetros!$B$5) | O18: =MIN(K18,Parâmetros!$B$8)*Parâmetros!$B$7 | P18: =IF(K18<=Parâmetros!$B$33,0,MAX(0,(IF(MAX(0,K18-(MIN(K18,Parâmetros!$B$8)*Parâmetros!$B$7)-(IF(Parâmetros!$B$15=1,0,Parâmetros!$B$14)*Parâmetros!$B$10))<=Parâmetros!$B$25,0,IF(MAX(0,K18-(MIN(K18,Parâmetros!$B$8)*Parâmetros!$B$7)-(IF(Parâmetros!$B$15=1,0,Parâmetros!$B$14)*Parâmetros!$B$10))<=Parâmetros!$B$26,MAX(0,K18-(MIN(K18,Parâmetros!$B$8)*Parâmetros!$B$7)-(IF(Parâmetros!$B$15=1,0,Parâmetros!$B$14)*Parâmetros!$B$10))*0.075-Parâmetros!$B$29,IF(MAX(0,K18-(MIN(K18,Parâmetros!$B$8)*Parâmetros!$B$7)-(IF(Parâmetros!$B$15=1,0,Parâmetros!$B$14)*Parâmetros!$B$10))<=Parâmetros!$B$27,MAX(0,K18-(MIN(K18,Parâmetros!$B$8)*Parâmetros!$B$7)-(IF(Parâmetros!$B$15=1,0,Parâmetros!$B$14)*Parâmetros!$B$10))*0.15-Parâmetros!$B$30,IF(MAX(0,K18-(MIN(K18,Parâmetros!$B$8)*Parâmetros!$B$7)-(IF(Parâmetros!$B$15=1,0,Parâmetros!$B$14)*Parâmetros!$B$10))<=Parâmetros!$B$28,MAX(0,K18-(MIN(K18,Parâmetros!$B$8)*Parâmetros!$B$7)-(IF(Parâmetros!$B$15=1,0,Parâmetros!$B$14)*Parâmetros!$B$10))*0.225-Parâmetros!$B$31,MAX(0,K18-(MIN(K18,Parâmetros!$B$8)*Parâmetros!$B$7)-(IF(Parâmetros!$B$15=1,0,Parâmetros!$B$14)*Parâmetros!$B$10))*0.275-Parâmetros!$B$32)))))-IF(K18<=Parâmetros!$B$34,Parâmetros!$B$35-Parâmetros!$B$36*K18,0))) | Q18: =MAX(0,B18-N18-K18) | R18: =B18-N18-O18-P18 | S18: =Parâmetros!$B$21 | T18: =IF(SUM(B7:B18)=0,0,SUM(S7:S18)/SUM(B7:B18)) | U18: =IF(T18>=Parâmetros!$B$6,"III","V") | V18: =IF(U18="III",B18*Parâmetros!$B$4,B18*Parâmetros!$B$5) | W18: =MIN(S18,Parâmetros!$B$8)*Parâmetros!$B$7 | X18: =IF(S18<=Parâmetros!$B$33,0,MAX(0,(IF(MAX(0,S18-(MIN(S18,Parâmetros!$B$8)*Parâmetros!$B$7)-(IF(Parâmetros!$B$15=1,0,Parâmetros!$B$14)*Parâmetros!$B$10))<=Parâmetros!$B$25,0,IF(MAX(0,S18-(MIN(S18,Parâmetros!$B$8)*Parâmetros!$B$7)-(IF(Parâmetros!$B$15=1,0,Parâmetros!$B$14)*Parâmetros!$B$10))<=Parâmetros!$B$26,MAX(0,S18-(MIN(S18,Parâmetros!$B$8)*Parâmetros!$B$7)-(IF(Parâmetros!$B$15=1,0,Parâmetros!$B$14)*Parâmetros!$B$10))*0.075-Parâmetros!$B$29,IF(MAX(0,S18-(MIN(S18,Parâmetros!$B$8)*Parâmetros!$B$7)-(IF(Parâmetros!$B$15=1,0,Parâmetros!$B$14)*Parâmetros!$B$10))<=Parâmetros!$B$27,MAX(0,S18-(MIN(S18,Parâmetros!$B$8)*Parâmetros!$B$7)-(IF(Parâmetros!$B$15=1,0,Parâmetros!$B$14)*Parâmetros!$B$10))*0.15-Parâmetros!$B$30,IF(MAX(0,S18-(MIN(S18,Parâmetros!$B$8)*Parâmetros!$B$7)-(IF(Parâmetros!$B$15=1,0,Parâmetros!$B$14)*Parâmetros!$B$10))<=Parâmetros!$B$28,MAX(0,S18-(MIN(S18,Parâmetros!$B$8)*Parâmetros!$B$7)-(IF(Parâmetros!$B$15=1,0,Parâmetros!$B$14)*Parâmetros!$B$10))*0.225-Parâmetros!$B$31,MAX(0,S18-(MIN(S18,Parâmetros!$B$8)*Parâmetros!$B$7)-(IF(Parâmetros!$B$15=1,0,Parâmetros!$B$14)*Parâmetros!$B$10))*0.275-Parâmetros!$B$32)))))-IF(S18<=Parâmetros!$B$34,Parâmetros!$B$35-Parâmetros!$B$36*S18,0))) | Y18: =MAX(0,B18-V18-S18) | Z18: =B18-V18-W18-X18
A19: 46082 | B19: =Notas!G20 | C19: =Parâmetros!$B$19 | D19: =IF(SUM(B8:B19)=0,0,SUM(C8:C19)/SUM(B8:B19)) | E19: =IF(D19>=Parâmetros!$B$6,"III","V") | F19: =IF(E19="III",B19*Parâmetros!$B$4,B19*Parâmetros!$B$5) | G19: =MIN(C19,Parâmetros!$B$8)*Parâmetros!$B$7 | H19: =IF(C19<=Parâmetros!$B$33,0,MAX(0,(IF(MAX(0,C19-(MIN(C19,Parâmetros!$B$8)*Parâmetros!$B$7)-(IF(Parâmetros!$B$15=1,0,Parâmetros!$B$14)*Parâmetros!$B$10))<=Parâmetros!$B$25,0,IF(MAX(0,C19-(MIN(C19,Parâmetros!$B$8)*Parâmetros!$B$7)-(IF(Parâmetros!$B$15=1,0,Parâmetros!$B$14)*Parâmetros!$B$10))<=Parâmetros!$B$26,MAX(0,C19-(MIN(C19,Parâmetros!$B$8)*Parâmetros!$B$7)-(IF(Parâmetros!$B$15=1,0,Parâmetros!$B$14)*Parâmetros!$B$10))*0.075-Parâmetros!$B$29,IF(MAX(0,C19-(MIN(C19,Parâmetros!$B$8)*Parâmetros!$B$7)-(IF(Parâmetros!$B$15=1,0,Parâmetros!$B$14)*Parâmetros!$B$10))<=Parâmetros!$B$27,MAX(0,C19-(MIN(C19,Parâmetros!$B$8)*Parâmetros!$B$7)-(IF(Parâmetros!$B$15=1,0,Parâmetros!$B$14)*Parâmetros!$B$10))*0.15-Parâmetros!$B$30,IF(MAX(0,C19-(MIN(C19,Parâmetros!$B$8)*Parâmetros!$B$7)-(IF(Parâmetros!$B$15=1,0,Parâmetros!$B$14)*Parâmetros!$B$10))<=Parâmetros!$B$28,MAX(0,C19-(MIN(C19,Parâmetros!$B$8)*Parâmetros!$B$7)-(IF(Parâmetros!$B$15=1,0,Parâmetros!$B$14)*Parâmetros!$B$10))*0.225-Parâmetros!$B$31,MAX(0,C19-(MIN(C19,Parâmetros!$B$8)*Parâmetros!$B$7)-(IF(Parâmetros!$B$15=1,0,Parâmetros!$B$14)*Parâmetros!$B$10))*0.275-Parâmetros!$B$32)))))-IF(C19<=Parâmetros!$B$34,Parâmetros!$B$35-Parâmetros!$B$36*C19,0))) | I19: =MAX(0,B19-F19-C19) | J19: =B19-F19-G19-H19 | K19: =IF(A19<Parâmetros!$B$23,Parâmetros!$B$19,MAX(Parâmetros!$B$22,Parâmetros!$B$6*SUM(B8:B19)-SUM(K8:K18))) | L19: =IF(SUM(B8:B19)=0,0,SUM(K8:K19)/SUM(B8:B19)) | M19: =IF(L19>=Parâmetros!$B$6,"III","V") | N19: =IF(M19="III",B19*Parâmetros!$B$4,B19*Parâmetros!$B$5) | O19: =MIN(K19,Parâmetros!$B$8)*Parâmetros!$B$7 | P19: =IF(K19<=Parâmetros!$B$33,0,MAX(0,(IF(MAX(0,K19-(MIN(K19,Parâmetros!$B$8)*Parâmetros!$B$7)-(IF(Parâmetros!$B$15=1,0,Parâmetros!$B$14)*Parâmetros!$B$10))<=Parâmetros!$B$25,0,IF(MAX(0,K19-(MIN(K19,Parâmetros!$B$8)*Parâmetros!$B$7)-(IF(Parâmetros!$B$15=1,0,Parâmetros!$B$14)*Parâmetros!$B$10))<=Parâmetros!$B$26,MAX(0,K19-(MIN(K19,Parâmetros!$B$8)*Parâmetros!$B$7)-(IF(Parâmetros!$B$15=1,0,Parâmetros!$B$14)*Parâmetros!$B$10))*0.075-Parâmetros!$B$29,IF(MAX(0,K19-(MIN(K19,Parâmetros!$B$8)*Parâmetros!$B$7)-(IF(Parâmetros!$B$15=1,0,Parâmetros!$B$14)*Parâmetros!$B$10))<=Parâmetros!$B$27,MAX(0,K19-(MIN(K19,Parâmetros!$B$8)*Parâmetros!$B$7)-(IF(Parâmetros!$B$15=1,0,Parâmetros!$B$14)*Parâmetros!$B$10))*0.15-Parâmetros!$B$30,IF(MAX(0,K19-(MIN(K19,Parâmetros!$B$8)*Parâmetros!$B$7)-(IF(Parâmetros!$B$15=1,0,Parâmetros!$B$14)*Parâmetros!$B$10))<=Parâmetros!$B$28,MAX(0,K19-(MIN(K19,Parâmetros!$B$8)*Parâmetros!$B$7)-(IF(Parâmetros!$B$15=1,0,Parâmetros!$B$14)*Parâmetros!$B$10))*0.225-Parâmetros!$B$31,MAX(0,K19-(MIN(K19,Parâmetros!$B$8)*Parâmetros!$B$7)-(IF(Parâmetros!$B$15=1,0,Parâmetros!$B$14)*Parâmetros!$B$10))*0.275-Parâmetros!$B$32)))))-IF(K19<=Parâmetros!$B$34,Parâmetros!$B$35-Parâmetros!$B$36*K19,0))) | Q19: =MAX(0,B19-N19-K19) | R19: =B19-N19-O19-P19 | S19: =Parâmetros!$B$21 | T19: =IF(SUM(B8:B19)=0,0,SUM(S8:S19)/SUM(B8:B19)) | U19: =IF(T19>=Parâmetros!$B$6,"III","V") | V19: =IF(U19="III",B19*Parâmetros!$B$4,B19*Parâmetros!$B$5) | W19: =MIN(S19,Parâmetros!$B$8)*Parâmetros!$B$7 | X19: =IF(S19<=Parâmetros!$B$33,0,MAX(0,(IF(MAX(0,S19-(MIN(S19,Parâmetros!$B$8)*Parâmetros!$B$7)-(IF(Parâmetros!$B$15=1,0,Parâmetros!$B$14)*Parâmetros!$B$10))<=Parâmetros!$B$25,0,IF(MAX(0,S19-(MIN(S19,Parâmetros!$B$8)*Parâmetros!$B$7)-(IF(Parâmetros!$B$15=1,0,Parâmetros!$B$14)*Parâmetros!$B$10))<=Parâmetros!$B$26,MAX(0,S19-(MIN(S19,Parâmetros!$B$8)*Parâmetros!$B$7)-(IF(Parâmetros!$B$15=1,0,Parâmetros!$B$14)*Parâmetros!$B$10))*0.075-Parâmetros!$B$29,IF(MAX(0,S19-(MIN(S19,Parâmetros!$B$8)*Parâmetros!$B$7)-(IF(Parâmetros!$B$15=1,0,Parâmetros!$B$14)*Parâmetros!$B$10))<=Parâmetros!$B$27,MAX(0,S19-(MIN(S19,Parâmetros!$B$8)*Parâmetros!$B$7)-(IF(Parâmetros!$B$15=1,0,Parâmetros!$B$14)*Parâmetros!$B$10))*0.15-Parâmetros!$B$30,IF(MAX(0,S19-(MIN(S19,Parâmetros!$B$8)*Parâmetros!$B$7)-(IF(Parâmetros!$B$15=1,0,Parâmetros!$B$14)*Parâmetros!$B$10))<=Parâmetros!$B$28,MAX(0,S19-(MIN(S19,Parâmetros!$B$8)*Parâmetros!$B$7)-(IF(Parâmetros!$B$15=1,0,Parâmetros!$B$14)*Parâmetros!$B$10))*0.225-Parâmetros!$B$31,MAX(0,S19-(MIN(S19,Parâmetros!$B$8)*Parâmetros!$B$7)-(IF(Parâmetros!$B$15=1,0,Parâmetros!$B$14)*Parâmetros!$B$10))*0.275-Parâmetros!$B$32)))))-IF(S19<=Parâmetros!$B$34,Parâmetros!$B$35-Parâmetros!$B$36*S19,0))) | Y19: =MAX(0,B19-V19-S19) | Z19: =B19-V19-W19-X19
A20: 46113 | B20: =Notas!G21 | C20: =Parâmetros!$B$19 | D20: =IF(SUM(B9:B20)=0,0,SUM(C9:C20)/SUM(B9:B20)) | E20: =IF(D20>=Parâmetros!$B$6,"III","V") | F20: =IF(E20="III",B20*Parâmetros!$B$4,B20*Parâmetros!$B$5) | G20: =MIN(C20,Parâmetros!$B$8)*Parâmetros!$B$7 | H20: =IF(C20<=Parâmetros!$B$33,0,MAX(0,(IF(MAX(0,C20-(MIN(C20,Parâmetros!$B$8)*Parâmetros!$B$7)-(IF(Parâmetros!$B$15=1,0,Parâmetros!$B$14)*Parâmetros!$B$10))<=Parâmetros!$B$25,0,IF(MAX(0,C20-(MIN(C20,Parâmetros!$B$8)*Parâmetros!$B$7)-(IF(Parâmetros!$B$15=1,0,Parâmetros!$B$14)*Parâmetros!$B$10))<=Parâmetros!$B$26,MAX(0,C20-(MIN(C20,Parâmetros!$B$8)*Parâmetros!$B$7)-(IF(Parâmetros!$B$15=1,0,Parâmetros!$B$14)*Parâmetros!$B$10))*0.075-Parâmetros!$B$29,IF(MAX(0,C20-(MIN(C20,Parâmetros!$B$8)*Parâmetros!$B$7)-(IF(Parâmetros!$B$15=1,0,Parâmetros!$B$14)*Parâmetros!$B$10))<=Parâmetros!$B$27,MAX(0,C20-(MIN(C20,Parâmetros!$B$8)*Parâmetros!$B$7)-(IF(Parâmetros!$B$15=1,0,Parâmetros!$B$14)*Parâmetros!$B$10))*0.15-Parâmetros!$B$30,IF(MAX(0,C20-(MIN(C20,Parâmetros!$B$8)*Parâmetros!$B$7)-(IF(Parâmetros!$B$15=1,0,Parâmetros!$B$14)*Parâmetros!$B$10))<=Parâmetros!$B$28,MAX(0,C20-(MIN(C20,Parâmetros!$B$8)*Parâmetros!$B$7)-(IF(Parâmetros!$B$15=1,0,Parâmetros!$B$14)*Parâmetros!$B$10))*0.225-Parâmetros!$B$31,MAX(0,C20-(MIN(C20,Parâmetros!$B$8)*Parâmetros!$B$7)-(IF(Parâmetros!$B$15=1,0,Parâmetros!$B$14)*Parâmetros!$B$10))*0.275-Parâmetros!$B$32)))))-IF(C20<=Parâmetros!$B$34,Parâmetros!$B$35-Parâmetros!$B$36*C20,0))) | I20: =MAX(0,B20-F20-C20) | J20: =B20-F20-G20-H20 | K20: =IF(A20<Parâmetros!$B$23,Parâmetros!$B$19,MAX(Parâmetros!$B$22,Parâmetros!$B$6*SUM(B9:B20)-SUM(K9:K19))) | L20: =IF(SUM(B9:B20)=0,0,SUM(K9:K20)/SUM(B9:B20)) | M20: =IF(L20>=Parâmetros!$B$6,"III","V") | N20: =IF(M20="III",B20*Parâmetros!$B$4,B20*Parâmetros!$B$5) | O20: =MIN(K20,Parâmetros!$B$8)*Parâmetros!$B$7 | P20: =IF(K20<=Parâmetros!$B$33,0,MAX(0,(IF(MAX(0,K20-(MIN(K20,Parâmetros!$B$8)*Parâmetros!$B$7)-(IF(Parâmetros!$B$15=1,0,Parâmetros!$B$14)*Parâmetros!$B$10))<=Parâmetros!$B$25,0,IF(MAX(0,K20-(MIN(K20,Parâmetros!$B$8)*Parâmetros!$B$7)-(IF(Parâmetros!$B$15=1,0,Parâmetros!$B$14)*Parâmetros!$B$10))<=Parâmetros!$B$26,MAX(0,K20-(MIN(K20,Parâmetros!$B$8)*Parâmetros!$B$7)-(IF(Parâmetros!$B$15=1,0,Parâmetros!$B$14)*Parâmetros!$B$10))*0.075-Parâmetros!$B$29,IF(MAX(0,K20-(MIN(K20,Parâmetros!$B$8)*Parâmetros!$B$7)-(IF(Parâmetros!$B$15=1,0,Parâmetros!$B$14)*Parâmetros!$B$10))<=Parâmetros!$B$27,MAX(0,K20-(MIN(K20,Parâmetros!$B$8)*Parâmetros!$B$7)-(IF(Parâmetros!$B$15=1,0,Parâmetros!$B$14)*Parâmetros!$B$10))*0.15-Parâmetros!$B$30,IF(MAX(0,K20-(MIN(K20,Parâmetros!$B$8)*Parâmetros!$B$7)-(IF(Parâmetros!$B$15=1,0,Parâmetros!$B$14)*Parâmetros!$B$10))<=Parâmetros!$B$28,MAX(0,K20-(MIN(K20,Parâmetros!$B$8)*Parâmetros!$B$7)-(IF(Parâmetros!$B$15=1,0,Parâmetros!$B$14)*Parâmetros!$B$10))*0.225-Parâmetros!$B$31,MAX(0,K20-(MIN(K20,Parâmetros!$B$8)*Parâmetros!$B$7)-(IF(Parâmetros!$B$15=1,0,Parâmetros!$B$14)*Parâmetros!$B$10))*0.275-Parâmetros!$B$32)))))-IF(K20<=Parâmetros!$B$34,Parâmetros!$B$35-Parâmetros!$B$36*K20,0))) | Q20: =MAX(0,B20-N20-K20) | R20: =B20-N20-O20-P20 | S20: =Parâmetros!$B$21 | T20: =IF(SUM(B9:B20)=0,0,SUM(S9:S20)/SUM(B9:B20)) | U20: =IF(T20>=Parâmetros!$B$6,"III","V") | V20: =IF(U20="III",B20*Parâmetros!$B$4,B20*Parâmetros!$B$5) | W20: =MIN(S20,Parâmetros!$B$8)*Parâmetros!$B$7 | X20: =IF(S20<=Parâmetros!$B$33,0,MAX(0,(IF(MAX(0,S20-(MIN(S20,Parâmetros!$B$8)*Parâmetros!$B$7)-(IF(Parâmetros!$B$15=1,0,Parâmetros!$B$14)*Parâmetros!$B$10))<=Parâmetros!$B$25,0,IF(MAX(0,S20-(MIN(S20,Parâmetros!$B$8)*Parâmetros!$B$7)-(IF(Parâmetros!$B$15=1,0,Parâmetros!$B$14)*Parâmetros!$B$10))<=Parâmetros!$B$26,MAX(0,S20-(MIN(S20,Parâmetros!$B$8)*Parâmetros!$B$7)-(IF(Parâmetros!$B$15=1,0,Parâmetros!$B$14)*Parâmetros!$B$10))*0.075-Parâmetros!$B$29,IF(MAX(0,S20-(MIN(S20,Parâmetros!$B$8)*Parâmetros!$B$7)-(IF(Parâmetros!$B$15=1,0,Parâmetros!$B$14)*Parâmetros!$B$10))<=Parâmetros!$B$27,MAX(0,S20-(MIN(S20,Parâmetros!$B$8)*Parâmetros!$B$7)-(IF(Parâmetros!$B$15=1,0,Parâmetros!$B$14)*Parâmetros!$B$10))*0.15-Parâmetros!$B$30,IF(MAX(0,S20-(MIN(S20,Parâmetros!$B$8)*Parâmetros!$B$7)-(IF(Parâmetros!$B$15=1,0,Parâmetros!$B$14)*Parâmetros!$B$10))<=Parâmetros!$B$28,MAX(0,S20-(MIN(S20,Parâmetros!$B$8)*Parâmetros!$B$7)-(IF(Parâmetros!$B$15=1,0,Parâmetros!$B$14)*Parâmetros!$B$10))*0.225-Parâmetros!$B$31,MAX(0,S20-(MIN(S20,Parâmetros!$B$8)*Parâmetros!$B$7)-(IF(Parâmetros!$B$15=1,0,Parâmetros!$B$14)*Parâmetros!$B$10))*0.275-Parâmetros!$B$32)))))-IF(S20<=Parâmetros!$B$34,Parâmetros!$B$35-Parâmetros!$B$36*S20,0))) | Y20: =MAX(0,B20-V20-S20) | Z20: =B20-V20-W20-X20
A21: 46143 | B21: =Notas!G22 | C21: =Parâmetros!$B$19 | D21: =IF(SUM(B10:B21)=0,0,SUM(C10:C21)/SUM(B10:B21)) | E21: =IF(D21>=Parâmetros!$B$6,"III","V") | F21: =IF(E21="III",B21*Parâmetros!$B$4,B21*Parâmetros!$B$5) | G21: =MIN(C21,Parâmetros!$B$8)*Parâmetros!$B$7 | H21: =IF(C21<=Parâmetros!$B$33,0,MAX(0,(IF(MAX(0,C21-(MIN(C21,Parâmetros!$B$8)*Parâmetros!$B$7)-(IF(Parâmetros!$B$15=1,0,Parâmetros!$B$14)*Parâmetros!$B$10))<=Parâmetros!$B$25,0,IF(MAX(0,C21-(MIN(C21,Parâmetros!$B$8)*Parâmetros!$B$7)-(IF(Parâmetros!$B$15=1,0,Parâmetros!$B$14)*Parâmetros!$B$10))<=Parâmetros!$B$26,MAX(0,C21-(MIN(C21,Parâmetros!$B$8)*Parâmetros!$B$7)-(IF(Parâmetros!$B$15=1,0,Parâmetros!$B$14)*Parâmetros!$B$10))*0.075-Parâmetros!$B$29,IF(MAX(0,C21-(MIN(C21,Parâmetros!$B$8)*Parâmetros!$B$7)-(IF(Parâmetros!$B$15=1,0,Parâmetros!$B$14)*Parâmetros!$B$10))<=Parâmetros!$B$27,MAX(0,C21-(MIN(C21,Parâmetros!$B$8)*Parâmetros!$B$7)-(IF(Parâmetros!$B$15=1,0,Parâmetros!$B$14)*Parâmetros!$B$10))*0.15-Parâmetros!$B$30,IF(MAX(0,C21-(MIN(C21,Parâmetros!$B$8)*Parâmetros!$B$7)-(IF(Parâmetros!$B$15=1,0,Parâmetros!$B$14)*Parâmetros!$B$10))<=Parâmetros!$B$28,MAX(0,C21-(MIN(C21,Parâmetros!$B$8)*Parâmetros!$B$7)-(IF(Parâmetros!$B$15=1,0,Parâmetros!$B$14)*Parâmetros!$B$10))*0.225-Parâmetros!$B$31,MAX(0,C21-(MIN(C21,Parâmetros!$B$8)*Parâmetros!$B$7)-(IF(Parâmetros!$B$15=1,0,Parâmetros!$B$14)*Parâmetros!$B$10))*0.275-Parâmetros!$B$32)))))-IF(C21<=Parâmetros!$B$34,Parâmetros!$B$35-Parâmetros!$B$36*C21,0))) | I21: =MAX(0,B21-F21-C21) | J21: =B21-F21-G21-H21 | K21: =IF(A21<Parâmetros!$B$23,Parâmetros!$B$19,MAX(Parâmetros!$B$22,Parâmetros!$B$6*SUM(B10:B21)-SUM(K10:K20))) | L21: =IF(SUM(B10:B21)=0,0,SUM(K10:K21)/SUM(B10:B21)) | M21: =IF(L21>=Parâmetros!$B$6,"III","V") | N21: =IF(M21="III",B21*Parâmetros!$B$4,B21*Parâmetros!$B$5) | O21: =MIN(K21,Parâmetros!$B$8)*Parâmetros!$B$7 | P21: =IF(K21<=Parâmetros!$B$33,0,MAX(0,(IF(MAX(0,K21-(MIN(K21,Parâmetros!$B$8)*Parâmetros!$B$7)-(IF(Parâmetros!$B$15=1,0,Parâmetros!$B$14)*Parâmetros!$B$10))<=Parâmetros!$B$25,0,IF(MAX(0,K21-(MIN(K21,Parâmetros!$B$8)*Parâmetros!$B$7)-(IF(Parâmetros!$B$15=1,0,Parâmetros!$B$14)*Parâmetros!$B$10))<=Parâmetros!$B$26,MAX(0,K21-(MIN(K21,Parâmetros!$B$8)*Parâmetros!$B$7)-(IF(Parâmetros!$B$15=1,0,Parâmetros!$B$14)*Parâmetros!$B$10))*0.075-Parâmetros!$B$29,IF(MAX(0,K21-(MIN(K21,Parâmetros!$B$8)*Parâmetros!$B$7)-(IF(Parâmetros!$B$15=1,0,Parâmetros!$B$14)*Parâmetros!$B$10))<=Parâmetros!$B$27,MAX(0,K21-(MIN(K21,Parâmetros!$B$8)*Parâmetros!$B$7)-(IF(Parâmetros!$B$15=1,0,Parâmetros!$B$14)*Parâmetros!$B$10))*0.15-Parâmetros!$B$30,IF(MAX(0,K21-(MIN(K21,Parâmetros!$B$8)*Parâmetros!$B$7)-(IF(Parâmetros!$B$15=1,0,Parâmetros!$B$14)*Parâmetros!$B$10))<=Parâmetros!$B$28,MAX(0,K21-(MIN(K21,Parâmetros!$B$8)*Parâmetros!$B$7)-(IF(Parâmetros!$B$15=1,0,Parâmetros!$B$14)*Parâmetros!$B$10))*0.225-Parâmetros!$B$31,MAX(0,K21-(MIN(K21,Parâmetros!$B$8)*Parâmetros!$B$7)-(IF(Parâmetros!$B$15=1,0,Parâmetros!$B$14)*Parâmetros!$B$10))*0.275-Parâmetros!$B$32)))))-IF(K21<=Parâmetros!$B$34,Parâmetros!$B$35-Parâmetros!$B$36*K21,0))) | Q21: =MAX(0,B21-N21-K21) | R21: =B21-N21-O21-P21 | S21: =Parâmetros!$B$21 | T21: =IF(SUM(B10:B21)=0,0,SUM(S10:S21)/SUM(B10:B21)) | U21: =IF(T21>=Parâmetros!$B$6,"III","V") | V21: =IF(U21="III",B21*Parâmetros!$B$4,B21*Parâmetros!$B$5) | W21: =MIN(S21,Parâmetros!$B$8)*Parâmetros!$B$7 | X21: =IF(S21<=Parâmetros!$B$33,0,MAX(0,(IF(MAX(0,S21-(MIN(S21,Parâmetros!$B$8)*Parâmetros!$B$7)-(IF(Parâmetros!$B$15=1,0,Parâmetros!$B$14)*Parâmetros!$B$10))<=Parâmetros!$B$25,0,IF(MAX(0,S21-(MIN(S21,Parâmetros!$B$8)*Parâmetros!$B$7)-(IF(Parâmetros!$B$15=1,0,Parâmetros!$B$14)*Parâmetros!$B$10))<=Parâmetros!$B$26,MAX(0,S21-(MIN(S21,Parâmetros!$B$8)*Parâmetros!$B$7)-(IF(Parâmetros!$B$15=1,0,Parâmetros!$B$14)*Parâmetros!$B$10))*0.075-Parâmetros!$B$29,IF(MAX(0,S21-(MIN(S21,Parâmetros!$B$8)*Parâmetros!$B$7)-(IF(Parâmetros!$B$15=1,0,Parâmetros!$B$14)*Parâmetros!$B$10))<=Parâmetros!$B$27,MAX(0,S21-(MIN(S21,Parâmetros!$B$8)*Parâmetros!$B$7)-(IF(Parâmetros!$B$15=1,0,Parâmetros!$B$14)*Parâmetros!$B$10))*0.15-Parâmetros!$B$30,IF(MAX(0,S21-(MIN(S21,Parâmetros!$B$8)*Parâmetros!$B$7)-(IF(Parâmetros!$B$15=1,0,Parâmetros!$B$14)*Parâmetros!$B$10))<=Parâmetros!$B$28,MAX(0,S21-(MIN(S21,Parâmetros!$B$8)*Parâmetros!$B$7)-(IF(Parâmetros!$B$15=1,0,Parâmetros!$B$14)*Parâmetros!$B$10))*0.225-Parâmetros!$B$31,MAX(0,S21-(MIN(S21,Parâmetros!$B$8)*Parâmetros!$B$7)-(IF(Parâmetros!$B$15=1,0,Parâmetros!$B$14)*Parâmetros!$B$10))*0.275-Parâmetros!$B$32)))))-IF(S21<=Parâmetros!$B$34,Parâmetros!$B$35-Parâmetros!$B$36*S21,0))) | Y21: =MAX(0,B21-V21-S21) | Z21: =B21-V21-W21-X21
A22: 46174 | B22: =Notas!G23 | C22: =Parâmetros!$B$19 | D22: =IF(SUM(B11:B22)=0,0,SUM(C11:C22)/SUM(B11:B22)) | E22: =IF(D22>=Parâmetros!$B$6,"III","V") | F22: =IF(E22="III",B22*Parâmetros!$B$4,B22*Parâmetros!$B$5) | G22: =MIN(C22,Parâmetros!$B$8)*Parâmetros!$B$7 | H22: =IF(C22<=Parâmetros!$B$33,0,MAX(0,(IF(MAX(0,C22-(MIN(C22,Parâmetros!$B$8)*Parâmetros!$B$7)-(IF(Parâmetros!$B$15=1,0,Parâmetros!$B$14)*Parâmetros!$B$10))<=Parâmetros!$B$25,0,IF(MAX(0,C22-(MIN(C22,Parâmetros!$B$8)*Parâmetros!$B$7)-(IF(Parâmetros!$B$15=1,0,Parâmetros!$B$14)*Parâmetros!$B$10))<=Parâmetros!$B$26,MAX(0,C22-(MIN(C22,Parâmetros!$B$8)*Parâmetros!$B$7)-(IF(Parâmetros!$B$15=1,0,Parâmetros!$B$14)*Parâmetros!$B$10))*0.075-Parâmetros!$B$29,IF(MAX(0,C22-(MIN(C22,Parâmetros!$B$8)*Parâmetros!$B$7)-(IF(Parâmetros!$B$15=1,0,Parâmetros!$B$14)*Parâmetros!$B$10))<=Parâmetros!$B$27,MAX(0,C22-(MIN(C22,Parâmetros!$B$8)*Parâmetros!$B$7)-(IF(Parâmetros!$B$15=1,0,Parâmetros!$B$14)*Parâmetros!$B$10))*0.15-Parâmetros!$B$30,IF(MAX(0,C22-(MIN(C22,Parâmetros!$B$8)*Parâmetros!$B$7)-(IF(Parâmetros!$B$15=1,0,Parâmetros!$B$14)*Parâmetros!$B$10))<=Parâmetros!$B$28,MAX(0,C22-(MIN(C22,Parâmetros!$B$8)*Parâmetros!$B$7)-(IF(Parâmetros!$B$15=1,0,Parâmetros!$B$14)*Parâmetros!$B$10))*0.225-Parâmetros!$B$31,MAX(0,C22-(MIN(C22,Parâmetros!$B$8)*Parâmetros!$B$7)-(IF(Parâmetros!$B$15=1,0,Parâmetros!$B$14)*Parâmetros!$B$10))*0.275-Parâmetros!$B$32)))))-IF(C22<=Parâmetros!$B$34,Parâmetros!$B$35-Parâmetros!$B$36*C22,0))) | I22: =MAX(0,B22-F22-C22) | J22: =B22-F22-G22-H22 | K22: =IF(A22<Parâmetros!$B$23,Parâmetros!$B$19,MAX(Parâmetros!$B$22,Parâmetros!$B$6*SUM(B11:B22)-SUM(K11:K21))) | L22: =IF(SUM(B11:B22)=0,0,SUM(K11:K22)/SUM(B11:B22)) | M22: =IF(L22>=Parâmetros!$B$6,"III","V") | N22: =IF(M22="III",B22*Parâmetros!$B$4,B22*Parâmetros!$B$5) | O22: =MIN(K22,Parâmetros!$B$8)*Parâmetros!$B$7 | P22: =IF(K22<=Parâmetros!$B$33,0,MAX(0,(IF(MAX(0,K22-(MIN(K22,Parâmetros!$B$8)*Parâmetros!$B$7)-(IF(Parâmetros!$B$15=1,0,Parâmetros!$B$14)*Parâmetros!$B$10))<=Parâmetros!$B$25,0,IF(MAX(0,K22-(MIN(K22,Parâmetros!$B$8)*Parâmetros!$B$7)-(IF(Parâmetros!$B$15=1,0,Parâmetros!$B$14)*Parâmetros!$B$10))<=Parâmetros!$B$26,MAX(0,K22-(MIN(K22,Parâmetros!$B$8)*Parâmetros!$B$7)-(IF(Parâmetros!$B$15=1,0,Parâmetros!$B$14)*Parâmetros!$B$10))*0.075-Parâmetros!$B$29,IF(MAX(0,K22-(MIN(K22,Parâmetros!$B$8)*Parâmetros!$B$7)-(IF(Parâmetros!$B$15=1,0,Parâmetros!$B$14)*Parâmetros!$B$10))<=Parâmetros!$B$27,MAX(0,K22-(MIN(K22,Parâmetros!$B$8)*Parâmetros!$B$7)-(IF(Parâmetros!$B$15=1,0,Parâmetros!$B$14)*Parâmetros!$B$10))*0.15-Parâmetros!$B$30,IF(MAX(0,K22-(MIN(K22,Parâmetros!$B$8)*Parâmetros!$B$7)-(IF(Parâmetros!$B$15=1,0,Parâmetros!$B$14)*Parâmetros!$B$10))<=Parâmetros!$B$28,MAX(0,K22-(MIN(K22,Parâmetros!$B$8)*Parâmetros!$B$7)-(IF(Parâmetros!$B$15=1,0,Parâmetros!$B$14)*Parâmetros!$B$10))*0.225-Parâmetros!$B$31,MAX(0,K22-(MIN(K22,Parâmetros!$B$8)*Parâmetros!$B$7)-(IF(Parâmetros!$B$15=1,0,Parâmetros!$B$14)*Parâmetros!$B$10))*0.275-Parâmetros!$B$32)))))-IF(K22<=Parâmetros!$B$34,Parâmetros!$B$35-Parâmetros!$B$36*K22,0))) | Q22: =MAX(0,B22-N22-K22) | R22: =B22-N22-O22-P22 | S22: =Parâmetros!$B$21 | T22: =IF(SUM(B11:B22)=0,0,SUM(S11:S22)/SUM(B11:B22)) | U22: =IF(T22>=Parâmetros!$B$6,"III","V") | V22: =IF(U22="III",B22*Parâmetros!$B$4,B22*Parâmetros!$B$5) | W22: =MIN(S22,Parâmetros!$B$8)*Parâmetros!$B$7 | X22: =IF(S22<=Parâmetros!$B$33,0,MAX(0,(IF(MAX(0,S22-(MIN(S22,Parâmetros!$B$8)*Parâmetros!$B$7)-(IF(Parâmetros!$B$15=1,0,Parâmetros!$B$14)*Parâmetros!$B$10))<=Parâmetros!$B$25,0,IF(MAX(0,S22-(MIN(S22,Parâmetros!$B$8)*Parâmetros!$B$7)-(IF(Parâmetros!$B$15=1,0,Parâmetros!$B$14)*Parâmetros!$B$10))<=Parâmetros!$B$26,MAX(0,S22-(MIN(S22,Parâmetros!$B$8)*Parâmetros!$B$7)-(IF(Parâmetros!$B$15=1,0,Parâmetros!$B$14)*Parâmetros!$B$10))*0.075-Parâmetros!$B$29,IF(MAX(0,S22-(MIN(S22,Parâmetros!$B$8)*Parâmetros!$B$7)-(IF(Parâmetros!$B$15=1,0,Parâmetros!$B$14)*Parâmetros!$B$10))<=Parâmetros!$B$27,MAX(0,S22-(MIN(S22,Parâmetros!$B$8)*Parâmetros!$B$7)-(IF(Parâmetros!$B$15=1,0,Parâmetros!$B$14)*Parâmetros!$B$10))*0.15-Parâmetros!$B$30,IF(MAX(0,S22-(MIN(S22,Parâmetros!$B$8)*Parâmetros!$B$7)-(IF(Parâmetros!$B$15=1,0,Parâmetros!$B$14)*Parâmetros!$B$10))<=Parâmetros!$B$28,MAX(0,S22-(MIN(S22,Parâmetros!$B$8)*Parâmetros!$B$7)-(IF(Parâmetros!$B$15=1,0,Parâmetros!$B$14)*Parâmetros!$B$10))*0.225-Parâmetros!$B$31,MAX(0,S22-(MIN(S22,Parâmetros!$B$8)*Parâmetros!$B$7)-(IF(Parâmetros!$B$15=1,0,Parâmetros!$B$14)*Parâmetros!$B$10))*0.275-Parâmetros!$B$32)))))-IF(S22<=Parâmetros!$B$34,Parâmetros!$B$35-Parâmetros!$B$36*S22,0))) | Y22: =MAX(0,B22-V22-S22) | Z22: =B22-V22-W22-X22
A23: 46204 | B23: =Notas!G24 | C23: =Parâmetros!$B$19 | D23: =IF(SUM(B12:B23)=0,0,SUM(C12:C23)/SUM(B12:B23)) | E23: =IF(D23>=Parâmetros!$B$6,"III","V") | F23: =IF(E23="III",B23*Parâmetros!$B$4,B23*Parâmetros!$B$5) | G23: =MIN(C23,Parâmetros!$B$8)*Parâmetros!$B$7 | H23: =IF(C23<=Parâmetros!$B$33,0,MAX(0,(IF(MAX(0,C23-(MIN(C23,Parâmetros!$B$8)*Parâmetros!$B$7)-(IF(Parâmetros!$B$15=1,0,Parâmetros!$B$14)*Parâmetros!$B$10))<=Parâmetros!$B$25,0,IF(MAX(0,C23-(MIN(C23,Parâmetros!$B$8)*Parâmetros!$B$7)-(IF(Parâmetros!$B$15=1,0,Parâmetros!$B$14)*Parâmetros!$B$10))<=Parâmetros!$B$26,MAX(0,C23-(MIN(C23,Parâmetros!$B$8)*Parâmetros!$B$7)-(IF(Parâmetros!$B$15=1,0,Parâmetros!$B$14)*Parâmetros!$B$10))*0.075-Parâmetros!$B$29,IF(MAX(0,C23-(MIN(C23,Parâmetros!$B$8)*Parâmetros!$B$7)-(IF(Parâmetros!$B$15=1,0,Parâmetros!$B$14)*Parâmetros!$B$10))<=Parâmetros!$B$27,MAX(0,C23-(MIN(C23,Parâmetros!$B$8)*Parâmetros!$B$7)-(IF(Parâmetros!$B$15=1,0,Parâmetros!$B$14)*Parâmetros!$B$10))*0.15-Parâmetros!$B$30,IF(MAX(0,C23-(MIN(C23,Parâmetros!$B$8)*Parâmetros!$B$7)-(IF(Parâmetros!$B$15=1,0,Parâmetros!$B$14)*Parâmetros!$B$10))<=Parâmetros!$B$28,MAX(0,C23-(MIN(C23,Parâmetros!$B$8)*Parâmetros!$B$7)-(IF(Parâmetros!$B$15=1,0,Parâmetros!$B$14)*Parâmetros!$B$10))*0.225-Parâmetros!$B$31,MAX(0,C23-(MIN(C23,Parâmetros!$B$8)*Parâmetros!$B$7)-(IF(Parâmetros!$B$15=1,0,Parâmetros!$B$14)*Parâmetros!$B$10))*0.275-Parâmetros!$B$32)))))-IF(C23<=Parâmetros!$B$34,Parâmetros!$B$35-Parâmetros!$B$36*C23,0))) | I23: =MAX(0,B23-F23-C23) | J23: =B23-F23-G23-H23 | K23: =IF(A23<Parâmetros!$B$23,Parâmetros!$B$19,MAX(Parâmetros!$B$22,Parâmetros!$B$6*SUM(B12:B23)-SUM(K12:K22))) | L23: =IF(SUM(B12:B23)=0,0,SUM(K12:K23)/SUM(B12:B23)) | M23: =IF(L23>=Parâmetros!$B$6,"III","V") | N23: =IF(M23="III",B23*Parâmetros!$B$4,B23*Parâmetros!$B$5) | O23: =MIN(K23,Parâmetros!$B$8)*Parâmetros!$B$7 | P23: =IF(K23<=Parâmetros!$B$33,0,MAX(0,(IF(MAX(0,K23-(MIN(K23,Parâmetros!$B$8)*Parâmetros!$B$7)-(IF(Parâmetros!$B$15=1,0,Parâmetros!$B$14)*Parâmetros!$B$10))<=Parâmetros!$B$25,0,IF(MAX(0,K23-(MIN(K23,Parâmetros!$B$8)*Parâmetros!$B$7)-(IF(Parâmetros!$B$15=1,0,Parâmetros!$B$14)*Parâmetros!$B$10))<=Parâmetros!$B$26,MAX(0,K23-(MIN(K23,Parâmetros!$B$8)*Parâmetros!$B$7)-(IF(Parâmetros!$B$15=1,0,Parâmetros!$B$14)*Parâmetros!$B$10))*0.075-Parâmetros!$B$29,IF(MAX(0,K23-(MIN(K23,Parâmetros!$B$8)*Parâmetros!$B$7)-(IF(Parâmetros!$B$15=1,0,Parâmetros!$B$14)*Parâmetros!$B$10))<=Parâmetros!$B$27,MAX(0,K23-(MIN(K23,Parâmetros!$B$8)*Parâmetros!$B$7)-(IF(Parâmetros!$B$15=1,0,Parâmetros!$B$14)*Parâmetros!$B$10))*0.15-Parâmetros!$B$30,IF(MAX(0,K23-(MIN(K23,Parâmetros!$B$8)*Parâmetros!$B$7)-(IF(Parâmetros!$B$15=1,0,Parâmetros!$B$14)*Parâmetros!$B$10))<=Parâmetros!$B$28,MAX(0,K23-(MIN(K23,Parâmetros!$B$8)*Parâmetros!$B$7)-(IF(Parâmetros!$B$15=1,0,Parâmetros!$B$14)*Parâmetros!$B$10))*0.225-Parâmetros!$B$31,MAX(0,K23-(MIN(K23,Parâmetros!$B$8)*Parâmetros!$B$7)-(IF(Parâmetros!$B$15=1,0,Parâmetros!$B$14)*Parâmetros!$B$10))*0.275-Parâmetros!$B$32)))))-IF(K23<=Parâmetros!$B$34,Parâmetros!$B$35-Parâmetros!$B$36*K23,0))) | Q23: =MAX(0,B23-N23-K23) | R23: =B23-N23-O23-P23 | S23: =Parâmetros!$B$21 | T23: =IF(SUM(B12:B23)=0,0,SUM(S12:S23)/SUM(B12:B23)) | U23: =IF(T23>=Parâmetros!$B$6,"III","V") | V23: =IF(U23="III",B23*Parâmetros!$B$4,B23*Parâmetros!$B$5) | W23: =MIN(S23,Parâmetros!$B$8)*Parâmetros!$B$7 | X23: =IF(S23<=Parâmetros!$B$33,0,MAX(0,(IF(MAX(0,S23-(MIN(S23,Parâmetros!$B$8)*Parâmetros!$B$7)-(IF(Parâmetros!$B$15=1,0,Parâmetros!$B$14)*Parâmetros!$B$10))<=Parâmetros!$B$25,0,IF(MAX(0,S23-(MIN(S23,Parâmetros!$B$8)*Parâmetros!$B$7)-(IF(Parâmetros!$B$15=1,0,Parâmetros!$B$14)*Parâmetros!$B$10))<=Parâmetros!$B$26,MAX(0,S23-(MIN(S23,Parâmetros!$B$8)*Parâmetros!$B$7)-(IF(Parâmetros!$B$15=1,0,Parâmetros!$B$14)*Parâmetros!$B$10))*0.075-Parâmetros!$B$29,IF(MAX(0,S23-(MIN(S23,Parâmetros!$B$8)*Parâmetros!$B$7)-(IF(Parâmetros!$B$15=1,0,Parâmetros!$B$14)*Parâmetros!$B$10))<=Parâmetros!$B$27,MAX(0,S23-(MIN(S23,Parâmetros!$B$8)*Parâmetros!$B$7)-(IF(Parâmetros!$B$15=1,0,Parâmetros!$B$14)*Parâmetros!$B$10))*0.15-Parâmetros!$B$30,IF(MAX(0,S23-(MIN(S23,Parâmetros!$B$8)*Parâmetros!$B$7)-(IF(Parâmetros!$B$15=1,0,Parâmetros!$B$14)*Parâmetros!$B$10))<=Parâmetros!$B$28,MAX(0,S23-(MIN(S23,Parâmetros!$B$8)*Parâmetros!$B$7)-(IF(Parâmetros!$B$15=1,0,Parâmetros!$B$14)*Parâmetros!$B$10))*0.225-Parâmetros!$B$31,MAX(0,S23-(MIN(S23,Parâmetros!$B$8)*Parâmetros!$B$7)-(IF(Parâmetros!$B$15=1,0,Parâmetros!$B$14)*Parâmetros!$B$10))*0.275-Parâmetros!$B$32)))))-IF(S23<=Parâmetros!$B$34,Parâmetros!$B$35-Parâmetros!$B$36*S23,0))) | Y23: =MAX(0,B23-V23-S23) | Z23: =B23-V23-W23-X23
A24: 46235 | B24: =Notas!G25 | C24: =Parâmetros!$B$19 | D24: =IF(SUM(B13:B24)=0,0,SUM(C13:C24)/SUM(B13:B24)) | E24: =IF(D24>=Parâmetros!$B$6,"III","V") | F24: =IF(E24="III",B24*Parâmetros!$B$4,B24*Parâmetros!$B$5) | G24: =MIN(C24,Parâmetros!$B$8)*Parâmetros!$B$7 | H24: =IF(C24<=Parâmetros!$B$33,0,MAX(0,(IF(MAX(0,C24-(MIN(C24,Parâmetros!$B$8)*Parâmetros!$B$7)-(IF(Parâmetros!$B$15=1,0,Parâmetros!$B$14)*Parâmetros!$B$10))<=Parâmetros!$B$25,0,IF(MAX(0,C24-(MIN(C24,Parâmetros!$B$8)*Parâmetros!$B$7)-(IF(Parâmetros!$B$15=1,0,Parâmetros!$B$14)*Parâmetros!$B$10))<=Parâmetros!$B$26,MAX(0,C24-(MIN(C24,Parâmetros!$B$8)*Parâmetros!$B$7)-(IF(Parâmetros!$B$15=1,0,Parâmetros!$B$14)*Parâmetros!$B$10))*0.075-Parâmetros!$B$29,IF(MAX(0,C24-(MIN(C24,Parâmetros!$B$8)*Parâmetros!$B$7)-(IF(Parâmetros!$B$15=1,0,Parâmetros!$B$14)*Parâmetros!$B$10))<=Parâmetros!$B$27,MAX(0,C24-(MIN(C24,Parâmetros!$B$8)*Parâmetros!$B$7)-(IF(Parâmetros!$B$15=1,0,Parâmetros!$B$14)*Parâmetros!$B$10))*0.15-Parâmetros!$B$30,IF(MAX(0,C24-(MIN(C24,Parâmetros!$B$8)*Parâmetros!$B$7)-(IF(Parâmetros!$B$15=1,0,Parâmetros!$B$14)*Parâmetros!$B$10))<=Parâmetros!$B$28,MAX(0,C24-(MIN(C24,Parâmetros!$B$8)*Parâmetros!$B$7)-(IF(Parâmetros!$B$15=1,0,Parâmetros!$B$14)*Parâmetros!$B$10))*0.225-Parâmetros!$B$31,MAX(0,C24-(MIN(C24,Parâmetros!$B$8)*Parâmetros!$B$7)-(IF(Parâmetros!$B$15=1,0,Parâmetros!$B$14)*Parâmetros!$B$10))*0.275-Parâmetros!$B$32)))))-IF(C24<=Parâmetros!$B$34,Parâmetros!$B$35-Parâmetros!$B$36*C24,0))) | I24: =MAX(0,B24-F24-C24) | J24: =B24-F24-G24-H24 | K24: =IF(A24<Parâmetros!$B$23,Parâmetros!$B$19,MAX(Parâmetros!$B$22,Parâmetros!$B$6*SUM(B13:B24)-SUM(K13:K23))) | L24: =IF(SUM(B13:B24)=0,0,SUM(K13:K24)/SUM(B13:B24)) | M24: =IF(L24>=Parâmetros!$B$6,"III","V") | N24: =IF(M24="III",B24*Parâmetros!$B$4,B24*Parâmetros!$B$5) | O24: =MIN(K24,Parâmetros!$B$8)*Parâmetros!$B$7 | P24: =IF(K24<=Parâmetros!$B$33,0,MAX(0,(IF(MAX(0,K24-(MIN(K24,Parâmetros!$B$8)*Parâmetros!$B$7)-(IF(Parâmetros!$B$15=1,0,Parâmetros!$B$14)*Parâmetros!$B$10))<=Parâmetros!$B$25,0,IF(MAX(0,K24-(MIN(K24,Parâmetros!$B$8)*Parâmetros!$B$7)-(IF(Parâmetros!$B$15=1,0,Parâmetros!$B$14)*Parâmetros!$B$10))<=Parâmetros!$B$26,MAX(0,K24-(MIN(K24,Parâmetros!$B$8)*Parâmetros!$B$7)-(IF(Parâmetros!$B$15=1,0,Parâmetros!$B$14)*Parâmetros!$B$10))*0.075-Parâmetros!$B$29,IF(MAX(0,K24-(MIN(K24,Parâmetros!$B$8)*Parâmetros!$B$7)-(IF(Parâmetros!$B$15=1,0,Parâmetros!$B$14)*Parâmetros!$B$10))<=Parâmetros!$B$27,MAX(0,K24-(MIN(K24,Parâmetros!$B$8)*Parâmetros!$B$7)-(IF(Parâmetros!$B$15=1,0,Parâmetros!$B$14)*Parâmetros!$B$10))*0.15-Parâmetros!$B$30,IF(MAX(0,K24-(MIN(K24,Parâmetros!$B$8)*Parâmetros!$B$7)-(IF(Parâmetros!$B$15=1,0,Parâmetros!$B$14)*Parâmetros!$B$10))<=Parâmetros!$B$28,MAX(0,K24-(MIN(K24,Parâmetros!$B$8)*Parâmetros!$B$7)-(IF(Parâmetros!$B$15=1,0,Parâmetros!$B$14)*Parâmetros!$B$10))*0.225-Parâmetros!$B$31,MAX(0,K24-(MIN(K24,Parâmetros!$B$8)*Parâmetros!$B$7)-(IF(Parâmetros!$B$15=1,0,Parâmetros!$B$14)*Parâmetros!$B$10))*0.275-Parâmetros!$B$32)))))-IF(K24<=Parâmetros!$B$34,Parâmetros!$B$35-Parâmetros!$B$36*K24,0))) | Q24: =MAX(0,B24-N24-K24) | R24: =B24-N24-O24-P24 | S24: =Parâmetros!$B$21 | T24: =IF(SUM(B13:B24)=0,0,SUM(S13:S24)/SUM(B13:B24)) | U24: =IF(T24>=Parâmetros!$B$6,"III","V") | V24: =IF(U24="III",B24*Parâmetros!$B$4,B24*Parâmetros!$B$5) | W24: =MIN(S24,Parâmetros!$B$8)*Parâmetros!$B$7 | X24: =IF(S24<=Parâmetros!$B$33,0,MAX(0,(IF(MAX(0,S24-(MIN(S24,Parâmetros!$B$8)*Parâmetros!$B$7)-(IF(Parâmetros!$B$15=1,0,Parâmetros!$B$14)*Parâmetros!$B$10))<=Parâmetros!$B$25,0,IF(MAX(0,S24-(MIN(S24,Parâmetros!$B$8)*Parâmetros!$B$7)-(IF(Parâmetros!$B$15=1,0,Parâmetros!$B$14)*Parâmetros!$B$10))<=Parâmetros!$B$26,MAX(0,S24-(MIN(S24,Parâmetros!$B$8)*Parâmetros!$B$7)-(IF(Parâmetros!$B$15=1,0,Parâmetros!$B$14)*Parâmetros!$B$10))*0.075-Parâmetros!$B$29,IF(MAX(0,S24-(MIN(S24,Parâmetros!$B$8)*Parâmetros!$B$7)-(IF(Parâmetros!$B$15=1,0,Parâmetros!$B$14)*Parâmetros!$B$10))<=Parâmetros!$B$27,MAX(0,S24-(MIN(S24,Parâmetros!$B$8)*Parâmetros!$B$7)-(IF(Parâmetros!$B$15=1,0,Parâmetros!$B$14)*Parâmetros!$B$10))*0.15-Parâmetros!$B$30,IF(MAX(0,S24-(MIN(S24,Parâmetros!$B$8)*Parâmetros!$B$7)-(IF(Parâmetros!$B$15=1,0,Parâmetros!$B$14)*Parâmetros!$B$10))<=Parâmetros!$B$28,MAX(0,S24-(MIN(S24,Parâmetros!$B$8)*Parâmetros!$B$7)-(IF(Parâmetros!$B$15=1,0,Parâmetros!$B$14)*Parâmetros!$B$10))*0.225-Parâmetros!$B$31,MAX(0,S24-(MIN(S24,Parâmetros!$B$8)*Parâmetros!$B$7)-(IF(Parâmetros!$B$15=1,0,Parâmetros!$B$14)*Parâmetros!$B$10))*0.275-Parâmetros!$B$32)))))-IF(S24<=Parâmetros!$B$34,Parâmetros!$B$35-Parâmetros!$B$36*S24,0))) | Y24: =MAX(0,B24-V24-S24) | Z24: =B24-V24-W24-X24
A25: 46266 | B25: =Notas!G26 | C25: =Parâmetros!$B$19 | D25: =IF(SUM(B14:B25)=0,0,SUM(C14:C25)/SUM(B14:B25)) | E25: =IF(D25>=Parâmetros!$B$6,"III","V") | F25: =IF(E25="III",B25*Parâmetros!$B$4,B25*Parâmetros!$B$5) | G25: =MIN(C25,Parâmetros!$B$8)*Parâmetros!$B$7 | H25: =IF(C25<=Parâmetros!$B$33,0,MAX(0,(IF(MAX(0,C25-(MIN(C25,Parâmetros!$B$8)*Parâmetros!$B$7)-(IF(Parâmetros!$B$15=1,0,Parâmetros!$B$14)*Parâmetros!$B$10))<=Parâmetros!$B$25,0,IF(MAX(0,C25-(MIN(C25,Parâmetros!$B$8)*Parâmetros!$B$7)-(IF(Parâmetros!$B$15=1,0,Parâmetros!$B$14)*Parâmetros!$B$10))<=Parâmetros!$B$26,MAX(0,C25-(MIN(C25,Parâmetros!$B$8)*Parâmetros!$B$7)-(IF(Parâmetros!$B$15=1,0,Parâmetros!$B$14)*Parâmetros!$B$10))*0.075-Parâmetros!$B$29,IF(MAX(0,C25-(MIN(C25,Parâmetros!$B$8)*Parâmetros!$B$7)-(IF(Parâmetros!$B$15=1,0,Parâmetros!$B$14)*Parâmetros!$B$10))<=Parâmetros!$B$27,MAX(0,C25-(MIN(C25,Parâmetros!$B$8)*Parâmetros!$B$7)-(IF(Parâmetros!$B$15=1,0,Parâmetros!$B$14)*Parâmetros!$B$10))*0.15-Parâmetros!$B$30,IF(MAX(0,C25-(MIN(C25,Parâmetros!$B$8)*Parâmetros!$B$7)-(IF(Parâmetros!$B$15=1,0,Parâmetros!$B$14)*Parâmetros!$B$10))<=Parâmetros!$B$28,MAX(0,C25-(MIN(C25,Parâmetros!$B$8)*Parâmetros!$B$7)-(IF(Parâmetros!$B$15=1,0,Parâmetros!$B$14)*Parâmetros!$B$10))*0.225-Parâmetros!$B$31,MAX(0,C25-(MIN(C25,Parâmetros!$B$8)*Parâmetros!$B$7)-(IF(Parâmetros!$B$15=1,0,Parâmetros!$B$14)*Parâmetros!$B$10))*0.275-Parâmetros!$B$32)))))-IF(C25<=Parâmetros!$B$34,Parâmetros!$B$35-Parâmetros!$B$36*C25,0))) | I25: =MAX(0,B25-F25-C25) | J25: =B25-F25-G25-H25 | K25: =IF(A25<Parâmetros!$B$23,Parâmetros!$B$19,MAX(Parâmetros!$B$22,Parâmetros!$B$6*SUM(B14:B25)-SUM(K14:K24))) | L25: =IF(SUM(B14:B25)=0,0,SUM(K14:K25)/SUM(B14:B25)) | M25: =IF(L25>=Parâmetros!$B$6,"III","V") | N25: =IF(M25="III",B25*Parâmetros!$B$4,B25*Parâmetros!$B$5) | O25: =MIN(K25,Parâmetros!$B$8)*Parâmetros!$B$7 | P25: =IF(K25<=Parâmetros!$B$33,0,MAX(0,(IF(MAX(0,K25-(MIN(K25,Parâmetros!$B$8)*Parâmetros!$B$7)-(IF(Parâmetros!$B$15=1,0,Parâmetros!$B$14)*Parâmetros!$B$10))<=Parâmetros!$B$25,0,IF(MAX(0,K25-(MIN(K25,Parâmetros!$B$8)*Parâmetros!$B$7)-(IF(Parâmetros!$B$15=1,0,Parâmetros!$B$14)*Parâmetros!$B$10))<=Parâmetros!$B$26,MAX(0,K25-(MIN(K25,Parâmetros!$B$8)*Parâmetros!$B$7)-(IF(Parâmetros!$B$15=1,0,Parâmetros!$B$14)*Parâmetros!$B$10))*0.075-Parâmetros!$B$29,IF(MAX(0,K25-(MIN(K25,Parâmetros!$B$8)*Parâmetros!$B$7)-(IF(Parâmetros!$B$15=1,0,Parâmetros!$B$14)*Parâmetros!$B$10))<=Parâmetros!$B$27,MAX(0,K25-(MIN(K25,Parâmetros!$B$8)*Parâmetros!$B$7)-(IF(Parâmetros!$B$15=1,0,Parâmetros!$B$14)*Parâmetros!$B$10))*0.15-Parâmetros!$B$30,IF(MAX(0,K25-(MIN(K25,Parâmetros!$B$8)*Parâmetros!$B$7)-(IF(Parâmetros!$B$15=1,0,Parâmetros!$B$14)*Parâmetros!$B$10))<=Parâmetros!$B$28,MAX(0,K25-(MIN(K25,Parâmetros!$B$8)*Parâmetros!$B$7)-(IF(Parâmetros!$B$15=1,0,Parâmetros!$B$14)*Parâmetros!$B$10))*0.225-Parâmetros!$B$31,MAX(0,K25-(MIN(K25,Parâmetros!$B$8)*Parâmetros!$B$7)-(IF(Parâmetros!$B$15=1,0,Parâmetros!$B$14)*Parâmetros!$B$10))*0.275-Parâmetros!$B$32)))))-IF(K25<=Parâmetros!$B$34,Parâmetros!$B$35-Parâmetros!$B$36*K25,0))) | Q25: =MAX(0,B25-N25-K25) | R25: =B25-N25-O25-P25 | S25: =Parâmetros!$B$21 | T25: =IF(SUM(B14:B25)=0,0,SUM(S14:S25)/SUM(B14:B25)) | U25: =IF(T25>=Parâmetros!$B$6,"III","V") | V25: =IF(U25="III",B25*Parâmetros!$B$4,B25*Parâmetros!$B$5) | W25: =MIN(S25,Parâmetros!$B$8)*Parâmetros!$B$7 | X25: =IF(S25<=Parâmetros!$B$33,0,MAX(0,(IF(MAX(0,S25-(MIN(S25,Parâmetros!$B$8)*Parâmetros!$B$7)-(IF(Parâmetros!$B$15=1,0,Parâmetros!$B$14)*Parâmetros!$B$10))<=Parâmetros!$B$25,0,IF(MAX(0,S25-(MIN(S25,Parâmetros!$B$8)*Parâmetros!$B$7)-(IF(Parâmetros!$B$15=1,0,Parâmetros!$B$14)*Parâmetros!$B$10))<=Parâmetros!$B$26,MAX(0,S25-(MIN(S25,Parâmetros!$B$8)*Parâmetros!$B$7)-(IF(Parâmetros!$B$15=1,0,Parâmetros!$B$14)*Parâmetros!$B$10))*0.075-Parâmetros!$B$29,IF(MAX(0,S25-(MIN(S25,Parâmetros!$B$8)*Parâmetros!$B$7)-(IF(Parâmetros!$B$15=1,0,Parâmetros!$B$14)*Parâmetros!$B$10))<=Parâmetros!$B$27,MAX(0,S25-(MIN(S25,Parâmetros!$B$8)*Parâmetros!$B$7)-(IF(Parâmetros!$B$15=1,0,Parâmetros!$B$14)*Parâmetros!$B$10))*0.15-Parâmetros!$B$30,IF(MAX(0,S25-(MIN(S25,Parâmetros!$B$8)*Parâmetros!$B$7)-(IF(Parâmetros!$B$15=1,0,Parâmetros!$B$14)*Parâmetros!$B$10))<=Parâmetros!$B$28,MAX(0,S25-(MIN(S25,Parâmetros!$B$8)*Parâmetros!$B$7)-(IF(Parâmetros!$B$15=1,0,Parâmetros!$B$14)*Parâmetros!$B$10))*0.225-Parâmetros!$B$31,MAX(0,S25-(MIN(S25,Parâmetros!$B$8)*Parâmetros!$B$7)-(IF(Parâmetros!$B$15=1,0,Parâmetros!$B$14)*Parâmetros!$B$10))*0.275-Parâmetros!$B$32)))))-IF(S25<=Parâmetros!$B$34,Parâmetros!$B$35-Parâmetros!$B$36*S25,0))) | Y25: =MAX(0,B25-V25-S25) | Z25: =B25-V25-W25-X25
A26: 46296 | B26: =Notas!G27 | C26: =Parâmetros!$B$19 | D26: =IF(SUM(B15:B26)=0,0,SUM(C15:C26)/SUM(B15:B26)) | E26: =IF(D26>=Parâmetros!$B$6,"III","V") | F26: =IF(E26="III",B26*Parâmetros!$B$4,B26*Parâmetros!$B$5) | G26: =MIN(C26,Parâmetros!$B$8)*Parâmetros!$B$7 | H26: =IF(C26<=Parâmetros!$B$33,0,MAX(0,(IF(MAX(0,C26-(MIN(C26,Parâmetros!$B$8)*Parâmetros!$B$7)-(IF(Parâmetros!$B$15=1,0,Parâmetros!$B$14)*Parâmetros!$B$10))<=Parâmetros!$B$25,0,IF(MAX(0,C26-(MIN(C26,Parâmetros!$B$8)*Parâmetros!$B$7)-(IF(Parâmetros!$B$15=1,0,Parâmetros!$B$14)*Parâmetros!$B$10))<=Parâmetros!$B$26,MAX(0,C26-(MIN(C26,Parâmetros!$B$8)*Parâmetros!$B$7)-(IF(Parâmetros!$B$15=1,0,Parâmetros!$B$14)*Parâmetros!$B$10))*0.075-Parâmetros!$B$29,IF(MAX(0,C26-(MIN(C26,Parâmetros!$B$8)*Parâmetros!$B$7)-(IF(Parâmetros!$B$15=1,0,Parâmetros!$B$14)*Parâmetros!$B$10))<=Parâmetros!$B$27,MAX(0,C26-(MIN(C26,Parâmetros!$B$8)*Parâmetros!$B$7)-(IF(Parâmetros!$B$15=1,0,Parâmetros!$B$14)*Parâmetros!$B$10))*0.15-Parâmetros!$B$30,IF(MAX(0,C26-(MIN(C26,Parâmetros!$B$8)*Parâmetros!$B$7)-(IF(Parâmetros!$B$15=1,0,Parâmetros!$B$14)*Parâmetros!$B$10))<=Parâmetros!$B$28,MAX(0,C26-(MIN(C26,Parâmetros!$B$8)*Parâmetros!$B$7)-(IF(Parâmetros!$B$15=1,0,Parâmetros!$B$14)*Parâmetros!$B$10))*0.225-Parâmetros!$B$31,MAX(0,C26-(MIN(C26,Parâmetros!$B$8)*Parâmetros!$B$7)-(IF(Parâmetros!$B$15=1,0,Parâmetros!$B$14)*Parâmetros!$B$10))*0.275-Parâmetros!$B$32)))))-IF(C26<=Parâmetros!$B$34,Parâmetros!$B$35-Parâmetros!$B$36*C26,0))) | I26: =MAX(0,B26-F26-C26) | J26: =B26-F26-G26-H26 | K26: =IF(A26<Parâmetros!$B$23,Parâmetros!$B$19,MAX(Parâmetros!$B$22,Parâmetros!$B$6*SUM(B15:B26)-SUM(K15:K25))) | L26: =IF(SUM(B15:B26)=0,0,SUM(K15:K26)/SUM(B15:B26)) | M26: =IF(L26>=Parâmetros!$B$6,"III","V") | N26: =IF(M26="III",B26*Parâmetros!$B$4,B26*Parâmetros!$B$5) | O26: =MIN(K26,Parâmetros!$B$8)*Parâmetros!$B$7 | P26: =IF(K26<=Parâmetros!$B$33,0,MAX(0,(IF(MAX(0,K26-(MIN(K26,Parâmetros!$B$8)*Parâmetros!$B$7)-(IF(Parâmetros!$B$15=1,0,Parâmetros!$B$14)*Parâmetros!$B$10))<=Parâmetros!$B$25,0,IF(MAX(0,K26-(MIN(K26,Parâmetros!$B$8)*Parâmetros!$B$7)-(IF(Parâmetros!$B$15=1,0,Parâmetros!$B$14)*Parâmetros!$B$10))<=Parâmetros!$B$26,MAX(0,K26-(MIN(K26,Parâmetros!$B$8)*Parâmetros!$B$7)-(IF(Parâmetros!$B$15=1,0,Parâmetros!$B$14)*Parâmetros!$B$10))*0.075-Parâmetros!$B$29,IF(MAX(0,K26-(MIN(K26,Parâmetros!$B$8)*Parâmetros!$B$7)-(IF(Parâmetros!$B$15=1,0,Parâmetros!$B$14)*Parâmetros!$B$10))<=Parâmetros!$B$27,MAX(0,K26-(MIN(K26,Parâmetros!$B$8)*Parâmetros!$B$7)-(IF(Parâmetros!$B$15=1,0,Parâmetros!$B$14)*Parâmetros!$B$10))*0.15-Parâmetros!$B$30,IF(MAX(0,K26-(MIN(K26,Parâmetros!$B$8)*Parâmetros!$B$7)-(IF(Parâmetros!$B$15=1,0,Parâmetros!$B$14)*Parâmetros!$B$10))<=Parâmetros!$B$28,MAX(0,K26-(MIN(K26,Parâmetros!$B$8)*Parâmetros!$B$7)-(IF(Parâmetros!$B$15=1,0,Parâmetros!$B$14)*Parâmetros!$B$10))*0.225-Parâmetros!$B$31,MAX(0,K26-(MIN(K26,Parâmetros!$B$8)*Parâmetros!$B$7)-(IF(Parâmetros!$B$15=1,0,Parâmetros!$B$14)*Parâmetros!$B$10))*0.275-Parâmetros!$B$32)))))-IF(K26<=Parâmetros!$B$34,Parâmetros!$B$35-Parâmetros!$B$36*K26,0))) | Q26: =MAX(0,B26-N26-K26) | R26: =B26-N26-O26-P26 | S26: =Parâmetros!$B$21 | T26: =IF(SUM(B15:B26)=0,0,SUM(S15:S26)/SUM(B15:B26)) | U26: =IF(T26>=Parâmetros!$B$6,"III","V") | V26: =IF(U26="III",B26*Parâmetros!$B$4,B26*Parâmetros!$B$5) | W26: =MIN(S26,Parâmetros!$B$8)*Parâmetros!$B$7 | X26: =IF(S26<=Parâmetros!$B$33,0,MAX(0,(IF(MAX(0,S26-(MIN(S26,Parâmetros!$B$8)*Parâmetros!$B$7)-(IF(Parâmetros!$B$15=1,0,Parâmetros!$B$14)*Parâmetros!$B$10))<=Parâmetros!$B$25,0,IF(MAX(0,S26-(MIN(S26,Parâmetros!$B$8)*Parâmetros!$B$7)-(IF(Parâmetros!$B$15=1,0,Parâmetros!$B$14)*Parâmetros!$B$10))<=Parâmetros!$B$26,MAX(0,S26-(MIN(S26,Parâmetros!$B$8)*Parâmetros!$B$7)-(IF(Parâmetros!$B$15=1,0,Parâmetros!$B$14)*Parâmetros!$B$10))*0.075-Parâmetros!$B$29,IF(MAX(0,S26-(MIN(S26,Parâmetros!$B$8)*Parâmetros!$B$7)-(IF(Parâmetros!$B$15=1,0,Parâmetros!$B$14)*Parâmetros!$B$10))<=Parâmetros!$B$27,MAX(0,S26-(MIN(S26,Parâmetros!$B$8)*Parâmetros!$B$7)-(IF(Parâmetros!$B$15=1,0,Parâmetros!$B$14)*Parâmetros!$B$10))*0.15-Parâmetros!$B$30,IF(MAX(0,S26-(MIN(S26,Parâmetros!$B$8)*Parâmetros!$B$7)-(IF(Parâmetros!$B$15=1,0,Parâmetros!$B$14)*Parâmetros!$B$10))<=Parâmetros!$B$28,MAX(0,S26-(MIN(S26,Parâmetros!$B$8)*Parâmetros!$B$7)-(IF(Parâmetros!$B$15=1,0,Parâmetros!$B$14)*Parâmetros!$B$10))*0.225-Parâmetros!$B$31,MAX(0,S26-(MIN(S26,Parâmetros!$B$8)*Parâmetros!$B$7)-(IF(Parâmetros!$B$15=1,0,Parâmetros!$B$14)*Parâmetros!$B$10))*0.275-Parâmetros!$B$32)))))-IF(S26<=Parâmetros!$B$34,Parâmetros!$B$35-Parâmetros!$B$36*S26,0))) | Y26: =MAX(0,B26-V26-S26) | Z26: =B26-V26-W26-X26
A27: 46327 | B27: =Notas!G28 | C27: =Parâmetros!$B$19 | D27: =IF(SUM(B16:B27)=0,0,SUM(C16:C27)/SUM(B16:B27)) | E27: =IF(D27>=Parâmetros!$B$6,"III","V") | F27: =IF(E27="III",B27*Parâmetros!$B$4,B27*Parâmetros!$B$5) | G27: =MIN(C27,Parâmetros!$B$8)*Parâmetros!$B$7 | H27: =IF(C27<=Parâmetros!$B$33,0,MAX(0,(IF(MAX(0,C27-(MIN(C27,Parâmetros!$B$8)*Parâmetros!$B$7)-(IF(Parâmetros!$B$15=1,0,Parâmetros!$B$14)*Parâmetros!$B$10))<=Parâmetros!$B$25,0,IF(MAX(0,C27-(MIN(C27,Parâmetros!$B$8)*Parâmetros!$B$7)-(IF(Parâmetros!$B$15=1,0,Parâmetros!$B$14)*Parâmetros!$B$10))<=Parâmetros!$B$26,MAX(0,C27-(MIN(C27,Parâmetros!$B$8)*Parâmetros!$B$7)-(IF(Parâmetros!$B$15=1,0,Parâmetros!$B$14)*Parâmetros!$B$10))*0.075-Parâmetros!$B$29,IF(MAX(0,C27-(MIN(C27,Parâmetros!$B$8)*Parâmetros!$B$7)-(IF(Parâmetros!$B$15=1,0,Parâmetros!$B$14)*Parâmetros!$B$10))<=Parâmetros!$B$27,MAX(0,C27-(MIN(C27,Parâmetros!$B$8)*Parâmetros!$B$7)-(IF(Parâmetros!$B$15=1,0,Parâmetros!$B$14)*Parâmetros!$B$10))*0.15-Parâmetros!$B$30,IF(MAX(0,C27-(MIN(C27,Parâmetros!$B$8)*Parâmetros!$B$7)-(IF(Parâmetros!$B$15=1,0,Parâmetros!$B$14)*Parâmetros!$B$10))<=Parâmetros!$B$28,MAX(0,C27-(MIN(C27,Parâmetros!$B$8)*Parâmetros!$B$7)-(IF(Parâmetros!$B$15=1,0,Parâmetros!$B$14)*Parâmetros!$B$10))*0.225-Parâmetros!$B$31,MAX(0,C27-(MIN(C27,Parâmetros!$B$8)*Parâmetros!$B$7)-(IF(Parâmetros!$B$15=1,0,Parâmetros!$B$14)*Parâmetros!$B$10))*0.275-Parâmetros!$B$32)))))-IF(C27<=Parâmetros!$B$34,Parâmetros!$B$35-Parâmetros!$B$36*C27,0))) | I27: =MAX(0,B27-F27-C27) | J27: =B27-F27-G27-H27 | K27: =IF(A27<Parâmetros!$B$23,Parâmetros!$B$19,MAX(Parâmetros!$B$22,Parâmetros!$B$6*SUM(B16:B27)-SUM(K16:K26))) | L27: =IF(SUM(B16:B27)=0,0,SUM(K16:K27)/SUM(B16:B27)) | M27: =IF(L27>=Parâmetros!$B$6,"III","V") | N27: =IF(M27="III",B27*Parâmetros!$B$4,B27*Parâmetros!$B$5) | O27: =MIN(K27,Parâmetros!$B$8)*Parâmetros!$B$7 | P27: =IF(K27<=Parâmetros!$B$33,0,MAX(0,(IF(MAX(0,K27-(MIN(K27,Parâmetros!$B$8)*Parâmetros!$B$7)-(IF(Parâmetros!$B$15=1,0,Parâmetros!$B$14)*Parâmetros!$B$10))<=Parâmetros!$B$25,0,IF(MAX(0,K27-(MIN(K27,Parâmetros!$B$8)*Parâmetros!$B$7)-(IF(Parâmetros!$B$15=1,0,Parâmetros!$B$14)*Parâmetros!$B$10))<=Parâmetros!$B$26,MAX(0,K27-(MIN(K27,Parâmetros!$B$8)*Parâmetros!$B$7)-(IF(Parâmetros!$B$15=1,0,Parâmetros!$B$14)*Parâmetros!$B$10))*0.075-Parâmetros!$B$29,IF(MAX(0,K27-(MIN(K27,Parâmetros!$B$8)*Parâmetros!$B$7)-(IF(Parâmetros!$B$15=1,0,Parâmetros!$B$14)*Parâmetros!$B$10))<=Parâmetros!$B$27,MAX(0,K27-(MIN(K27,Parâmetros!$B$8)*Parâmetros!$B$7)-(IF(Parâmetros!$B$15=1,0,Parâmetros!$B$14)*Parâmetros!$B$10))*0.15-Parâmetros!$B$30,IF(MAX(0,K27-(MIN(K27,Parâmetros!$B$8)*Parâmetros!$B$7)-(IF(Parâmetros!$B$15=1,0,Parâmetros!$B$14)*Parâmetros!$B$10))<=Parâmetros!$B$28,MAX(0,K27-(MIN(K27,Parâmetros!$B$8)*Parâmetros!$B$7)-(IF(Parâmetros!$B$15=1,0,Parâmetros!$B$14)*Parâmetros!$B$10))*0.225-Parâmetros!$B$31,MAX(0,K27-(MIN(K27,Parâmetros!$B$8)*Parâmetros!$B$7)-(IF(Parâmetros!$B$15=1,0,Parâmetros!$B$14)*Parâmetros!$B$10))*0.275-Parâmetros!$B$32)))))-IF(K27<=Parâmetros!$B$34,Parâmetros!$B$35-Parâmetros!$B$36*K27,0))) | Q27: =MAX(0,B27-N27-K27) | R27: =B27-N27-O27-P27 | S27: =Parâmetros!$B$21 | T27: =IF(SUM(B16:B27)=0,0,SUM(S16:S27)/SUM(B16:B27)) | U27: =IF(T27>=Parâmetros!$B$6,"III","V") | V27: =IF(U27="III",B27*Parâmetros!$B$4,B27*Parâmetros!$B$5) | W27: =MIN(S27,Parâmetros!$B$8)*Parâmetros!$B$7 | X27: =IF(S27<=Parâmetros!$B$33,0,MAX(0,(IF(MAX(0,S27-(MIN(S27,Parâmetros!$B$8)*Parâmetros!$B$7)-(IF(Parâmetros!$B$15=1,0,Parâmetros!$B$14)*Parâmetros!$B$10))<=Parâmetros!$B$25,0,IF(MAX(0,S27-(MIN(S27,Parâmetros!$B$8)*Parâmetros!$B$7)-(IF(Parâmetros!$B$15=1,0,Parâmetros!$B$14)*Parâmetros!$B$10))<=Parâmetros!$B$26,MAX(0,S27-(MIN(S27,Parâmetros!$B$8)*Parâmetros!$B$7)-(IF(Parâmetros!$B$15=1,0,Parâmetros!$B$14)*Parâmetros!$B$10))*0.075-Parâmetros!$B$29,IF(MAX(0,S27-(MIN(S27,Parâmetros!$B$8)*Parâmetros!$B$7)-(IF(Parâmetros!$B$15=1,0,Parâmetros!$B$14)*Parâmetros!$B$10))<=Parâmetros!$B$27,MAX(0,S27-(MIN(S27,Parâmetros!$B$8)*Parâmetros!$B$7)-(IF(Parâmetros!$B$15=1,0,Parâmetros!$B$14)*Parâmetros!$B$10))*0.15-Parâmetros!$B$30,IF(MAX(0,S27-(MIN(S27,Parâmetros!$B$8)*Parâmetros!$B$7)-(IF(Parâmetros!$B$15=1,0,Parâmetros!$B$14)*Parâmetros!$B$10))<=Parâmetros!$B$28,MAX(0,S27-(MIN(S27,Parâmetros!$B$8)*Parâmetros!$B$7)-(IF(Parâmetros!$B$15=1,0,Parâmetros!$B$14)*Parâmetros!$B$10))*0.225-Parâmetros!$B$31,MAX(0,S27-(MIN(S27,Parâmetros!$B$8)*Parâmetros!$B$7)-(IF(Parâmetros!$B$15=1,0,Parâmetros!$B$14)*Parâmetros!$B$10))*0.275-Parâmetros!$B$32)))))-IF(S27<=Parâmetros!$B$34,Parâmetros!$B$35-Parâmetros!$B$36*S27,0))) | Y27: =MAX(0,B27-V27-S27) | Z27: =B27-V27-W27-X27
... A40: 46722 | B40: =Notas!G41 | C40: =Parâmetros!$B$19 | D40: =IF(SUM(B29:B40)=0,0,SUM(C29:C40)/SUM(B29:B40)) | E40: =IF(D40>=Parâmetros!$B$6,"III","V") | F40: =IF(E40="III",B40*Parâmetros!$B$4,B40*Parâmetros!$B$5) | G40: =MIN(C40,Parâmetros!$B$8)*Parâmetros!$B$7 | H40: =IF(C40<=Parâmetros!$B$33,0,MAX(0,(IF(MAX(0,C40-(MIN(C40,Parâmetros!$B$8)*Parâmetros!$B$7)-(IF(Parâmetros!$B$15=1,0,Parâmetros!$B$14)*Parâmetros!$B$10))<=Parâmetros!$B$25,0,IF(MAX(0,C40-(MIN(C40,Parâmetros!$B$8)*Parâmetros!$B$7)-(IF(Parâmetros!$B$15=1,0,Parâmetros!$B$14)*Parâmetros!$B$10))<=Parâmetros!$B$26,MAX(0,C40-(MIN(C40,Parâmetros!$B$8)*Parâmetros!$B$7)-(IF(Parâmetros!$B$15=1,0,Parâmetros!$B$14)*Parâmetros!$B$10))*0.075-Parâmetros!$B$29,IF(MAX(0,C40-(MIN(C40,Parâmetros!$B$8)*Parâmetros!$B$7)-(IF(Parâmetros!$B$15=1,0,Parâmetros!$B$14)*Parâmetros!$B$10))<=Parâmetros!$B$27,MAX(0,C40-(MIN(C40,Parâmetros!$B$8)*Parâmetros!$B$7)-(IF(Parâmetros!$B$15=1,0,Parâmetros!$B$14)*Parâmetros!$B$10))*0.15-Parâmetros!$B$30,IF(MAX(0,C40-(MIN(C40,Parâmetros!$B$8)*Parâmetros!$B$7)-(IF(Parâmetros!$B$15=1,0,Parâmetros!$B$14)*Parâmetros!$B$10))<=Parâmetros!$B$28,MAX(0,C40-(MIN(C40,Parâmetros!$B$8)*Parâmetros!$B$7)-(IF(Parâmetros!$B$15=1,0,Parâmetros!$B$14)*Parâmetros!$B$10))*0.225-Parâmetros!$B$31,MAX(0,C40-(MIN(C40,Parâmetros!$B$8)*Parâmetros!$B$7)-(IF(Parâmetros!$B$15=1,0,Parâmetros!$B$14)*Parâmetros!$B$10))*0.275-Parâmetros!$B$32)))))-IF(C40<=Parâmetros!$B$34,Parâmetros!$B$35-Parâmetros!$B$36*C40,0))) | I40: =MAX(0,B40-F40-C40) | J40: =B40-F40-G40-H40 | K40: =IF(A40<Parâmetros!$B$23,Parâmetros!$B$19,MAX(Parâmetros!$B$22,Parâmetros!$B$6*SUM(B29:B40)-SUM(K29:K39))) | L40: =IF(SUM(B29:B40)=0,0,SUM(K29:K40)/SUM(B29:B40)) | M40: =IF(L40>=Parâmetros!$B$6,"III","V") | N40: =IF(M40="III",B40*Parâmetros!$B$4,B40*Parâmetros!$B$5) | O40: =MIN(K40,Parâmetros!$B$8)*Parâmetros!$B$7 | P40: =IF(K40<=Parâmetros!$B$33,0,MAX(0,(IF(MAX(0,K40-(MIN(K40,Parâmetros!$B$8)*Parâmetros!$B$7)-(IF(Parâmetros!$B$15=1,0,Parâmetros!$B$14)*Parâmetros!$B$10))<=Parâmetros!$B$25,0,IF(MAX(0,K40-(MIN(K40,Parâmetros!$B$8)*Parâmetros!$B$7)-(IF(Parâmetros!$B$15=1,0,Parâmetros!$B$14)*Parâmetros!$B$10))<=Parâmetros!$B$26,MAX(0,K40-(MIN(K40,Parâmetros!$B$8)*Parâmetros!$B$7)-(IF(Parâmetros!$B$15=1,0,Parâmetros!$B$14)*Parâmetros!$B$10))*0.075-Parâmetros!$B$29,IF(MAX(0,K40-(MIN(K40,Parâmetros!$B$8)*Parâmetros!$B$7)-(IF(Parâmetros!$B$15=1,0,Parâmetros!$B$14)*Parâmetros!$B$10))<=Parâmetros!$B$27,MAX(0,K40-(MIN(K40,Parâmetros!$B$8)*Parâmetros!$B$7)-(IF(Parâmetros!$B$15=1,0,Parâmetros!$B$14)*Parâmetros!$B$10))*0.15-Parâmetros!$B$30,IF(MAX(0,K40-(MIN(K40,Parâmetros!$B$8)*Parâmetros!$B$7)-(IF(Parâmetros!$B$15=1,0,Parâmetros!$B$14)*Parâmetros!$B$10))<=Parâmetros!$B$28,MAX(0,K40-(MIN(K40,Parâmetros!$B$8)*Parâmetros!$B$7)-(IF(Parâmetros!$B$15=1,0,Parâmetros!$B$14)*Parâmetros!$B$10))*0.225-Parâmetros!$B$31,MAX(0,K40-(MIN(K40,Parâmetros!$B$8)*Parâmetros!$B$7)-(IF(Parâmetros!$B$15=1,0,Parâmetros!$B$14)*Parâmetros!$B$10))*0.275-Parâmetros!$B$32)))))-IF(K40<=Parâmetros!$B$34,Parâmetros!$B$35-Parâmetros!$B$36*K40,0))) | Q40: =MAX(0,B40-N40-K40) | R40: =B40-N40-O40-P40 | S40: =Parâmetros!$B$21 | T40: =IF(SUM(B29:B40)=0,0,SUM(S29:S40)/SUM(B29:B40)) | U40: =IF(T40>=Parâmetros!$B$6,"III","V") | V40: =IF(U40="III",B40*Parâmetros!$B$4,B40*Parâmetros!$B$5) | W40: =MIN(S40,Parâmetros!$B$8)*Parâmetros!$B$7 | X40: =IF(S40<=Parâmetros!$B$33,0,MAX(0,(IF(MAX(0,S40-(MIN(S40,Parâmetros!$B$8)*Parâmetros!$B$7)-(IF(Parâmetros!$B$15=1,0,Parâmetros!$B$14)*Parâmetros!$B$10))<=Parâmetros!$B$25,0,IF(MAX(0,S40-(MIN(S40,Parâmetros!$B$8)*Parâmetros!$B$7)-(IF(Parâmetros!$B$15=1,0,Parâmetros!$B$14)*Parâmetros!$B$10))<=Parâmetros!$B$26,MAX(0,S40-(MIN(S40,Parâmetros!$B$8)*Parâmetros!$B$7)-(IF(Parâmetros!$B$15=1,0,Parâmetros!$B$14)*Parâmetros!$B$10))*0.075-Parâmetros!$B$29,IF(MAX(0,S40-(MIN(S40,Parâmetros!$B$8)*Parâmetros!$B$7)-(IF(Parâmetros!$B$15=1,0,Parâmetros!$B$14)*Parâmetros!$B$10))<=Parâmetros!$B$27,MAX(0,S40-(MIN(S40,Parâmetros!$B$8)*Parâmetros!$B$7)-(IF(Parâmetros!$B$15=1,0,Parâmetros!$B$14)*Parâmetros!$B$10))*0.15-Parâmetros!$B$30,IF(MAX(0,S40-(MIN(S40,Parâmetros!$B$8)*Parâmetros!$B$7)-(IF(Parâmetros!$B$15=1,0,Parâmetros!$B$14)*Parâmetros!$B$10))<=Parâmetros!$B$28,MAX(0,S40-(MIN(S40,Parâmetros!$B$8)*Parâmetros!$B$7)-(IF(Parâmetros!$B$15=1,0,Parâmetros!$B$14)*Parâmetros!$B$10))*0.225-Parâmetros!$B$31,MAX(0,S40-(MIN(S40,Parâmetros!$B$8)*Parâmetros!$B$7)-(IF(Parâmetros!$B$15=1,0,Parâmetros!$B$14)*Parâmetros!$B$10))*0.275-Parâmetros!$B$32)))))-IF(S40<=Parâmetros!$B$34,Parâmetros!$B$35-Parâmetros!$B$36*S40,0))) | Y40: =MAX(0,B40-V40-S40) | Z40: =B40-V40-W40-X40
A42: * Lucro isento (estimativa) = Receita − DAS − Pró-labore. Não considera outras despesas da empresa. Distribuição depende de lucro contábil real.
A43: ** Líquido familiar (lado PJ) = Receita − DAS − INSS pró-labore − IRRF pró-labore. Pró-labore e lucro ficam na família; só saem impostos. CLT é adicional (veja Comparativo).

Sheet Comparativo
A1: Comparativo anual dos cenários
A2: Totais agregados. Ano-calendário selecionável abaixo (impacta IR 2027 = ano 2026).
A4: Ano para consolidar | B4: 2026 | C4: ← altere para 2025, 2026 ou 2027
A6: Indicador | B6: C1 — Atual | C6: C2 — Automático Fator R | D6: C3 — Manual
A7: Receita bruta PJ | B7: =SUMPRODUCT((YEAR(Simulação!$A$5:$A$40)=B4)*(Simulação!B$5:B$40)) | C7: =SUMPRODUCT((YEAR(Simulação!$A$5:$A$40)=B4)*(Simulação!B$5:B$40)) | D7: =SUMPRODUCT((YEAR(Simulação!$A$5:$A$40)=B4)*(Simulação!B$5:B$40))
A8: Pró-labore total | B8: =SUMPRODUCT((YEAR(Simulação!$A$5:$A$40)=B4)*(Simulação!C$5:C$40)) | C8: =SUMPRODUCT((YEAR(Simulação!$A$5:$A$40)=B4)*(Simulação!K$5:K$40)) | D8: =SUMPRODUCT((YEAR(Simulação!$A$5:$A$40)=B4)*(Simulação!S$5:S$40))
A9: DAS total | B9: =SUMPRODUCT((YEAR(Simulação!$A$5:$A$40)=B4)*(Simulação!F$5:F$40)) | C9: =SUMPRODUCT((YEAR(Simulação!$A$5:$A$40)=B4)*(Simulação!N$5:N$40)) | D9: =SUMPRODUCT((YEAR(Simulação!$A$5:$A$40)=B4)*(Simulação!V$5:V$40))
A10: INSS pró-labore | B10: =SUMPRODUCT((YEAR(Simulação!$A$5:$A$40)=B4)*(Simulação!G$5:G$40)) | C10: =SUMPRODUCT((YEAR(Simulação!$A$5:$A$40)=B4)*(Simulação!O$5:O$40)) | D10: =SUMPRODUCT((YEAR(Simulação!$A$5:$A$40)=B4)*(Simulação!W$5:W$40))
A11: IRRF pró-labore | B11: =SUMPRODUCT((YEAR(Simulação!$A$5:$A$40)=B4)*(Simulação!H$5:H$40)) | C11: =SUMPRODUCT((YEAR(Simulação!$A$5:$A$40)=B4)*(Simulação!P$5:P$40)) | D11: =SUMPRODUCT((YEAR(Simulação!$A$5:$A$40)=B4)*(Simulação!X$5:X$40))
A12: Total impostos PJ+pró-labore | B12: =B9+B10+B11 | C12: =C9+C10+C11 | D12: =D9+D10+D11
A13: Lucro isento estimado | B13: =SUMPRODUCT((YEAR(Simulação!$A$5:$A$40)=B4)*(Simulação!I$5:I$40)) | C13: =SUMPRODUCT((YEAR(Simulação!$A$5:$A$40)=B4)*(Simulação!Q$5:Q$40)) | D13: =SUMPRODUCT((YEAR(Simulação!$A$5:$A$40)=B4)*(Simulação!Y$5:Y$40))
A14: Líquido familiar (lado PJ) | B14: =SUMPRODUCT((YEAR(Simulação!$A$5:$A$40)=B4)*(Simulação!J$5:J$40)) | C14: =SUMPRODUCT((YEAR(Simulação!$A$5:$A$40)=B4)*(Simulação!R$5:R$40)) | D14: =SUMPRODUCT((YEAR(Simulação!$A$5:$A$40)=B4)*(Simulação!Z$5:Z$40))
A16: Melhor cenário (menor total de impostos) | B16: =IF(AND(B12<=C12,B12<=D12),"C1",IF(C12<=D12,"C2","C3")) | C16: Economia de C2 vs C1 | D16: =B12-C12
A18: CLT (você) — referência para IRPF
A19: Meses trabalhados no ano | B19: =Parâmetros!B16
A20: CLT bruto no ano (sem 13º) | B20: =Parâmetros!B13*Parâmetros!B16
A21: 13º estimado | B21: =Parâmetros!B13
A22: CLT bruto total ano (c/ 13º) | B22: =B20+B21
A24: IRPF 2027 (ano-calendário da célula B4)
A25: Rendimentos tributáveis família (aprox.)
A26: — CLT (você) | B26: =B22
A27: — Pró-labore (esposa) no cenário C2 | B27: =C8
A28: — Lucros distribuídos (isentos, C2) | B28: =C13
A29: Obs.: cada cônjuge declara em separado. Lucros isentos vão na ficha de rendimentos isentos dela (ou do sócio titular).
A31: Checklist com o contador
A32: □ Confirmar RBT12 e folha 12 meses no PGDAS-D
A33: □ Definir pró-labore do mês (usar coluna C2 da Simulação como piso)
A34: □ Emitir guias: DAS + INSS código 1099 do pró-labore
A35: □ Registrar distribuição de lucros com base no balancete
A36: □ Informar dependentes no empregador CLT (você)
A37: □ Guardar NFs, DAS, holérides e informes para DIRPF 2027
A40: Empresas cadastradas na aba Notas
A41: Empresa 1 | B41: =Notas!B5
A42: Empresa 2 | B42: =Notas!C5
A43: Empresa 3 | B43: =Notas!D5
A44: Empresa 4 | B44: =Notas!E5
A45: Empresa 5 | B45: =Notas!F5

Sheet Composição DAS
A1: Composição estimada do DAS (proporcional ao seu documento de 07/2026)
A2: Usa o rateio do seu DAS de R$ 930 sobre R$ 15.500. É aproximação — o PGDAS oficial pode variar centavos/faixa.
A4: Receita do mês (escolher) | B4: 26000
A5: Anexo aplicado | B5: III
A6: DAS estimado | B6: =IF(B5="III",B4*Parâmetros!B4,B4*Parâmetros!B5)
A8: Tributo | B8: Partilha no DAS atual | C8: % do DAS | D8: Valor estimado no mês
A9: IRPJ (1001) | B9: 37.2 | C9: =B9/SUM($B$9:$B$14) | D9: =$B$6*C9
A10: CSLL (1002) | B10: 32.55 | C10: =B10/SUM($B$9:$B$14) | D10: =$B$6*C10
A11: COFINS (1004) | B11: 119.23 | C11: =B11/SUM($B$9:$B$14) | D11: =$B$6*C11
A12: PIS/Pasep (1005) | B12: 25.85 | C12: =B12/SUM($B$9:$B$14) | D12: =$B$6*C12
A13: INSS patronal no DAS (1006) | B13: 403.62 | C13: =B13/SUM($B$9:$B$14) | D13: =$B$6*C13
A14: ISS Brasília-DF (1010) | B14: 311.55 | C14: =B14/SUM($B$9:$B$14) | D14: =$B$6*C14
A16: Total | D16: =SUM(D9:D14)
A18: INSS do pró-labore (guia separada — código 1099)
A19: Pró-labore do mês | B19: 7280
A20: INSS 11% (código 1099) | B20: =MIN(B19,Parâmetros!B8)*Parâmetros!B7
A21: IRRF pró-labore estimado | B21: =IF(B19<=Parâmetros!$B$33,0,MAX(0,(IF(MAX(0,B19-(MIN(B19,Parâmetros!$B$8)*Parâmetros!$B$7)-(IF(Parâmetros!$B$15=1,0,Parâmetros!$B$14)*Parâmetros!$B$10))<=Parâmetros!$B$25,0,IF(MAX(0,B19-(MIN(B19,Parâmetros!$B$8)*Parâmetros!$B$7)-(IF(Parâmetros!$B$15=1,0,Parâmetros!$B$14)*Parâmetros!$B$10))<=Parâmetros!$B$26,MAX(0,B19-(MIN(B19,Parâmetros!$B$8)*Parâmetros!$B$7)-(IF(Parâmetros!$B$15=1,0,Parâmetros!$B$14)*Parâmetros!$B$10))*0.075-Parâmetros!$B$29,IF(MAX(0,B19-(MIN(B19,Parâmetros!$B$8)*Parâmetros!$B$7)-(IF(Parâmetros!$B$15=1,0,Parâmetros!$B$14)*Parâmetros!$B$10))<=Parâmetros!$B$27,MAX(0,B19-(MIN(B19,Parâmetros!$B$8)*Parâmetros!$B$7)-(IF(Parâmetros!$B$15=1,0,Parâmetros!$B$14)*Parâmetros!$B$10))*0.15-Parâmetros!$B$30,IF(MAX(0,B19-(MIN(B19,Parâmetros!$B$8)*Parâmetros!$B$7)-(IF(Parâmetros!$B$15=1,0,Parâmetros!$B$14)*Parâmetros!$B$10))<=Parâmetros!$B$28,MAX(0,B19-(MIN(B19,Parâmetros!$B$8)*Parâmetros!$B$7)-(IF(Parâmetros!$B$15=1,0,Parâmetros!$B$14)*Parâmetros!$B$10))*0.225-Parâmetros!$B$31,MAX(0,B19-(MIN(B19,Parâmetros!$B$8)*Parâmetros!$B$7)-(IF(Parâmetros!$B$15=1,0,Parâmetros!$B$14)*Parâmetros!$B$10))*0.275-Parâmetros!$B$32)))))-IF(B19<=Parâmetros!$B$34,Parâmetros!$B$35-Parâmetros!$B$36*B19,0)))
